Workbook

Sheet Guide
A1: OPERF / TPG PARTNERS VI — GP/LP COMPENSATION MODEL
A2: Case: "Oregon Public Employees Retirement Fund: Push and Pull Over GP/LP Compensation" (Darden UV5622). Preparation Questions 3–6.
A3: Built on the layout of the Template sheet in the supplementary spreadsheet (UV5624-XLS-ENG.xlsx). $ millions unless stated.
A5: Model status
A6: Integrity checks | C6: =IF(AND('Q3 Base case'!$C$72="OK",'Q4 Fee cut'!$C$72="OK",'Q5a Hard hurdle'!$C$72="OK",'Q5b Soft hurdle'!$C$72="OK",'Q5c Lower carry'!$C$72="OK",Engine!$U$177=0,SUM(Summary!$B$36:$F$36)=0,'Q4 Analysis'!$C$26=0),"ALL CHECKS OK","CHECK THE MODEL") -> ALL CHECKS OK
A7: Base-case LP net IRR | C7: =Summary!$B$11 -> 0.15722559
A8: LP IRR with TPG offer | C8: =Summary!$C$11 -> 0.15936141
A10: Sheet map
A11: Sheet | B11: Prep question | C11: What it shows | D11: Presenter
A12: Inputs | B12: All | C12: Every assumption in one place (blue cells). Change here only. | D12: Shared
A13: Summary | B13: Q3–Q5 | C13: All scenarios side by side for LPs, TPG and OPERF, plus two charts and auto-updating talking points. | D13: Shared
A14: Q1-Q2 Context | B14: Q1–Q2 | C14: Case facts for the motivation and fee-vs-carry slides: what the offer costs TPG, fundraising and IPO data, LP sentiment, pay mix. | D14: Li (Parts 2–3)
A15: Q3 Base case | B15: Q3 | C15: Template model: current terms (1.50% fee, 20% carry). Year-by-year assets, waterfall, cash flows, IRR/NPV. | D15: Alex (Part 4)
A16: Q3 Analysis | B16: Q3 | C16: Gross-to-net bridge, who captures the value, fixed vs performance pay, fee growth with fund size. | D16: Alex (Part 4)
A17: Q4 Fee cut | B17: Q4 | C17: Template model with the 1.35% fee. | D17: Alex (Part 4)
A18: Q4 Analysis | B18: Q4 | C18: Fee cut vs current terms for the fund and for OPERF; fee saving vs extra carry; gain across outcomes. | D18: Alex (Part 4)
A19: Q5a Hard hurdle | B19: Q5 | C19: Template model: TPG offer + 8% preferred return, no catch-up. | D19: Jimmy (Part 5)
A20: Q5b Soft hurdle | B20: Q5 | C20: Template model: TPG offer + 8% preferred return with 100% GP catch-up. | D20: Jimmy (Part 5)
A21: Q5c Lower carry | B21: Q5 | C21: Template model: TPG offer + 15% carry. | D21: Jimmy (Part 5)
A22: Q5 Analysis | B22: Q5 | C22: Hurdle vs carry cut: base-case value, fee-equivalent, downside protection, carry earned in weak outcomes. | D22: Jimmy (Part 5)
... A25: Engine | B25: — | C25: Same model in one row per scenario (feeds the sensitivity tables). Reconciled to the template sheets. | D25: —
A27: Modelling conventions
A28: 1. | B28: Fund: $20bn committed, drawn in five equal 20% instalments at the start of Years 1–5 (Prep Q3).
A29: 2. | B29: Management fee = fee rate × committed capital, paid at the start of every year (Years 1–10) out of drawn capital / fund assets, exactly as the template does: Assets + Takedown − Fee = Invested capital.
A30: 3. | B30: Invested capital grows 20% during the year. From the end of Year 5, 20% of NAV is distributed each year; everything left is liquidated at the end of Year 10.
A31: 4. | B31: Whole-fund waterfall: (1) LPs get back all contributed capital, including the part used for fees; (2) preferred return, if any; (3) GP catch-up, soft hurdle only; (4) the rest split 80/20 (or 85/15).
A32: 5. | B32: Hurdle = 8% a year compounded on unreturned capital and unpaid preferred return, i.e. LPs must earn an 8% IRR before carry. Hard: carry only on profits above that. Soft: the GP takes 100% of distributions after the hurdle until it has 20% of all profits.
A33: 6. | B33: Timing: in the cash-flow rows each column is a point in time t; the start of Year n is t = n − 1. IRR and NPV use LP net cash flows; GP PV uses fees (start of year) and carry (end of year), all at 15%.
A34: 7. | B34: TPG's own ~$500m commitment is ignored (all capital is treated as LP capital). OPERF gets 750 ÷ 20,000 = 3.75% of LP cash flows.
A35: 8. | B35: TPG's 30% cap on 2009 capital calls is not binding in this model (draws are 20% a year).
A37: Colour code
A38: Input | B38: Blue text = hardcoded input (yellow fill = key lever)
A39: Formula | B39: Black text = calculation on the same sheet
A40: Link | B40: Green text = pulled from another sheet
A41: Section header | B41: Red bold italic = section header (template style)

Sheet Inputs
A1: MODEL INPUTS — OPERF / TPG PARTNERS VI
A2: Change blue cells here; every scenario sheet, table and chart updates. Yellow = the key levers for Q3–Q6.
A3: Colour code: blue = input · black = formula · green = linked from another sheet · red italic = section header (as in the Darden template)
A5: Fund assumptions (Preparation Question 3)
A6: Committed capital ($ millions) | C6: 20000 | D6: Prep Q3 assumption (case: TPG VI final close was $19.8bn)
A7: Fund life (years) | C7: =COLUMNS(C13:L13) -> 10 | D7: Model is built for a 10-year life (fee charged in each year)
A8: Annual growth rate of invested assets | C8: 0.2 | D8: Prep Q3 assumption
A9: Discount rate for fund cash flows | C9: 0.15 | D9: Prep Q3 assumption
A11: Drawdown and distribution schedule
A12: Year | B12: 0 | C12: 1 | D12: 2 | E12: 3 | F12: 4 | G12: 5 | H12: 6 | I12: 7 | J12: 8 | K12: 9 | L12: 10
A13: % of committed capital drawn (start of year) | C13: 0.2 | D13: 0.2 | E13: 0.2 | F13: 0.2 | G13: 0.2 | H13: 0 | I13: 0 | J13: 0 | K13: 0 | L13: 0
A14: Distribution rate (% of NAV, end of year) | C14: 0 | D14: 0 | E14: 0 | F14: 0 | G14: 0.2 | H14: 0.2 | I14: 0.2 | J14: 0.2 | K14: 0.2 | L14: 1
A15: Check: total drawn (must be 100%) | C15: =SUM(C13:L13) -> 1 | D15: Prep Q3: five equal draws at the start of Years 1–5; 20% of the portfolio liquidated from end of Year 5; all remaining assets at end of Year 10
A17: GP compensation terms
A18: Current management fee (% of committed capital, paid annually in advance) | C18: 0.015 | D18: Prep Q3; case p.1
A19: TPG proposed management fee | C19: 0.0135 | D19: TPG letter, Dec 2008 (case p.1)
A20: Carried interest — current (GP share of profits) | C20: 0.2 | D20: Standard 80/20 split (case p.4)
A21: Carried interest — OPERF counter-proposal | C21: 0.15 | D21: Prep Q5
A22: Hurdle (preferred return) — OPERF counter-proposal | C22: 0.08 | D22: Prep Q5
A23: GP catch-up in the soft-hurdle variant (1 = 100% catch-up, 0 = none) | C23: 1 | D23: Modelling choice: typical buyout-fund term; the hard-hurdle variant uses no catch-up
A25: OPERF position (case data)
A26: OPERF commitment to TPG VI ($ millions) | C26: 750 | D26: Case p.1 and p.5; Exhibit 7
A27: Commitment reduction offered by TPG | C27: 0.1 | D27: Case p.1 ($75m for OPERF)
A28: TPG VI capital contributed by OPERF to date ($ millions) | C28: 79.9 | D28: Exhibit 7
A29: TPG VI distributions to OPERF to date ($ millions) | C29: 0.6 | D29: Exhibit 7
A30: TPG VI fair market value of OPERF stake ($ millions) | C30: 47.5 | D30: Exhibit 7
A31: Max share of commitment TPG may call in 2009 | C31: 0.3 | D31: Case p.1
A32: OPERF total fund value, Dec 2008 ($ millions) | C32: 45800 | D32: Case p.4
A33: OPERF private equity allocation, Dec 2008 ($ millions) | C33: 9800 | D33: Case p.4
A34: Private equity actual allocation, 4Q 2008 | C34: 0.219 | D34: Case p.5; Exhibit 9
A35: Private equity target allocation | C35: 0.16 | D35: Case p.5; Exhibit 9
A37: Sensitivity grid (used by the Engine and Sensitivity sheets)
A38: Asset growth grid — start | C38: 0
A39: Asset growth grid — step | C39: 0.01 | D39: Keep the step at 1% so the Q6 two-way table can look up growth rates such as 18% or 22%
A40: Asset growth grid — end (31 points, fixed) | C40: =C38+30*C39 -> 0.3

Sheet Summary
A1: SCENARIO SUMMARY — what each set of terms means for LPs, TPG and OPERF
A2: Whole-fund figures in $ millions; LP = all limited partners together. Each column links to its template-style scenario sheet.
A4: Metric | B4: Current terms (Q3 base case) | C4: TPG offer (Q4: fee 1.35%) | D4: Offer + 8% hard hurdle (Q5a) | E4: Offer + 8% soft hurdle (Q5b) | F4: Offer + 15% carry (Q5c)
A5: Management fee (% of committed capital) | B5: ='Q3 Base case'!$C$3 -> 0.015 | C5: ='Q4 Fee cut'!$C$3 -> 0.0135 | D5: ='Q5a Hard hurdle'!$C$3 -> 0.0135 | E5: ='Q5b Soft hurdle'!$C$3 -> 0.0135 | F5: ='Q5c Lower carry'!$C$3 -> 0.0135
A6: Carried interest (GP share of profit) | B6: ='Q3 Base case'!$F$4 -> 0.2 | C6: ='Q4 Fee cut'!$F$4 -> 0.2 | D6: ='Q5a Hard hurdle'!$F$4 -> 0.2 | E6: ='Q5b Soft hurdle'!$F$4 -> 0.2 | F6: ='Q5c Lower carry'!$F$4 -> 0.15
A7: Hurdle rate | B7: ='Q3 Base case'!$I$2 -> 0 | C7: ='Q4 Fee cut'!$I$2 -> 0 | D7: ='Q5a Hard hurdle'!$I$2 -> 0.08 | E7: ='Q5b Soft hurdle'!$I$2 -> 0.08 | F7: ='Q5c Lower carry'!$I$2 -> 0
A8: GP catch-up | B8: =IF('Q3 Base case'!$I$2=0,"n/a",IF('Q3 Base case'!$I$3=1,"Yes","No")) -> n/a | C8: =IF('Q4 Fee cut'!$I$2=0,"n/a",IF('Q4 Fee cut'!$I$3=1,"Yes","No")) -> n/a | D8: =IF('Q5a Hard hurdle'!$I$2=0,"n/a",IF('Q5a Hard hurdle'!$I$3=1,"Yes","No")) -> No | E8: =IF('Q5b Soft hurdle'!$I$2=0,"n/a",IF('Q5b Soft hurdle'!$I$3=1,"Yes","No")) -> Yes | F8: =IF('Q5c Lower carry'!$I$2=0,"n/a",IF('Q5c Lower carry'!$I$3=1,"Yes","No")) -> n/a
A10: Limited partners (whole fund)
A11: LP net IRR | B11: ='Q3 Base case'!$C$50 -> 0.15722559 | C11: ='Q4 Fee cut'!$C$50 -> 0.15936141 | D11: ='Q5a Hard hurdle'!$C$50 -> 0.16591822 | E11: ='Q5b Soft hurdle'!$C$50 -> 0.16029224 | F11: ='Q5c Lower carry'!$C$50 -> 0.16491098
A12: Change vs current terms | B12: =('Q3 Base case'!$C$50-$B$11)*10000 -> 0 | C12: =('Q4 Fee cut'!$C$50-$B$11)*10000 -> 21.358143 | D12: =('Q5a Hard hurdle'!$C$50-$B$11)*10000 -> 86.926301 | E12: =('Q5b Soft hurdle'!$C$50-$B$11)*10000 -> 30.666435 | F12: =('Q5c Lower carry'!$C$50-$B$11)*10000 -> 76.853883
A13: LP NPV at 15% ($m) | B13: ='Q3 Base case'!$C$51 -> 578.21714 | C13: ='Q4 Fee cut'!$C$51 -> 752.97923 | D13: ='Q5a Hard hurdle'!$C$51 -> 1303.5385 | E13: ='Q5b Soft hurdle'!$C$51 -> 825.66274 | F13: ='Q5c Lower carry'!$C$51 -> 1224.1241
A14: Change vs current terms ($m) | B14: ='Q3 Base case'!$C$51-$B$13 -> 0 | C14: ='Q4 Fee cut'!$C$51-$B$13 -> 174.76209 | D14: ='Q5a Hard hurdle'!$C$51-$B$13 -> 725.32133 | E14: ='Q5b Soft hurdle'!$C$51-$B$13 -> 247.4456 | F14: ='Q5c Lower carry'!$C$51-$B$13 -> 645.90701
A15: LP distributions, nominal ($m) | B15: ='Q3 Base case'!$C$53 -> 48070.521 | C15: ='Q4 Fee cut'!$C$53 -> 48631.388 | D15: ='Q5a Hard hurdle'!$C$53 -> 50426.835 | E15: ='Q5b Soft hurdle'!$C$53 -> 48631.388 | F15: ='Q5c Lower carry'!$C$53 -> 50420.85
A16: LP multiple of contributed capital (TVPI) | B16: ='Q3 Base case'!$C$54 -> 2.403526 | C16: ='Q4 Fee cut'!$C$54 -> 2.4315694 | D16: ='Q5a Hard hurdle'!$C$54 -> 2.5213418 | E16: ='Q5b Soft hurdle'!$C$54 -> 2.4315694 | F16: ='Q5c Lower carry'!$C$54 -> 2.5210425
A18: General partner — TPG
A19: Management fees, nominal ($m) | B19: ='Q3 Base case'!$C$55 -> 3000 | C19: ='Q4 Fee cut'!$C$55 -> 2700 | D19: ='Q5a Hard hurdle'!$C$55 -> 2700 | E19: ='Q5b Soft hurdle'!$C$55 -> 2700 | F19: ='Q5c Lower carry'!$C$55 -> 2700
A20: Carried interest, nominal ($m) | B20: ='Q3 Base case'!$C$56 -> 7017.6302 | C20: ='Q4 Fee cut'!$C$56 -> 7157.847 | D20: ='Q5a Hard hurdle'!$C$56 -> 5362.4 | E20: ='Q5b Soft hurdle'!$C$56 -> 7157.847 | F20: ='Q5c Lower carry'!$C$56 -> 5368.3853
A21: PV of management fees ($m) | B21: ='Q3 Base case'!$C$57 -> 1731.4752 | C21: ='Q4 Fee cut'!$C$57 -> 1558.3277 | D21: ='Q5a Hard hurdle'!$C$57 -> 1558.3277 | E21: ='Q5b Soft hurdle'!$C$57 -> 1558.3277 | F21: ='Q5c Lower carry'!$C$57 -> 1558.3277
A22: PV of carried interest ($m) | B22: ='Q3 Base case'!$C$58 -> 1845.4937 | C22: ='Q4 Fee cut'!$C$58 -> 1884.5797 | D22: ='Q5a Hard hurdle'!$C$58 -> 1334.0204 | E22: ='Q5b Soft hurdle'!$C$58 -> 1811.8962 | F22: ='Q5c Lower carry'!$C$58 -> 1413.4348
A23: PV of total GP compensation ($m) | B23: ='Q3 Base case'!$C$59 -> 3576.9689 | C23: ='Q4 Fee cut'!$C$59 -> 3442.9073 | D23: ='Q5a Hard hurdle'!$C$59 -> 2892.3481 | E23: ='Q5b Soft hurdle'!$C$59 -> 3370.2238 | F23: ='Q5c Lower carry'!$C$59 -> 2971.7624
A24: Change vs current terms ($m) | B24: ='Q3 Base case'!$C$59-$B$23 -> 0 | C24: ='Q4 Fee cut'!$C$59-$B$23 -> -134.06158 | D24: ='Q5a Hard hurdle'!$C$59-$B$23 -> -684.62082 | E24: ='Q5b Soft hurdle'!$C$59-$B$23 -> -206.74509 | F24: ='Q5c Lower carry'!$C$59-$B$23 -> -605.2065
A25: Fees as % of GP compensation (PV) | B25: ='Q3 Base case'!$C$60 -> 0.48406213 | C25: ='Q4 Fee cut'!$C$60 -> 0.45261969 | D25: ='Q5a Hard hurdle'!$C$60 -> 0.53877597 | E25: ='Q5b Soft hurdle'!$C$60 -> 0.46238106 | F25: ='Q5c Lower carry'!$C$60 -> 0.52437828
A26: First year GP receives carry | B26: ='Q3 Base case'!$C$62 -> 8 | C26: ='Q4 Fee cut'!$C$62 -> 8 | D26: ='Q5a Hard hurdle'!$C$62 -> 9 | E26: ='Q5b Soft hurdle'!$C$62 -> 9 | F26: ='Q5c Lower carry'!$C$62 -> 8
A28: ="OPERF ($"&TEXT(Inputs!$C$26,"#,##0")&"m commitment = "&TEXT('Q3 Base case'!$C$63,"0.00%")&" of the fund)" -> OPERF ($750m commitment = 3.75% of the fund)
A29: OPERF NPV at 15% ($m) | B29: ='Q3 Base case'!$C$64 -> 21.683143 | C29: ='Q4 Fee cut'!$C$64 -> 28.236721 | D29: ='Q5a Hard hurdle'!$C$64 -> 48.882693 | E29: ='Q5b Soft hurdle'!$C$64 -> 30.962353 | F29: ='Q5c Lower carry'!$C$64 -> 45.904656
A30: Change vs current terms ($m) | B30: ='Q3 Base case'!$C$64-$B$29 -> 0 | C30: ='Q4 Fee cut'!$C$64-$B$29 -> 6.5535783 | D30: ='Q5a Hard hurdle'!$C$64-$B$29 -> 27.19955 | E30: ='Q5b Soft hurdle'!$C$64-$B$29 -> 9.2792099 | F30: ='Q5c Lower carry'!$C$64-$B$29 -> 24.221513
A31: OPERF management fees paid, nominal ($m) | B31: ='Q3 Base case'!$C$65 -> 112.5 | C31: ='Q4 Fee cut'!$C$65 -> 101.25 | D31: ='Q5a Hard hurdle'!$C$65 -> 101.25 | E31: ='Q5b Soft hurdle'!$C$65 -> 101.25 | F31: ='Q5c Lower carry'!$C$65 -> 101.25
A32: OPERF distributions received, nominal ($m) | B32: ='Q3 Base case'!$C$66 -> 1802.6445 | C32: ='Q4 Fee cut'!$C$66 -> 1823.6771 | D32: ='Q5a Hard hurdle'!$C$66 -> 1891.0063 | E32: ='Q5b Soft hurdle'!$C$66 -> 1823.6771 | F32: ='Q5c Lower carry'!$C$66 -> 1890.7819
A34: Model integrity
A35: Scenario-sheet checks | B35: ='Q3 Base case'!$C$72 -> OK | C35: ='Q4 Fee cut'!$C$72 -> OK | D35: ='Q5a Hard hurdle'!$C$72 -> OK | E35: ='Q5b Soft hurdle'!$C$72 -> OK | F35: ='Q5c Lower carry'!$C$72 -> OK
A36: Difference vs Engine rows M1–M5 (0 = reconciles) | B36: =ROUND(ABS('Q3 Base case'!$C$50-Engine!$K$7)+ABS('Q3 Base case'!$C$51-Engine!$L$7)+ABS('Q3 Base case'!$C$59-Engine!$S$7),6) -> 0 | C36: =ROUND(ABS('Q4 Fee cut'!$C$50-Engine!$K$8)+ABS('Q4 Fee cut'!$C$51-Engine!$L$8)+ABS('Q4 Fee cut'!$C$59-Engine!$S$8),6) -> 0 | D36: =ROUND(ABS('Q5a Hard hurdle'!$C$50-Engine!$K$9)+ABS('Q5a Hard hurdle'!$C$51-Engine!$L$9)+ABS('Q5a Hard hurdle'!$C$59-Engine!$S$9),6) -> 0 | E36: =ROUND(ABS('Q5b Soft hurdle'!$C$50-Engine!$K$10)+ABS('Q5b Soft hurdle'!$C$51-Engine!$L$10)+ABS('Q5b Soft hurdle'!$C$59-Engine!$S$10),6) -> 0 | F36: =ROUND(ABS('Q5c Lower carry'!$C$50-Engine!$K$11)+ABS('Q5c Lower carry'!$C$51-Engine!$L$11)+ABS('Q5c Lower carry'!$C$59-Engine!$S$11),6) -> 0
A38: Talking points (text updates with the model)
A39: ="Base case: assets grow "&TEXT(Inputs!$C$8,"0%")&" a year but LPs net "&TEXT(B11,"0.0%")&" after fees and carry; NPV at 15% is only $"&TEXT(B13,"#,##0")&"m on a $"&TEXT(Inputs!$C$6,"#,##0")&"m fund." -> Base case: assets grow 20% a year but LPs net 15.7% after fees and carry; NPV at 15% is only $578m on a $20,000m fund.
A40: ="TPG earns $"&TEXT(B23,"#,##0")&"m in PV terms; "&TEXT(B25,"0%")&" of that is management fees, which are paid whatever the fund returns." -> TPG earns $3,577m in PV terms; 48% of that is management fees, which are paid whatever the fund returns.
A41: ="TPG's fee cut adds "&TEXT(C12,"0")&" bps to LP IRR (+$"&TEXT(C30,"0.0")&"m NPV for OPERF), a small gain, as Schmitz expected." -> TPG's fee cut adds 21 bps to LP IRR (+$6.6m NPV for OPERF), a small gain, as Schmitz expected.
A42: ="On top of the offer, an 8% hard hurdle adds "&TEXT(D12-C12,"0")&" bps and a 15% carry adds "&TEXT(F12-C12,"0")&" bps; a soft hurdle (with catch-up) adds only "&TEXT(E12-C12,"0")&" bps at 20% growth." -> On top of the offer, an 8% hard hurdle adds 66 bps and a 15% carry adds 55 bps; a soft hurdle (with catch-up) adds only 9 bps at 20% growth.

Sheet Q1-Q2 Context
A1: Q1–Q2 — WHY IS TPG OFFERING THIS, AND WHAT DO FEES AND CARRY DO?
A2: Case facts for Parts 2–3 (blue = case data with source; black = calculation; green = linked to the model). $ millions unless stated.
A4: A. What TPG's December 2008 offer costs TPG (per year unless stated)
A5: TPG VI committed capital, final close Sept 2008 | C5: 19800 | D5: Case p.1; Exhibit 1
A6: Management fee — current | C6: =Inputs!$C$18 -> 0.015
A7: Management fee — offered | C7: =Inputs!$C$19 -> 0.0135
A8: Annual fee at current rate | C8: =C5*C6 -> 297
A9: Annual fee at offered rate (nobody cuts) | C9: =C5*C7 -> 267.3
A10: Cost of the fee cut to TPG per year | C10: =C8-C9 -> 29.7
A11: Cost of the fee cut over the fund life | C11: =C10*Inputs!$C$7 -> 297
A12: Fund size if every LP takes the 10% cut | C12: =C5*(1-Inputs!$C$27) -> 17820
A13: Annual fee at offered rate on the smaller fund | C13: =C12*C7 -> 240.57
A14: Maximum annual fee reduction (fee cut + full take-up) | C14: =C8-C13 -> 56.43
A15: TPG firm-wide commitments under management ($m) | C15: 50000 | D15: Case p.2 ("approximately $50.0 billion")
A16: Illustrative firm-wide fee base at the current rate | C16: =C15*C6 -> 750 | D16: Assumes 1.50% on all funds — illustration only
A17: Maximum reduction as % of the illustrative firm-wide fee base | C17: =IF(C16=0,0,C14/C16) -> 0.07524
A18: Maximum 2009 capital calls fund-wide (30% cap) | C18: =C5*Inputs!$C$31 -> 5940 | D18: Case p.1 — without advisory committee approval
A19: Reading: the offer is cheap for TPG — a few percent of firm-wide fees — which supports the "goodwill / PR" reading; the 10% cut is small next to Permira's 60%.
A21: B. U.S. private equity fundraising (Exhibit 4)
A22: Year | B22: Amount raised ($bn) | C22: Funds closed | D22: Avg fund size ($bn) | E22: Change in amount | F22: Change in funds
A23: 2004 | B23: 90 | C23: 123 | D23: =IF(C23=0,0,B23/C23) -> 0.73170732
A24: 2005 | B24: 153 | C24: 211 | D24: =IF(C24=0,0,B24/C24) -> 0.72511848 | E24: =IF(B23=0,0,B24/B23-1) -> 0.7 | F24: =IF(C23=0,0,C24/C23-1) -> 0.71544715
A25: 2006 | B25: 201 | C25: 188 | D25: =IF(C25=0,0,B25/C25) -> 1.0691489 | E25: =IF(B24=0,0,B25/B24-1) -> 0.31372549 | F25: =IF(C24=0,0,C25/C24-1) -> -0.10900474
A26: 2007 | B26: 300 | C26: 233 | D26: =IF(C26=0,0,B26/C26) -> 1.2875536 | E26: =IF(B25=0,0,B26/B25-1) -> 0.49253731 | F26: =IF(C25=0,0,C26/C25-1) -> 0.2393617
A27: 2008 | B27: 314 | C27: 187 | D27: =IF(C27=0,0,B27/C27) -> 1.6791444 | E27: =IF(B26=0,0,B27/B26-1) -> 0.046666667 | F27: =IF(C26=0,0,C27/C26-1) -> -0.19742489
A28: Source: Exhibit 4 (PitchBook). 2008 dollars were a record — funds like TPG VI closed before Lehman — but fund count fell 20% and the case says future fundraising prospects were poor (p.5).
A30: C. Exit markets and TPG VI setbacks (case p.1, p.5; Exhibit 8)
A31: U.S. IPO proceeds, 2007 ($bn, read from Exhibit 8 chart, approx.) | C31: 81 | D31: Exhibit 8
A32: U.S. IPO proceeds, 2008 ($bn, approx.) | C32: 11 | D32: Exhibit 8
A33: Number of U.S. IPOs, 2007 (approx.) | C33: 330 | D33: Exhibit 8
A34: Number of U.S. IPOs, 2008 (approx.) | C34: 50 | D34: Exhibit 8
A35: TPG IPO exits 2006: proceeds ($m) from six IPOs | C35: 3100 | D35: Case p.5
A36: TPG IPO exits 2008: proceeds ($m) from one IPO | C36: 83 | D36: Case p.5
A37: TPG investment in Washington Mutual across funds ($m) | C37: 1350 | D37: Case p.1
A38: TPG VI's share of the WaMu investment, written off ($m) | C38: 437 | D38: Case p.5
A39: WaMu loss as % of TPG VI committed capital | C39: =C38/C5 -> 0.022070707
A40: TPG VI write-down reported March 2009 | C40: 0.29 | D40: Case fn 11 (Reuters)
A41: Permira's offer to LPs: commitment cut | C41: 0.6 | D41: Case p.1
A42: TPG's offer: commitment cut | C42: =Inputs!$C$27 -> 0.1 | D42: Case p.1
A43: IPO proceeds change 2007→2008 | C43: =IF(C31=0,0,C32/C31-1) -> -0.86419753
A44: TPG IPO proceeds change 2006→2008 | C44: =IF(C35=0,0,C36/C35-1) -> -0.97322581
A46: D. LP sentiment on GP alignment (Exhibit 11, Preqin)
A47: Satisfaction with the compensation structure | B47: Apr 2008 | C47: Dec 2008 | D47: Change (pp)
A48: Very satisfied | B48: 0.06 | C48: 0.13 | D48: =(C48-B48)*100 -> 7
A49: Satisfied | B49: 0.76 | C49: 0.56 | D49: =(C49-B49)*100 -> -20
A50: Dissatisfied | B50: 0.13 | C50: 0.27 | D50: =(C50-B50)*100 -> 14
A51: Very dissatisfied (remainder) | B51: =1-SUM(B48:B50) -> 0.05 | C51: =1-SUM(C48:C50) -> 0.04 | D51: =(C51-B51)*100 -> -1
A52: Satisfied or very satisfied | B52: =B48+B49 -> 0.82 | C52: =C48+C49 -> 0.69 | D52: =(C52-B52)*100 -> -13
A53: Case p.6 quotes "satisfaction ... dropped from 76% to 56%" (the "satisfied" bar) and "strongly dissatisfied ... from 13% to 27%" (the "dissatisfied" bar) — use the case wording on the slide.
A55: Areas of the LPA (Dec 2008 survey) | B55: Requiring improvement | C55: Improved in last 6 months
A56: Management fees | B56: 0.57 | C56: 0.65
A57: Carry structure and clawback | B57: 0.37 | C57: 0.12
A58: Fees on uninvested capital | B58: 0.25 | C58: 0.06
A59: Amount committed by GP | B59: 0.17 | C59: 0.03
A60: Hurdle | B60: 0.12 | C60: 0.09
A61: Transparency | B61: 0.12 | C61: 0.03
A62: Fees are the #1 complaint and the #1 area GPs had already moved on; the hurdle barely registers (12%) — useful context for Q5: LPs were not pushing hard on hurdles in 2008.
A64: E. Fees vs carry — what each does for TPG (linked to the model, current terms)
A65: PV of management fees at 15% | C65: ='Q3 Base case'!$C$57 -> 1731.4752
A66: PV of carried interest at 15% | C66: ='Q3 Base case'!$C$58 -> 1845.4937
A67: Fees as share of total GP compensation (PV) | C67: ='Q3 Base case'!$C$60 -> 0.48406213
A68: First year TPG receives any carry | C68: ='Q3 Base case'!$C$62 -> 8
A69: Management fee income per year (fund-wide, model) | C69: ='Q3 Base case'!$C$16 -> 300
A70: Management fee income per partner per year ($m, 40 partners, TPG VI only) | C70: ='Q3 Base case'!$C$16/40 -> 7.5 | D70: Case p.2: 40 partner-level professionals, ~150 investment professionals, 12 offices
A72: Pay mix across fund outcomes (current terms)
A73: Asset growth | B73: LP net IRR | C73: PV fees | D73: PV carry | E73: Fees % of GP pay
A74: =Engine!$I$21 -> 0 | B74: =Engine!$K$21 -> -0.028740632 | C74: =Engine!$Q$21 -> 1731.4752 | D74: =Engine!$R$21 -> 0 | E74: =IF(C74+D74=0,0,C74/(C74+D74)) -> 1
A75: =Engine!$I$31 -> 0.1 | B75: =Engine!$K$31 -> 0.064190788 | C75: =Engine!$Q$31 -> 1731.4752 | D75: =Engine!$R$31 -> 533.26558 | E75: =IF(C75+D75=0,0,C75/(C75+D75)) -> 0.76453571
A76: =Engine!$I$41 -> 0.2 | B76: =Engine!$K$41 -> 0.15722559 | C76: =Engine!$Q$41 -> 1731.4752 | D76: =Engine!$R$41 -> 1845.4937 | E76: =IF(C76+D76=0,0,C76/(C76+D76)) -> 0.48406213
A77: =Engine!$I$51 -> 0.3 | B77: =Engine!$K$51 -> 0.25164567 | C77: =Engine!$Q$51 -> 1731.4752 | D77: =Engine!$R$51 -> 4215.6996 | E77: =IF(C77+D77=0,0,C77/(C77+D77)) -> 0.29114247
A78: Fees = fixed pay that covers salaries and offices regardless of performance (case p.3–4; ILPA, Exhibit 12). Carry = performance pay that only starts once LPs have all their capital back (whole-fund, case p.4).
A79: The misalignment argument (case p.6): as funds grew, fee income alone could pay "ever-larger salaries" — the "corporatization" of PE. See Q3 Analysis §E for fee income by TPG fund.
A81: F. Talking points (update with the model)
A82: ="The fee cut costs TPG about $"&TEXT(C10,"#,##0")&"m a year on TPG VI; even if every LP cut 10%, fee income falls by $"&TEXT(C14,"#,##0")&"m a year — roughly "&TEXT(C17,"0%")&" of TPG's firm-wide fee base." -> The fee cut costs TPG about $30m a year on TPG VI; even if every LP cut 10%, fee income falls by $56m a year — roughly 8% of TPG's firm-wide fee base.
A83: ="2008 fundraising was a record $"&TEXT(B27,"#,##0")&"bn but the number of funds closed fell "&TEXT(-F27,"0%")&"; IPO proceeds collapsed "&TEXT(-C43,"0%")&" and TPG VI lost $"&TEXT(C38,"#,##0")&"m on WaMu ("&TEXT(C39,"0.0%")&" of the fund)." -> 2008 fundraising was a record $314bn but the number of funds closed fell 20%; IPO proceeds collapsed 86% and TPG VI lost $437m on WaMu (2.2% of the fund).
A84: ="Under current terms "&TEXT(C67,"0%")&" of TPG's compensation (PV) is fees it receives in every outcome; carry does not start until Year "&C68&"." -> Under current terms 48% of TPG's compensation (PV) is fees it receives in every outcome; carry does not start until Year 8.
A85: ="LP satisfaction fell from "&TEXT(B49,"0%")&" to "&TEXT(C49,"0%")&" in eight months; "&TEXT(B56,"0%")&" of LPs named management fees as needing improvement, only "&TEXT(B60,"0%")&" named the hurdle." -> LP satisfaction fell from 76% to 56% in eight months; 57% of LPs named management fees as needing improvement, only 12% named the hurdle.

Sheet Q3 Base case
A1: OREGON PUBLIC EMPLOYEES RETIREMENT FUND
B2: Committed capital ($ millions) | C2: =Inputs!$C$6 -> 20000 | E2: Asset growth rate (%) | F2: =Inputs!$C$8 -> 0.2 | H2: Hurdle rate (%) | I2: 0
B3: Management fee (%) | C3: =Inputs!$C$18 -> 0.015 | E3: Discount rate (%) | F3: =Inputs!$C$9 -> 0.15 | H3: GP catch-up (1 = yes) | I3: 0
B4: LP share of profit (%) | C4: =1-F4 -> 0.8 | E4: GP share of profit (%) | F4: =Inputs!$C$20 -> 0.2 | H4: OPERF ($ millions) | I4: =Inputs!$C$26 -> 750
A6: ="Scenario: "&"Current LPA terms — "&TEXT(C3,"0.00%")&" fee on committed capital, "&TEXT(F4,"0%")&" carry, "&IF(I2=0,"no hurdle",TEXT(I2,"0%")&" hurdle"&IF(I3=1," with 100% GP catch-up (soft)"," with no catch-up (hard)")) -> Scenario: Current LPA terms — 1.50% fee on committed capital, 20% carry, no hurdle | J6: Prep Q3 — base case
A8: Year | B8: 0 | C8: 1 | D8: 2 | E8: 3 | F8: 4 | G8: 5 | H8: 6 | I8: 7 | J8: 8 | K8: 9 | L8: 10
A9: Assumptions
A10: % Drawn of committed capital | C10: =Inputs!C$13 -> 0.2 | D10: =Inputs!D$13 -> 0.2 | E10: =Inputs!E$13 -> 0.2 | F10: =Inputs!F$13 -> 0.2 | G10: =Inputs!G$13 -> 0.2 | H10: =Inputs!H$13 -> 0 | I10: =Inputs!I$13 -> 0 | J10: =Inputs!J$13 -> 0 | ... L10: =Inputs!L$13 -> 0
A11: Distribution rate | C11: =Inputs!C$14 -> 0 | D11: =Inputs!D$14 -> 0 | E11: =Inputs!E$14 -> 0 | F11: =Inputs!F$14 -> 0 | G11: =Inputs!G$14 -> 0.2 | H11: =Inputs!H$14 -> 0.2 | I11: =Inputs!I$14 -> 0.2 | J11: =Inputs!J$14 -> 0.2 | ... L11: =Inputs!L$14 -> 1
A13: At the beginning of the year
A14: Assets | C14: =B24 -> 0 | D14: =C24 -> 4440 | E14: =D24 -> 9768 | F14: =E24 -> 16161.6 | G14: =F24 -> 23833.92 | H14: =G24 -> 26432.563 | I14: =H24 -> 25087.261 | J14: =I24 -> 23795.77 | ... L14: =K24 -> 21365.702
A15: Plus: Takedown | C15: =$C$2*C10 -> 4000 | D15: =$C$2*D10 -> 4000 | E15: =$C$2*E10 -> 4000 | F15: =$C$2*F10 -> 4000 | G15: =$C$2*G10 -> 4000 | H15: =$C$2*H10 -> 0 | I15: =$C$2*I10 -> 0 | J15: =$C$2*J10 -> 0 | ... L15: =$C$2*L10 -> 0
A16: Less: Management fee | C16: =$C$2*$C$3 -> 300 | D16: =$C$2*$C$3 -> 300 | E16: =$C$2*$C$3 -> 300 | F16: =$C$2*$C$3 -> 300 | G16: =$C$2*$C$3 -> 300 | H16: =$C$2*$C$3 -> 300 | I16: =$C$2*$C$3 -> 300 | J16: =$C$2*$C$3 -> 300 | ... L16: =$C$2*$C$3 -> 300
A17: Invested capital per period | C17: =C14+C15-C16 -> 3700 | D17: =D14+D15-D16 -> 8140 | E17: =E14+E15-E16 -> 13468 | F17: =F14+F15-F16 -> 19861.6 | G17: =G14+G15-G16 -> 27533.92 | H17: =H14+H15-H16 -> 26132.563 | I17: =I14+I15-I16 -> 24787.261 | J17: =J14+J15-J16 -> 23495.77 | ... L17: =L14+L15-L16 -> 21065.702
A19: At the end of the year
A20: Plus: Asset growth over year | C20: =C17*$F$2 -> 740 | D20: =D17*$F$2 -> 1628 | E20: =E17*$F$2 -> 2693.6 | F20: =F17*$F$2 -> 3972.32 | G20: =G17*$F$2 -> 5506.784 | H20: =H17*$F$2 -> 5226.5126 | I20: =I17*$F$2 -> 4957.4521 | J20: =J17*$F$2 -> 4699.154 | ... L20: =L17*$F$2 -> 4213.1404
A21: NAV before distributions | C21: =C17+C20 -> 4440 | D21: =D17+D20 -> 9768 | E21: =E17+E20 -> 16161.6 | F21: =F17+F20 -> 23833.92 | G21: =G17+G20 -> 33040.704 | H21: =H17+H20 -> 31359.076 | I21: =I17+I20 -> 29744.713 | J21: =J17+J20 -> 28194.924 | ... L21: =L17+L20 -> 25278.842
A23: Less: Distributions | C23: =C21*C11 -> 0 | D23: =D21*D11 -> 0 | E23: =E21*E11 -> 0 | F23: =F21*F11 -> 0 | G23: =G21*G11 -> 6608.1408 | H23: =H21*H11 -> 6271.8152 | I23: =I21*I11 -> 5948.9426 | J23: =J21*J11 -> 5638.9849 | ... L23: =L21*L11 -> 25278.842
A24: NAV after distributions | C24: =C21-C23 -> 4440 | D24: =D21-D23 -> 9768 | E24: =E21-E23 -> 16161.6 | F24: =F21-F23 -> 23833.92 | G24: =G21-G23 -> 26432.563 | H24: =H21-H23 -> 25087.261 | I24: =I21-I23 -> 23795.77 | J24: =J21-J23 -> 22555.939 | ... L24: =L21-L23 -> 0
A26: Distribution waterfall (whole-fund carry: LPs made whole first)
A27: Unreturned LP capital, incl. this year's takedown | C27: =B29+C15 -> 4000 | D27: =C29+D15 -> 8000 | E27: =D29+E15 -> 12000 | F27: =E29+F15 -> 16000 | G27: =F29+G15 -> 20000 | H27: =G29+H15 -> 13391.859 | I27: =H29+I15 -> 7120.044 | J27: =I29+J15 -> 1171.1015 | ... L27: =K29+L15 -> 0
A28: Tier 1 – Return of capital to LPs | C28: =MIN(C23,C27) -> 0 | D28: =MIN(D23,D27) -> 0 | E28: =MIN(E23,E27) -> 0 | F28: =MIN(F23,F27) -> 0 | G28: =MIN(G23,G27) -> 6608.1408 | H28: =MIN(H23,H27) -> 6271.8152 | I28: =MIN(I23,I27) -> 5948.9426 | J28: =MIN(J23,J27) -> 1171.1015 | ... L28: =MIN(L23,L27) -> 0
A29: Unreturned LP capital, end of year | C29: =C27-C28 -> 4000 | D29: =D27-D28 -> 8000 | E29: =E27-E28 -> 12000 | F29: =F27-F28 -> 16000 | G29: =G27-G28 -> 13391.859 | H29: =H27-H28 -> 7120.044 | I29: =I27-I28 -> 1171.1015 | J29: =J27-J28 -> 0 | ... L29: =L27-L28 -> 0
A30: Preferred return due (hurdle accrual + unpaid) | C30: =B32+$I$2*(C27+B32) -> 0 | D30: =C32+$I$2*(D27+C32) -> 0 | E30: =D32+$I$2*(E27+D32) -> 0 | F30: =E32+$I$2*(F27+E32) -> 0 | G30: =F32+$I$2*(G27+F32) -> 0 | H30: =G32+$I$2*(H27+G32) -> 0 | I30: =H32+$I$2*(I27+H32) -> 0 | J30: =I32+$I$2*(J27+I32) -> 0 | ... L30: =K32+$I$2*(L27+K32) -> 0
A31: Tier 2 – Preferred return paid to LPs | C31: =MIN(C23-C28,C30) -> 0 | D31: =MIN(D23-D28,D30) -> 0 | E31: =MIN(E23-E28,E30) -> 0 | F31: =MIN(F23-F28,F30) -> 0 | G31: =MIN(G23-G28,G30) -> 0 | H31: =MIN(H23-H28,H30) -> 0 | I31: =MIN(I23-I28,I30) -> 0 | J31: =MIN(J23-J28,J30) -> 0 | ... L31: =MIN(L23-L28,L30) -> 0
A32: Unpaid preferred return, end of year | C32: =C30-C31 -> 0 | D32: =D30-D31 -> 0 | E32: =E30-E31 -> 0 | F32: =F30-F31 -> 0 | G32: =G30-G31 -> 0 | H32: =H30-H31 -> 0 | I32: =I30-I31 -> 0 | J32: =J30-J31 -> 0 | ... L32: =L30-L31 -> 0
A33: Tier 3 – GP catch-up (soft hurdle only) | C33: =IF($I$3=1,MIN(C23-C28-C31,MAX(0,$F$4/(1-$F$4)*(B37+C31)-B38)),0) -> 0 | D33: =IF($I$3=1,MIN(D23-D28-D31,MAX(0,$F$4/(1-$F$4)*(C37+D31)-C38)),0) -> 0 | E33: =IF($I$3=1,MIN(E23-E28-E31,MAX(0,$F$4/(1-$F$4)*(D37+E31)-D38)),0) -> 0 | F33: =IF($I$3=1,MIN(F23-F28-F31,MAX(0,$F$4/(1-$F$4)*(E37+F31)-E38)),0) -> 0 | G33: =IF($I$3=1,MIN(G23-G28-G31,MAX(0,$F$4/(1-$F$4)*(F37+G31)-F38)),0) -> 0 | H33: =IF($I$3=1,MIN(H23-H28-H31,MAX(0,$F$4/(1-$F$4)*(G37+H31)-G38)),0) -> 0 | I33: =IF($I$3=1,MIN(I23-I28-I31,MAX(0,$F$4/(1-$F$4)*(H37+I31)-H38)),0) -> 0 | J33: =IF($I$3=1,MIN(J23-J28-J31,MAX(0,$F$4/(1-$F$4)*(I37+J31)-I38)),0) -> 0 | ... L33: =IF($I$3=1,MIN(L23-L28-L31,MAX(0,$F$4/(1-$F$4)*(K37+L31)-K38)),0) -> 0
A34: Tier 4 – Remaining profit split LP/GP | C34: =C23-C28-C31-C33 -> 0 | D34: =D23-D28-D31-D33 -> 0 | E34: =E23-E28-E31-E33 -> 0 | F34: =F23-F28-F31-F33 -> 0 | G34: =G23-G28-G31-G33 -> 0 | H34: =H23-H28-H31-H33 -> 0 | I34: =I23-I28-I31-I33 -> 0 | J34: =J23-J28-J31-J33 -> 4467.8834 | ... L34: =L23-L28-L31-L33 -> 25278.842
A35: Total distributions to LPs | C35: =C28+C31+$C$4*C34 -> 0 | D35: =D28+D31+$C$4*D34 -> 0 | E35: =E28+E31+$C$4*E34 -> 0 | F35: =F28+F31+$C$4*F34 -> 0 | G35: =G28+G31+$C$4*G34 -> 6608.1408 | H35: =H28+H31+$C$4*H34 -> 6271.8152 | I35: =I28+I31+$C$4*I34 -> 5948.9426 | J35: =J28+J31+$C$4*J34 -> 4745.4082 | ... L35: =L28+L31+$C$4*L34 -> 20223.074
A36: Total carried interest to GP | C36: =C33+$F$4*C34 -> 0 | D36: =D33+$F$4*D34 -> 0 | E36: =E33+$F$4*E34 -> 0 | F36: =F33+$F$4*F34 -> 0 | G36: =G33+$F$4*G34 -> 0 | H36: =H33+$F$4*H34 -> 0 | I36: =I33+$F$4*I34 -> 0 | J36: =J33+$F$4*J34 -> 893.57668 | ... L36: =L33+$F$4*L34 -> 5055.7684
A37: Cumulative LP profit received | C37: =B37+C31+$C$4*C34 -> 0 | D37: =C37+D31+$C$4*D34 -> 0 | E37: =D37+E31+$C$4*E34 -> 0 | F37: =E37+F31+$C$4*F34 -> 0 | G37: =F37+G31+$C$4*G34 -> 0 | H37: =G37+H31+$C$4*H34 -> 0 | I37: =H37+I31+$C$4*I34 -> 0 | J37: =I37+J31+$C$4*J34 -> 3574.3067 | ... L37: =K37+L31+$C$4*L34 -> 28070.521
A38: Cumulative GP carried interest | C38: =B38+C36 -> 0 | D38: =C38+D36 -> 0 | E38: =D38+E36 -> 0 | F38: =E38+F36 -> 0 | G38: =F38+G36 -> 0 | H38: =G38+H36 -> 0 | I38: =H38+I36 -> 0 | J38: =I38+J36 -> 893.57668 | ... L38: =K38+L36 -> 7017.6302
A40: Cash flows by date (column = point in time t: the start of Year n is t = n − 1; the end of Year n is t = n)
A41: LP: capital calls (takedowns) | B41: =IF(B$8>=COLUMNS($C$15:$L$15),0,-INDEX($C$15:$L$15,B$8+1)) -> -4000 | C41: =IF(C$8>=COLUMNS($C$15:$L$15),0,-INDEX($C$15:$L$15,C$8+1)) -> -4000 | D41: =IF(D$8>=COLUMNS($C$15:$L$15),0,-INDEX($C$15:$L$15,D$8+1)) -> -4000 | E41: =IF(E$8>=COLUMNS($C$15:$L$15),0,-INDEX($C$15:$L$15,E$8+1)) -> -4000 | F41: =IF(F$8>=COLUMNS($C$15:$L$15),0,-INDEX($C$15:$L$15,F$8+1)) -> -4000 | G41: =IF(G$8>=COLUMNS($C$15:$L$15),0,-INDEX($C$15:$L$15,G$8+1)) -> 0 | H41: =IF(H$8>=COLUMNS($C$15:$L$15),0,-INDEX($C$15:$L$15,H$8+1)) -> 0 | I41: =IF(I$8>=COLUMNS($C$15:$L$15),0,-INDEX($C$15:$L$15,I$8+1)) -> 0 | ... L41: =IF(L$8>=COLUMNS($C$15:$L$15),0,-INDEX($C$15:$L$15,L$8+1)) -> 0
A42: LP: distributions received | B42: =IF(B$8=0,0,INDEX($C$35:$L$35,B$8)) -> 0 | C42: =IF(C$8=0,0,INDEX($C$35:$L$35,C$8)) -> 0 | D42: =IF(D$8=0,0,INDEX($C$35:$L$35,D$8)) -> 0 | E42: =IF(E$8=0,0,INDEX($C$35:$L$35,E$8)) -> 0 | F42: =IF(F$8=0,0,INDEX($C$35:$L$35,F$8)) -> 0 | G42: =IF(G$8=0,0,INDEX($C$35:$L$35,G$8)) -> 6608.1408 | H42: =IF(H$8=0,0,INDEX($C$35:$L$35,H$8)) -> 6271.8152 | I42: =IF(I$8=0,0,INDEX($C$35:$L$35,I$8)) -> 5948.9426 | ... L42: =IF(L$8=0,0,INDEX($C$35:$L$35,L$8)) -> 20223.074
A43: LP: net cash flow | B43: =B41+B42 -> -4000 | C43: =C41+C42 -> -4000 | D43: =D41+D42 -> -4000 | E43: =E41+E42 -> -4000 | F43: =F41+F42 -> -4000 | G43: =G41+G42 -> 6608.1408 | H43: =H41+H42 -> 6271.8152 | I43: =I41+I42 -> 5948.9426 | ... L43: =L41+L42 -> 20223.074
A44: GP: management fees received | B44: =IF(B$8>=COLUMNS($C$16:$L$16),0,INDEX($C$16:$L$16,B$8+1)) -> 300 | C44: =IF(C$8>=COLUMNS($C$16:$L$16),0,INDEX($C$16:$L$16,C$8+1)) -> 300 | D44: =IF(D$8>=COLUMNS($C$16:$L$16),0,INDEX($C$16:$L$16,D$8+1)) -> 300 | E44: =IF(E$8>=COLUMNS($C$16:$L$16),0,INDEX($C$16:$L$16,E$8+1)) -> 300 | F44: =IF(F$8>=COLUMNS($C$16:$L$16),0,INDEX($C$16:$L$16,F$8+1)) -> 300 | G44: =IF(G$8>=COLUMNS($C$16:$L$16),0,INDEX($C$16:$L$16,G$8+1)) -> 300 | H44: =IF(H$8>=COLUMNS($C$16:$L$16),0,INDEX($C$16:$L$16,H$8+1)) -> 300 | I44: =IF(I$8>=COLUMNS($C$16:$L$16),0,INDEX($C$16:$L$16,I$8+1)) -> 300 | ... L44: =IF(L$8>=COLUMNS($C$16:$L$16),0,INDEX($C$16:$L$16,L$8+1)) -> 0
A45: GP: carried interest received | B45: =IF(B$8=0,0,INDEX($C$36:$L$36,B$8)) -> 0 | C45: =IF(C$8=0,0,INDEX($C$36:$L$36,C$8)) -> 0 | D45: =IF(D$8=0,0,INDEX($C$36:$L$36,D$8)) -> 0 | E45: =IF(E$8=0,0,INDEX($C$36:$L$36,E$8)) -> 0 | F45: =IF(F$8=0,0,INDEX($C$36:$L$36,F$8)) -> 0 | G45: =IF(G$8=0,0,INDEX($C$36:$L$36,G$8)) -> 0 | H45: =IF(H$8=0,0,INDEX($C$36:$L$36,H$8)) -> 0 | I45: =IF(I$8=0,0,INDEX($C$36:$L$36,I$8)) -> 0 | ... L45: =IF(L$8=0,0,INDEX($C$36:$L$36,L$8)) -> 5055.7684
A46: GP: total compensation | B46: =B44+B45 -> 300 | C46: =C44+C45 -> 300 | D46: =D44+D45 -> 300 | E46: =E44+E45 -> 300 | F46: =F44+F45 -> 300 | G46: =G44+G45 -> 300 | H46: =H44+H45 -> 300 | I46: =I44+I45 -> 300 | ... L46: =L44+L45 -> 5055.7684
A47: OPERF: net cash flow (pro-rata share of LP) | B47: =$C$63*B43 -> -150 | C47: =$C$63*C43 -> -150 | D47: =$C$63*D43 -> -150 | E47: =$C$63*E43 -> -150 | F47: =$C$63*F43 -> -150 | G47: =$C$63*G43 -> 247.80528 | H47: =$C$63*H43 -> 235.19307 | I47: =$C$63*I43 -> 223.08535 | ... L47: =$C$63*L43 -> 758.36527
A49: Results ($ millions unless stated)
A50: LP net IRR (after fees and carry) | C50: =IRR(B43:L43,0.1) -> 0.15722559 | E50: IRR of LP net cash flows (row 43)
A51: LP NPV at the discount rate | C51: =B43+NPV($F$3,C43:L43) -> 578.21714 | E51: Positive = beats the 15% required return
A52: LP total contributions | C52: =-SUM(B41:L41) -> 20000 | E52: Includes capital later used to pay fees
A53: LP total distributions | C53: =SUM(B42:L42) -> 48070.521
A54: LP multiple of contributed capital (TVPI) | C54: =IF(C52=0,0,C53/C52) -> 2.403526
A55: GP management fees, total (nominal) | C55: =SUM(B44:L44) -> 3000
A56: GP carried interest, total (nominal) | C56: =SUM(B45:L45) -> 7017.6302
A57: PV of management fees at the discount rate | C57: =B44+NPV($F$3,C44:L44) -> 1731.4752 | E57: Fees paid at the start of each year
A58: PV of carried interest at the discount rate | C58: =B45+NPV($F$3,C45:L45) -> 1845.4937
A59: PV of total GP compensation | C59: =C57+C58 -> 3576.9689
A60: Management fees as % of GP compensation (PV) | C60: =IF(C59=0,0,C57/C59) -> 0.48406213 | E60: Fixed pay share; the rest is performance pay
A61: Gross asset return less LP net IRR (fee + carry drag) | C61: =$F$2-C50 -> 0.042774406
A62: First year the GP receives carried interest | C62: =IF(MAX(C38:L38)<=0,"None",IFERROR(INDEX(C8:L8,MATCH(0,C38:L38,1)+1),C8)) -> 8
A63: OPERF share of the fund's LP cash flows | C63: =IF($C$2=0,0,$I$4/$C$2) -> 0.0375 | E63: OPERF commitment ÷ committed capital
A64: OPERF NPV at the discount rate | C64: =C63*C51 -> 21.683143
A65: OPERF share of management fees paid (nominal) | C65: =C63*C55 -> 112.5
A66: OPERF distributions received (nominal) | C66: =C63*C53 -> 1802.6445
A68: Checks (0 = OK)
A69: NAV fully liquidated at end of Year 10 | C69: =ROUND(L24,6) -> 0
A70: Distributions = LP distributions + GP carry | C70: =ROUND(SUM(C23:L23)-SUM(C35:L35)-SUM(C36:L36),6) -> 0
A71: Distributions = takedowns − fees + asset growth | C71: =ROUND(SUM(C23:L23)-(SUM(C15:L15)-SUM(C16:L16)+SUM(C20:L20)),6) -> 0
A72: All checks | C72: =IF(ABS(C69)+ABS(C70)+ABS(C71)<0.001,"OK","CHECK") -> OK
A74: Source: Layout follows the Template sheet of the Darden supplementary spreadsheet (UV5624); waterfall, cash-flow and results rows added by the team.

Sheet Q3 Analysis
A1: Q3 — FINANCIAL IMPLICATIONS OF THE GP/LP COMPENSATION STRUCTURE
A2: Base case: $20bn fund, 1.50% fee on committed capital, 20% carry, no hurdle, assets grow 20% a year, 15% discount rate (sheet "Q3 Base case").
A4: A. Base-case outcome ($ millions)
A5: LP net IRR | C5: ='Q3 Base case'!$C$50 -> 0.15722559 | D5: vs 20% gross asset growth
A6: LP NPV at 15% | C6: ='Q3 Base case'!$C$51 -> 578.21714
A7: LP multiple (TVPI) | C7: ='Q3 Base case'!$C$54 -> 2.403526
A8: GP management fees (nominal) | C8: ='Q3 Base case'!$C$55 -> 3000
A9: GP carried interest (nominal) | C9: ='Q3 Base case'!$C$56 -> 7017.6302
A10: PV of management fees | C10: ='Q3 Base case'!$C$57 -> 1731.4752
A11: PV of carried interest | C11: ='Q3 Base case'!$C$58 -> 1845.4937
A12: PV of total GP compensation | C12: ='Q3 Base case'!$C$59 -> 3576.9689
A13: Fees as % of GP compensation (PV) | C13: ='Q3 Base case'!$C$60 -> 0.48406213 | D13: fees are fixed pay — collected whether or not the fund performs
A14: First year TPG receives carry | C14: ='Q3 Base case'!$C$62 -> 8 | D14: carry only starts once LPs have their $20bn back
A16: B. Gross-to-net bridge — what fees and carry cost LPs
B17: LP IRR | C17: Drag (bps)
A18: Gross: asset return with no fees and no carry | B18: =Engine!$K$16 -> 0.2
A19: After 1.50% management fee only | B19: =Engine!$K$17 -> 0.17804892 | C19: =(B18-B19)*10000 -> 219.51075
A20: After management fee and 20% carry (LP net) | B20: ='Q3 Base case'!$C$50 -> 0.15722559 | C20: =(B19-B20)*10000 -> 208.2333
A21: Total drag | C21: =C19+C20 -> 427.74406
A23: C. Who captures the value created above the 15% required return (PV at 15%, $ millions)
B24: $ millions | C24: Share
A25: LPs: NPV of net cash flows | B25: ='Q3 Base case'!$C$51 -> 578.21714 | C25: =IF($B$28=0,0,B25/$B$28) -> 0.13915554 | D25: LPs put up all the capital and bear the risk...
A26: TPG: management fees | B26: ='Q3 Base case'!$C$57 -> 1731.4752 | C26: =IF($B$28=0,0,B26/$B$28) -> 0.4167022 | D26: ...but most of the value above 15% goes to the GP
A27: TPG: carried interest | B27: ='Q3 Base case'!$C$58 -> 1845.4937 | C27: =IF($B$28=0,0,B27/$B$28) -> 0.44414226
A28: Total value to LPs and TPG | B28: =SUM(B25:B27) -> 4155.1861 | C28: =IF($B$28=0,0,B28/$B$28) -> 1
A29: Memo: NPV of the fund with no fees and no carry | B29: =Engine!$L$16 -> 4562.1912
A30: Memo: growth lost because fees leave the invested base | B30: =B29-B28 -> 407.00511 | D30: fee dollars would have compounded at 20% inside the fund
A31: TPG's figures are before its operating costs (salaries, offices), which management fees are meant to cover (Exhibit 12).
A32: D. Fixed vs performance pay — TPG compensation across fund outcomes (current terms)
A33: Asset growth | B33: LP net IRR | C33: LP NPV | D33: PV mgmt fees | E33: PV carry | F33: PV total GP | G33: Fees % of GP
A34: =Engine!$I$21 -> 0 | B34: =Engine!$K$21 -> -0.028740632 | C34: =Engine!$L$21 -> -9275.938 | D34: =Engine!$Q$21 -> 1731.4752 | E34: =Engine!$R$21 -> 0 | F34: =D34+E34 -> 1731.4752 | G34: =IF(F34=0,0,D34/F34) -> 1
A35: =Engine!$I$26 -> 0.05 | B35: =Engine!$K$26 -> 0.019506054 | C35: =Engine!$L$26 -> -7534.8785 | D35: =Engine!$Q$26 -> 1731.4752 | E35: =Engine!$R$26 -> 143.71312 | F35: =D35+E35 -> 1875.1883 | G35: =IF(F35=0,0,D35/F35) -> 0.9233607
A36: =Engine!$I$31 -> 0.1 | B36: =Engine!$K$31 -> 0.064190788 | C36: =Engine!$L$31 -> -5465.5015 | D36: =Engine!$Q$31 -> 1731.4752 | E36: =Engine!$R$31 -> 533.26558 | F36: =D36+E36 -> 2264.7408 | G36: =IF(F36=0,0,D36/F36) -> 0.76453571
A37: =Engine!$I$36 -> 0.15 | B37: =Engine!$K$36 -> 0.1104452 | C37: =Engine!$L$36 -> -2810.4186 | D37: =Engine!$Q$36 -> 1731.4752 | E37: =Engine!$R$36 -> 1078.9434 | F37: =D37+E37 -> 2810.4186 | G37: =IF(F37=0,0,D37/F37) -> 0.61609156
A38: =Engine!$I$41 -> 0.2 | B38: =Engine!$K$41 -> 0.15722559 | C38: =Engine!$L$41 -> 578.21714 | D38: =Engine!$Q$41 -> 1731.4752 | E38: =Engine!$R$41 -> 1845.4937 | F38: =D38+E38 -> 3576.9689 | G38: =IF(F38=0,0,D38/F38) -> 0.48406213
A39: =Engine!$I$46 -> 0.25 | B39: =Engine!$K$46 -> 0.20431317 | C39: =Engine!$L$46 -> 4929.74 | D39: =Engine!$Q$46 -> 1731.4752 | E39: =Engine!$R$46 -> 2871.6653 | F39: =D39+E39 -> 4603.1405 | G39: =IF(F39=0,0,D39/F39) -> 0.37615084
A40: =Engine!$I$51 -> 0.3 | B40: =Engine!$K$51 -> 0.25164567 | C40: =Engine!$L$51 -> 10522.138 | D40: =Engine!$Q$51 -> 1731.4752 | E40: =Engine!$R$51 -> 4215.6996 | F40: =D40+E40 -> 5947.1748 | G40: =IF(F40=0,0,D40/F40) -> 0.29114247
A41: Even if the fund only returns capital (0–5% growth) and LPs lose money, TPG still collects the full fee stream.
A43: E. Fee income scales with fund size — TPG flagship buyout funds (Exhibit 1)
A44: Fund | B44: Vintage | C44: Committed ($m) | D44: Fee rate | E44: Annual fee ($m) | F44: 10-year fees ($m) | G44: × Fund I
A45: Texas Pacific Group Partners | B45: 1994 | C45: 721 | D45: =Inputs!$C$18 -> 0.015 | E45: =C45*D45 -> 10.815 | F45: =E45*Inputs!$C$7 -> 108.15 | G45: =IF($E$45=0,0,E45/$E$45) -> 1
A46: Texas Pacific Group Partners II | B46: 1997 | C46: 2500 | D46: =Inputs!$C$18 -> 0.015 | E46: =C46*D46 -> 37.5 | F46: =E46*Inputs!$C$7 -> 375 | G46: =IF($E$45=0,0,E46/$E$45) -> 3.4674064
A47: Texas Pacific Group Partners III | B47: 2000 | C47: 3414 | D47: =Inputs!$C$18 -> 0.015 | E47: =C47*D47 -> 51.21 | F47: =E47*Inputs!$C$7 -> 512.1 | G47: =IF($E$45=0,0,E47/$E$45) -> 4.7350902
A48: Texas Pacific Group Partners IV | B48: 2003 | C48: 5300 | D48: =Inputs!$C$18 -> 0.015 | E48: =C48*D48 -> 79.5 | F48: =E48*Inputs!$C$7 -> 795 | G48: =IF($E$45=0,0,E48/$E$45) -> 7.3509015
A49: Texas Pacific Group Partners V | B49: 2006 | C49: 15000 | D49: =Inputs!$C$18 -> 0.015 | E49: =C49*D49 -> 225 | F49: =E49*Inputs!$C$7 -> 2250 | G49: =IF($E$45=0,0,E49/$E$45) -> 20.804438
A50: TPG Partners VI | B50: 2008 | C50: 19800 | D50: =Inputs!$C$18 -> 0.015 | E50: =C50*D50 -> 297 | F50: =E50*Inputs!$C$7 -> 2970 | G50: =IF($E$45=0,0,E50/$E$45) -> 27.461859
A51: Fund sizes from Exhibit 1. Assumption: the case does not give historical fee rates, so the current 1.50% is applied to every fund for illustration.
A52: TPG today: ~$50bn of commitments run by 40 partners (case p.2) — fees, not carry, increasingly fund the firm ("corporatization", case p.6).

Sheet Q4 Fee cut
A1: OREGON PUBLIC EMPLOYEES RETIREMENT FUND
B2: Committed capital ($ millions) | C2: =Inputs!$C$6 -> 20000 | E2: Asset growth rate (%) | F2: =Inputs!$C$8 -> 0.2 | H2: Hurdle rate (%) | I2: 0
B3: Management fee (%) | C3: =Inputs!$C$19 -> 0.0135 | E3: Discount rate (%) | F3: =Inputs!$C$9 -> 0.15 | H3: GP catch-up (1 = yes) | I3: 0
B4: LP share of profit (%) | C4: =1-F4 -> 0.8 | E4: GP share of profit (%) | F4: =Inputs!$C$20 -> 0.2 | H4: OPERF ($ millions) | I4: =Inputs!$C$26 -> 750
A6: ="Scenario: "&"TPG offer — "&TEXT(C3,"0.00%")&" fee on committed capital, "&TEXT(F4,"0%")&" carry, "&IF(I2=0,"no hurdle",TEXT(I2,"0%")&" hurdle"&IF(I3=1," with 100% GP catch-up (soft)"," with no catch-up (hard)")) -> Scenario: TPG offer — 1.35% fee on committed capital, 20% carry, no hurdle | J6: Prep Q4 — fee cut to 1.35%
A8: Year | B8: 0 | C8: 1 | D8: 2 | E8: 3 | F8: 4 | G8: 5 | H8: 6 | I8: 7 | J8: 8 | K8: 9 | L8: 10
A9: Assumptions
A10: % Drawn of committed capital | C10: =Inputs!C$13 -> 0.2 | D10: =Inputs!D$13 -> 0.2 | E10: =Inputs!E$13 -> 0.2 | F10: =Inputs!F$13 -> 0.2 | G10: =Inputs!G$13 -> 0.2 | H10: =Inputs!H$13 -> 0 | I10: =Inputs!I$13 -> 0 | J10: =Inputs!J$13 -> 0 | ... L10: =Inputs!L$13 -> 0
A11: Distribution rate | C11: =Inputs!C$14 -> 0 | D11: =Inputs!D$14 -> 0 | E11: =Inputs!E$14 -> 0 | F11: =Inputs!F$14 -> 0 | G11: =Inputs!G$14 -> 0.2 | H11: =Inputs!H$14 -> 0.2 | I11: =Inputs!I$14 -> 0.2 | J11: =Inputs!J$14 -> 0.2 | ... L11: =Inputs!L$14 -> 1
A13: At the beginning of the year
A14: Assets | C14: =B24 -> 0 | D14: =C24 -> 4476 | E14: =D24 -> 9847.2 | F14: =E24 -> 16292.64 | G14: =F24 -> 24027.168 | H14: =G24 -> 26646.881 | I14: =H24 -> 25321.806 | J14: =I24 -> 24049.734 | ... L14: =K24 -> 21656.203
A15: Plus: Takedown | C15: =$C$2*C10 -> 4000 | D15: =$C$2*D10 -> 4000 | E15: =$C$2*E10 -> 4000 | F15: =$C$2*F10 -> 4000 | G15: =$C$2*G10 -> 4000 | H15: =$C$2*H10 -> 0 | I15: =$C$2*I10 -> 0 | J15: =$C$2*J10 -> 0 | ... L15: =$C$2*L10 -> 0
A16: Less: Management fee | C16: =$C$2*$C$3 -> 270 | D16: =$C$2*$C$3 -> 270 | E16: =$C$2*$C$3 -> 270 | F16: =$C$2*$C$3 -> 270 | G16: =$C$2*$C$3 -> 270 | H16: =$C$2*$C$3 -> 270 | I16: =$C$2*$C$3 -> 270 | J16: =$C$2*$C$3 -> 270 | ... L16: =$C$2*$C$3 -> 270
A17: Invested capital per period | C17: =C14+C15-C16 -> 3730 | D17: =D14+D15-D16 -> 8206 | E17: =E14+E15-E16 -> 13577.2 | F17: =F14+F15-F16 -> 20022.64 | G17: =G14+G15-G16 -> 27757.168 | H17: =H14+H15-H16 -> 26376.881 | I17: =I14+I15-I16 -> 25051.806 | J17: =J14+J15-J16 -> 23779.734 | ... L17: =L14+L15-L16 -> 21386.203
A19: At the end of the year
A20: Plus: Asset growth over year | C20: =C17*$F$2 -> 746 | D20: =D17*$F$2 -> 1641.2 | E20: =E17*$F$2 -> 2715.44 | F20: =F17*$F$2 -> 4004.528 | G20: =G17*$F$2 -> 5551.4336 | H20: =H17*$F$2 -> 5275.3763 | I20: =I17*$F$2 -> 5010.3612 | J20: =J17*$F$2 -> 4755.9468 | ... L20: =L17*$F$2 -> 4277.2405
A21: NAV before distributions | C21: =C17+C20 -> 4476 | D21: =D17+D20 -> 9847.2 | E21: =E17+E20 -> 16292.64 | F21: =F17+F20 -> 24027.168 | G21: =G17+G20 -> 33308.602 | H21: =H17+H20 -> 31652.258 | I21: =I17+I20 -> 30062.167 | J21: =J17+J20 -> 28535.681 | ... L21: =L17+L20 -> 25663.443
A23: Less: Distributions | C23: =C21*C11 -> 0 | D23: =D21*D11 -> 0 | E23: =E21*E11 -> 0 | F23: =F21*F11 -> 0 | G23: =G21*G11 -> 6661.7203 | H23: =H21*H11 -> 6330.4515 | I23: =I21*I11 -> 6012.4334 | J23: =J21*J11 -> 5707.1361 | ... L23: =L21*L11 -> 25663.443
A24: NAV after distributions | C24: =C21-C23 -> 4476 | D24: =D21-D23 -> 9847.2 | E24: =E21-E23 -> 16292.64 | F24: =F21-F23 -> 24027.168 | G24: =G21-G23 -> 26646.881 | H24: =H21-H23 -> 25321.806 | I24: =I21-I23 -> 24049.734 | J24: =J21-J23 -> 22828.544 | ... L24: =L21-L23 -> 0
A26: Distribution waterfall (whole-fund carry: LPs made whole first)
A27: Unreturned LP capital, incl. this year's takedown | C27: =B29+C15 -> 4000 | D27: =C29+D15 -> 8000 | E27: =D29+E15 -> 12000 | F27: =E29+F15 -> 16000 | G27: =F29+G15 -> 20000 | H27: =G29+H15 -> 13338.28 | I27: =H29+I15 -> 7007.8282 | J27: =I29+J15 -> 995.39473 | ... L27: =K29+L15 -> 0
A28: Tier 1 – Return of capital to LPs | C28: =MIN(C23,C27) -> 0 | D28: =MIN(D23,D27) -> 0 | E28: =MIN(E23,E27) -> 0 | F28: =MIN(F23,F27) -> 0 | G28: =MIN(G23,G27) -> 6661.7203 | H28: =MIN(H23,H27) -> 6330.4515 | I28: =MIN(I23,I27) -> 6012.4334 | J28: =MIN(J23,J27) -> 995.39473 | ... L28: =MIN(L23,L27) -> 0
A29: Unreturned LP capital, end of year | C29: =C27-C28 -> 4000 | D29: =D27-D28 -> 8000 | E29: =E27-E28 -> 12000 | F29: =F27-F28 -> 16000 | G29: =G27-G28 -> 13338.28 | H29: =H27-H28 -> 7007.8282 | I29: =I27-I28 -> 995.39473 | J29: =J27-J28 -> 0 | ... L29: =L27-L28 -> 0
A30: Preferred return due (hurdle accrual + unpaid) | C30: =B32+$I$2*(C27+B32) -> 0 | D30: =C32+$I$2*(D27+C32) -> 0 | E30: =D32+$I$2*(E27+D32) -> 0 | F30: =E32+$I$2*(F27+E32) -> 0 | G30: =F32+$I$2*(G27+F32) -> 0 | H30: =G32+$I$2*(H27+G32) -> 0 | I30: =H32+$I$2*(I27+H32) -> 0 | J30: =I32+$I$2*(J27+I32) -> 0 | ... L30: =K32+$I$2*(L27+K32) -> 0
A31: Tier 2 – Preferred return paid to LPs | C31: =MIN(C23-C28,C30) -> 0 | D31: =MIN(D23-D28,D30) -> 0 | E31: =MIN(E23-E28,E30) -> 0 | F31: =MIN(F23-F28,F30) -> 0 | G31: =MIN(G23-G28,G30) -> 0 | H31: =MIN(H23-H28,H30) -> 0 | I31: =MIN(I23-I28,I30) -> 0 | J31: =MIN(J23-J28,J30) -> 0 | ... L31: =MIN(L23-L28,L30) -> 0
A32: Unpaid preferred return, end of year | C32: =C30-C31 -> 0 | D32: =D30-D31 -> 0 | E32: =E30-E31 -> 0 | F32: =F30-F31 -> 0 | G32: =G30-G31 -> 0 | H32: =H30-H31 -> 0 | I32: =I30-I31 -> 0 | J32: =J30-J31 -> 0 | ... L32: =L30-L31 -> 0
A33: Tier 3 – GP catch-up (soft hurdle only) | C33: =IF($I$3=1,MIN(C23-C28-C31,MAX(0,$F$4/(1-$F$4)*(B37+C31)-B38)),0) -> 0 | D33: =IF($I$3=1,MIN(D23-D28-D31,MAX(0,$F$4/(1-$F$4)*(C37+D31)-C38)),0) -> 0 | E33: =IF($I$3=1,MIN(E23-E28-E31,MAX(0,$F$4/(1-$F$4)*(D37+E31)-D38)),0) -> 0 | F33: =IF($I$3=1,MIN(F23-F28-F31,MAX(0,$F$4/(1-$F$4)*(E37+F31)-E38)),0) -> 0 | G33: =IF($I$3=1,MIN(G23-G28-G31,MAX(0,$F$4/(1-$F$4)*(F37+G31)-F38)),0) -> 0 | H33: =IF($I$3=1,MIN(H23-H28-H31,MAX(0,$F$4/(1-$F$4)*(G37+H31)-G38)),0) -> 0 | I33: =IF($I$3=1,MIN(I23-I28-I31,MAX(0,$F$4/(1-$F$4)*(H37+I31)-H38)),0) -> 0 | J33: =IF($I$3=1,MIN(J23-J28-J31,MAX(0,$F$4/(1-$F$4)*(I37+J31)-I38)),0) -> 0 | ... L33: =IF($I$3=1,MIN(L23-L28-L31,MAX(0,$F$4/(1-$F$4)*(K37+L31)-K38)),0) -> 0
A34: Tier 4 – Remaining profit split LP/GP | C34: =C23-C28-C31-C33 -> 0 | D34: =D23-D28-D31-D33 -> 0 | E34: =E23-E28-E31-E33 -> 0 | F34: =F23-F28-F31-F33 -> 0 | G34: =G23-G28-G31-G33 -> 0 | H34: =H23-H28-H31-H33 -> 0 | I34: =I23-I28-I31-I33 -> 0 | J34: =J23-J28-J31-J33 -> 4711.7414 | ... L34: =L23-L28-L31-L33 -> 25663.443
A35: Total distributions to LPs | C35: =C28+C31+$C$4*C34 -> 0 | D35: =D28+D31+$C$4*D34 -> 0 | E35: =E28+E31+$C$4*E34 -> 0 | F35: =F28+F31+$C$4*F34 -> 0 | G35: =G28+G31+$C$4*G34 -> 6661.7203 | H35: =H28+H31+$C$4*H34 -> 6330.4515 | I35: =I28+I31+$C$4*I34 -> 6012.4334 | J35: =J28+J31+$C$4*J34 -> 4764.7878 | ... L35: =L28+L31+$C$4*L34 -> 20530.755
A36: Total carried interest to GP | C36: =C33+$F$4*C34 -> 0 | D36: =D33+$F$4*D34 -> 0 | E36: =E33+$F$4*E34 -> 0 | F36: =F33+$F$4*F34 -> 0 | G36: =G33+$F$4*G34 -> 0 | H36: =H33+$F$4*H34 -> 0 | I36: =I33+$F$4*I34 -> 0 | J36: =J33+$F$4*J34 -> 942.34828 | ... L36: =L33+$F$4*L34 -> 5132.6886
A37: Cumulative LP profit received | C37: =B37+C31+$C$4*C34 -> 0 | D37: =C37+D31+$C$4*D34 -> 0 | E37: =D37+E31+$C$4*E34 -> 0 | F37: =E37+F31+$C$4*F34 -> 0 | G37: =F37+G31+$C$4*G34 -> 0 | H37: =G37+H31+$C$4*H34 -> 0 | I37: =H37+I31+$C$4*I34 -> 0 | J37: =I37+J31+$C$4*J34 -> 3769.3931 | ... L37: =K37+L31+$C$4*L34 -> 28631.388
A38: Cumulative GP carried interest | C38: =B38+C36 -> 0 | D38: =C38+D36 -> 0 | E38: =D38+E36 -> 0 | F38: =E38+F36 -> 0 | G38: =F38+G36 -> 0 | H38: =G38+H36 -> 0 | I38: =H38+I36 -> 0 | J38: =I38+J36 -> 942.34828 | ... L38: =K38+L36 -> 7157.847
A40: Cash flows by date (column = point in time t: the start of Year n is t = n − 1; the end of Year n is t = n)
A41: LP: capital calls (takedowns) | B41: =IF(B$8>=COLUMNS($C$15:$L$15),0,-INDEX($C$15:$L$15,B$8+1)) -> -4000 | C41: =IF(C$8>=COLUMNS($C$15:$L$15),0,-INDEX($C$15:$L$15,C$8+1)) -> -4000 | D41: =IF(D$8>=COLUMNS($C$15:$L$15),0,-INDEX($C$15:$L$15,D$8+1)) -> -4000 | E41: =IF(E$8>=COLUMNS($C$15:$L$15),0,-INDEX($C$15:$L$15,E$8+1)) -> -4000 | F41: =IF(F$8>=COLUMNS($C$15:$L$15),0,-INDEX($C$15:$L$15,F$8+1)) -> -4000 | G41: =IF(G$8>=COLUMNS($C$15:$L$15),0,-INDEX($C$15:$L$15,G$8+1)) -> 0 | H41: =IF(H$8>=COLUMNS($C$15:$L$15),0,-INDEX($C$15:$L$15,H$8+1)) -> 0 | I41: =IF(I$8>=COLUMNS($C$15:$L$15),0,-INDEX($C$15:$L$15,I$8+1)) -> 0 | ... L41: =IF(L$8>=COLUMNS($C$15:$L$15),0,-INDEX($C$15:$L$15,L$8+1)) -> 0
A42: LP: distributions received | B42: =IF(B$8=0,0,INDEX($C$35:$L$35,B$8)) -> 0 | C42: =IF(C$8=0,0,INDEX($C$35:$L$35,C$8)) -> 0 | D42: =IF(D$8=0,0,INDEX($C$35:$L$35,D$8)) -> 0 | E42: =IF(E$8=0,0,INDEX($C$35:$L$35,E$8)) -> 0 | F42: =IF(F$8=0,0,INDEX($C$35:$L$35,F$8)) -> 0 | G42: =IF(G$8=0,0,INDEX($C$35:$L$35,G$8)) -> 6661.7203 | H42: =IF(H$8=0,0,INDEX($C$35:$L$35,H$8)) -> 6330.4515 | I42: =IF(I$8=0,0,INDEX($C$35:$L$35,I$8)) -> 6012.4334 | ... L42: =IF(L$8=0,0,INDEX($C$35:$L$35,L$8)) -> 20530.755
A43: LP: net cash flow | B43: =B41+B42 -> -4000 | C43: =C41+C42 -> -4000 | D43: =D41+D42 -> -4000 | E43: =E41+E42 -> -4000 | F43: =F41+F42 -> -4000 | G43: =G41+G42 -> 6661.7203 | H43: =H41+H42 -> 6330.4515 | I43: =I41+I42 -> 6012.4334 | ... L43: =L41+L42 -> 20530.755
A44: GP: management fees received | B44: =IF(B$8>=COLUMNS($C$16:$L$16),0,INDEX($C$16:$L$16,B$8+1)) -> 270 | C44: =IF(C$8>=COLUMNS($C$16:$L$16),0,INDEX($C$16:$L$16,C$8+1)) -> 270 | D44: =IF(D$8>=COLUMNS($C$16:$L$16),0,INDEX($C$16:$L$16,D$8+1)) -> 270 | E44: =IF(E$8>=COLUMNS($C$16:$L$16),0,INDEX($C$16:$L$16,E$8+1)) -> 270 | F44: =IF(F$8>=COLUMNS($C$16:$L$16),0,INDEX($C$16:$L$16,F$8+1)) -> 270 | G44: =IF(G$8>=COLUMNS($C$16:$L$16),0,INDEX($C$16:$L$16,G$8+1)) -> 270 | H44: =IF(H$8>=COLUMNS($C$16:$L$16),0,INDEX($C$16:$L$16,H$8+1)) -> 270 | I44: =IF(I$8>=COLUMNS($C$16:$L$16),0,INDEX($C$16:$L$16,I$8+1)) -> 270 | ... L44: =IF(L$8>=COLUMNS($C$16:$L$16),0,INDEX($C$16:$L$16,L$8+1)) -> 0
A45: GP: carried interest received | B45: =IF(B$8=0,0,INDEX($C$36:$L$36,B$8)) -> 0 | C45: =IF(C$8=0,0,INDEX($C$36:$L$36,C$8)) -> 0 | D45: =IF(D$8=0,0,INDEX($C$36:$L$36,D$8)) -> 0 | E45: =IF(E$8=0,0,INDEX($C$36:$L$36,E$8)) -> 0 | F45: =IF(F$8=0,0,INDEX($C$36:$L$36,F$8)) -> 0 | G45: =IF(G$8=0,0,INDEX($C$36:$L$36,G$8)) -> 0 | H45: =IF(H$8=0,0,INDEX($C$36:$L$36,H$8)) -> 0 | I45: =IF(I$8=0,0,INDEX($C$36:$L$36,I$8)) -> 0 | ... L45: =IF(L$8=0,0,INDEX($C$36:$L$36,L$8)) -> 5132.6886
A46: GP: total compensation | B46: =B44+B45 -> 270 | C46: =C44+C45 -> 270 | D46: =D44+D45 -> 270 | E46: =E44+E45 -> 270 | F46: =F44+F45 -> 270 | G46: =G44+G45 -> 270 | H46: =H44+H45 -> 270 | I46: =I44+I45 -> 270 | ... L46: =L44+L45 -> 5132.6886
A47: OPERF: net cash flow (pro-rata share of LP) | B47: =$C$63*B43 -> -150 | C47: =$C$63*C43 -> -150 | D47: =$C$63*D43 -> -150 | E47: =$C$63*E43 -> -150 | F47: =$C$63*F43 -> -150 | G47: =$C$63*G43 -> 249.81451 | H47: =$C$63*H43 -> 237.39193 | I47: =$C$63*I43 -> 225.46625 | ... L47: =$C$63*L43 -> 769.9033
A49: Results ($ millions unless stated)
A50: LP net IRR (after fees and carry) | C50: =IRR(B43:L43,0.1) -> 0.15936141 | E50: IRR of LP net cash flows (row 43)
A51: LP NPV at the discount rate | C51: =B43+NPV($F$3,C43:L43) -> 752.97923 | E51: Positive = beats the 15% required return
A52: LP total contributions | C52: =-SUM(B41:L41) -> 20000 | E52: Includes capital later used to pay fees
A53: LP total distributions | C53: =SUM(B42:L42) -> 48631.388
A54: LP multiple of contributed capital (TVPI) | C54: =IF(C52=0,0,C53/C52) -> 2.4315694
A55: GP management fees, total (nominal) | C55: =SUM(B44:L44) -> 2700
A56: GP carried interest, total (nominal) | C56: =SUM(B45:L45) -> 7157.847
A57: PV of management fees at the discount rate | C57: =B44+NPV($F$3,C44:L44) -> 1558.3277 | E57: Fees paid at the start of each year
A58: PV of carried interest at the discount rate | C58: =B45+NPV($F$3,C45:L45) -> 1884.5797
A59: PV of total GP compensation | C59: =C57+C58 -> 3442.9073
A60: Management fees as % of GP compensation (PV) | C60: =IF(C59=0,0,C57/C59) -> 0.45261969 | E60: Fixed pay share; the rest is performance pay
A61: Gross asset return less LP net IRR (fee + carry drag) | C61: =$F$2-C50 -> 0.040638591
A62: First year the GP receives carried interest | C62: =IF(MAX(C38:L38)<=0,"None",IFERROR(INDEX(C8:L8,MATCH(0,C38:L38,1)+1),C8)) -> 8
A63: OPERF share of the fund's LP cash flows | C63: =IF($C$2=0,0,$I$4/$C$2) -> 0.0375 | E63: OPERF commitment ÷ committed capital
A64: OPERF NPV at the discount rate | C64: =C63*C51 -> 28.236721
A65: OPERF share of management fees paid (nominal) | C65: =C63*C55 -> 101.25
A66: OPERF distributions received (nominal) | C66: =C63*C53 -> 1823.6771
A68: Checks (0 = OK)
A69: NAV fully liquidated at end of Year 10 | C69: =ROUND(L24,6) -> 0
A70: Distributions = LP distributions + GP carry | C70: =ROUND(SUM(C23:L23)-SUM(C35:L35)-SUM(C36:L36),6) -> 0
A71: Distributions = takedowns − fees + asset growth | C71: =ROUND(SUM(C23:L23)-(SUM(C15:L15)-SUM(C16:L16)+SUM(C20:L20)),6) -> 0
A72: All checks | C72: =IF(ABS(C69)+ABS(C70)+ABS(C71)<0.001,"OK","CHECK") -> OK
A74: Source: Layout follows the Template sheet of the Darden supplementary spreadsheet (UV5624); waterfall, cash-flow and results rows added by the team.

Sheet Q4 Analysis
A1: Q4 — EFFECT OF TPG'S FEE CUT (1.50% → 1.35%) ON OPERF
A2: Compares sheet "Q3 Base case" (current terms) with sheet "Q4 Fee cut" (TPG offer). Everything else is held constant.
A4: A. Whole fund ($ millions)
B5: Current (1.50%) | C5: Offer (1.35%) | D5: Change
A6: LP net IRR | B6: ='Q3 Base case'!$C$50 -> 0.15722559 | C6: ='Q4 Fee cut'!$C$50 -> 0.15936141 | D6: =(C6-B6)*10000 -> 21.358143
A7: LP NPV at 15% | B7: ='Q3 Base case'!$C$51 -> 578.21714 | C7: ='Q4 Fee cut'!$C$51 -> 752.97923 | D7: =C7-B7 -> 174.76209
A8: LP distributions (nominal) | B8: ='Q3 Base case'!$C$53 -> 48070.521 | C8: ='Q4 Fee cut'!$C$53 -> 48631.388 | D8: =C8-B8 -> 560.86732
A9: LP multiple (TVPI) | B9: ='Q3 Base case'!$C$54 -> 2.403526 | C9: ='Q4 Fee cut'!$C$54 -> 2.4315694 | D9: =C9-B9 -> 0.028043366
A10: GP management fees (nominal) | B10: ='Q3 Base case'!$C$55 -> 3000 | C10: ='Q4 Fee cut'!$C$55 -> 2700 | D10: =C10-B10 -> -300 | E10: fees fall by 0.15% × $20bn × 10 years
A11: GP carried interest (nominal) | B11: ='Q3 Base case'!$C$56 -> 7017.6302 | C11: ='Q4 Fee cut'!$C$56 -> 7157.847 | D11: =C11-B11 -> 140.21683 | E11: more capital stays invested, so profits and carry rise
A12: PV of management fees | B12: ='Q3 Base case'!$C$57 -> 1731.4752 | C12: ='Q4 Fee cut'!$C$57 -> 1558.3277 | D12: =C12-B12 -> -173.14752
A13: PV of carried interest | B13: ='Q3 Base case'!$C$58 -> 1845.4937 | C13: ='Q4 Fee cut'!$C$58 -> 1884.5797 | D13: =C13-B13 -> 39.08594
A14: PV of total GP compensation | B14: ='Q3 Base case'!$C$59 -> 3576.9689 | C14: ='Q4 Fee cut'!$C$59 -> 3442.9073 | D14: =C14-B14 -> -134.06158
A16: B. OPERF's $750m commitment ($ millions)
A17: OPERF share of the fund | C17: ='Q4 Fee cut'!$C$63 -> 0.0375
A18: Annual management fee — current terms | C18: =Inputs!$C$26*Inputs!$C$18 -> 11.25
A19: Annual management fee — TPG offer | C19: =Inputs!$C$26*Inputs!$C$19 -> 10.125
A20: Annual fee saving | C20: =C18-C19 -> 1.125
A21: Fee saving over the fund life (nominal) | C21: =C20*Inputs!$C$7 -> 11.25
A22: PV of fee saving at 15% (memo) | C22: =C17*(B12-C12) -> 6.4930319
A23: PV of extra distributions (fee dollars stay invested at 20%) | C23: =C17*(NPV(Inputs!$C$9,'Q4 Fee cut'!$C$23:$L$23)-NPV(Inputs!$C$9,'Q3 Base case'!$C$23:$L$23)) -> 8.0193011 | E23: exceeds the PV of fees saved: money left in the fund grows at 20% but is discounted at 15%
A24: Less: PV of extra carried interest paid to TPG | C24: =-C17*(C13-B13) -> -1.4657228 | E24: TPG keeps 20% of the extra profit
A25: Net NPV gain to OPERF | C25: =C23+C24 -> 6.5535783
A26: Check: equals OPERF NPV change between sheets (0 = OK) | C26: =ROUND(C25-('Q4 Fee cut'!$C$64-'Q3 Base case'!$C$64),6) -> 0
A27: Net NPV gain as % of OPERF commitment | C27: =IF(Inputs!$C$26=0,0,C25/Inputs!$C$26) -> 0.0087381044
A28: LP IRR gain | C28: =D6 -> 21.358143
A30: C. Gross-to-net bridge after the fee cut (LP IRR)
B31: Gross | C31: After fees | D31: Net to LPs | E31: Fee drag | F31: Carry drag
A32: Current terms (1.50%) | B32: =Engine!$K$16 -> 0.2 | C32: =Engine!$K$17 -> 0.17804892 | D32: ='Q3 Base case'!$C$50 -> 0.15722559 | E32: =(B32-C32)*10000 -> 219.51075 | F32: =(C32-D32)*10000 -> 208.2333
A33: TPG offer (1.35%) | B33: =Engine!$K$16 -> 0.2 | C33: =Engine!$K$18 -> 0.18034964 | D33: ='Q4 Fee cut'!$C$50 -> 0.15936141 | E33: =(B33-C33)*10000 -> 196.50358 | F33: =(C33-D33)*10000 -> 209.88234
A35: D. Is the gain from the fee cut the same in good and bad outcomes?
A36: Asset growth | B36: LP IRR current | C36: LP IRR offer | D36: Gain (bps) | E36: OPERF NPV gain ($m)
A37: =Engine!$I$21 -> 0 | B37: =Engine!$K$21 -> -0.028740632 | C37: =Engine!$K$52 -> -0.025625198 | D37: =(C37-B37)*10000 -> 31.154342 | E37: =$C$17*(Engine!$L$52-Engine!$L$21) -> 3.5465952
A38: =Engine!$I$26 -> 0.05 | B38: =Engine!$K$26 -> 0.019506054 | C38: =Engine!$K$57 -> 0.021836081 | D38: =(C38-B38)*10000 -> 23.300264 | E38: =$C$17*(Engine!$L$57-Engine!$L$26) -> 3.6349356
A39: =Engine!$I$31 -> 0.1 | B39: =Engine!$K$31 -> 0.064190788 | C39: =Engine!$K$62 -> 0.066474587 | D39: =(C39-B39)*10000 -> 22.83799 | E39: =$C$17*(Engine!$L$62-Engine!$L$31) -> 4.4405712
A40: =Engine!$I$36 -> 0.15 | B40: =Engine!$K$36 -> 0.1104452 | C40: =Engine!$K$67 -> 0.11263957 | D40: =(C40-B40)*10000 -> 21.943758 | E40: =$C$17*(Engine!$L$67-Engine!$L$36) -> 5.3289503
A41: =Engine!$I$41 -> 0.2 | B41: =Engine!$K$41 -> 0.15722559 | C41: =Engine!$K$72 -> 0.15936141 | D41: =(C41-B41)*10000 -> 21.358143 | E41: =$C$17*(Engine!$L$72-Engine!$L$41) -> 6.5535783
A42: =Engine!$I$46 -> 0.25 | B42: =Engine!$K$46 -> 0.20431317 | C42: =Engine!$K$77 -> 0.20638488 | D42: =(C42-B42)*10000 -> 20.717042 | E42: =$C$17*(Engine!$L$77-Engine!$L$46) -> 8.039932
A43: =Engine!$I$51 -> 0.3 | B43: =Engine!$K$51 -> 0.25164567 | C43: =Engine!$K$82 -> 0.25369121 | D43: =(C43-B43)*10000 -> 20.455408 | E43: =$C$17*(Engine!$L$82-Engine!$L$51) -> 9.9944624
A44: The gain is small and similar in every outcome: a transfer from TPG to LPs, not a change in incentives.
A46: E. Fee cut vs the other levers OPERF could ask for (base case, LP IRR gain vs current terms)
A47: TPG offer: fee 1.35% | C47: =Summary!C12 -> 21.358143
A48: Offer + 8% hard hurdle | C48: =Summary!D12 -> 86.926301
A49: Offer + 8% soft hurdle | C49: =Summary!E12 -> 30.666435
A50: Offer + 15% carry | C50: =Summary!F12 -> 76.853883

Sheet Q5a Hard hurdle
A1: OREGON PUBLIC EMPLOYEES RETIREMENT FUND
B2: Committed capital ($ millions) | C2: =Inputs!$C$6 -> 20000 | E2: Asset growth rate (%) | F2: =Inputs!$C$8 -> 0.2 | H2: Hurdle rate (%) | I2: =Inputs!$C$22 -> 0.08
B3: Management fee (%) | C3: =Inputs!$C$19 -> 0.0135 | E3: Discount rate (%) | F3: =Inputs!$C$9 -> 0.15 | H3: GP catch-up (1 = yes) | I3: 0
B4: LP share of profit (%) | C4: =1-F4 -> 0.8 | E4: GP share of profit (%) | F4: =Inputs!$C$20 -> 0.2 | H4: OPERF ($ millions) | I4: =Inputs!$C$26 -> 750
A6: ="Scenario: "&"TPG offer + hard hurdle — "&TEXT(C3,"0.00%")&" fee on committed capital, "&TEXT(F4,"0%")&" carry, "&IF(I2=0,"no hurdle",TEXT(I2,"0%")&" hurdle"&IF(I3=1," with 100% GP catch-up (soft)"," with no catch-up (hard)")) -> Scenario: TPG offer + hard hurdle — 1.35% fee on committed capital, 20% carry, 8% hurdle with no catch-up (hard) | J6: Prep Q5 — 8% hurdle, no catch-up
A8: Year | B8: 0 | C8: 1 | D8: 2 | E8: 3 | F8: 4 | G8: 5 | H8: 6 | I8: 7 | J8: 8 | K8: 9 | L8: 10
A9: Assumptions
A10: % Drawn of committed capital | C10: =Inputs!C$13 -> 0.2 | D10: =Inputs!D$13 -> 0.2 | E10: =Inputs!E$13 -> 0.2 | F10: =Inputs!F$13 -> 0.2 | G10: =Inputs!G$13 -> 0.2 | H10: =Inputs!H$13 -> 0 | I10: =Inputs!I$13 -> 0 | J10: =Inputs!J$13 -> 0 | ... L10: =Inputs!L$13 -> 0
A11: Distribution rate | C11: =Inputs!C$14 -> 0 | D11: =Inputs!D$14 -> 0 | E11: =Inputs!E$14 -> 0 | F11: =Inputs!F$14 -> 0 | G11: =Inputs!G$14 -> 0.2 | H11: =Inputs!H$14 -> 0.2 | I11: =Inputs!I$14 -> 0.2 | J11: =Inputs!J$14 -> 0.2 | ... L11: =Inputs!L$14 -> 1
A13: At the beginning of the year
A14: Assets | C14: =B24 -> 0 | D14: =C24 -> 4476 | E14: =D24 -> 9847.2 | F14: =E24 -> 16292.64 | G14: =F24 -> 24027.168 | H14: =G24 -> 26646.881 | I14: =H24 -> 25321.806 | J14: =I24 -> 24049.734 | ... L14: =K24 -> 21656.203
A15: Plus: Takedown | C15: =$C$2*C10 -> 4000 | D15: =$C$2*D10 -> 4000 | E15: =$C$2*E10 -> 4000 | F15: =$C$2*F10 -> 4000 | G15: =$C$2*G10 -> 4000 | H15: =$C$2*H10 -> 0 | I15: =$C$2*I10 -> 0 | J15: =$C$2*J10 -> 0 | ... L15: =$C$2*L10 -> 0
A16: Less: Management fee | C16: =$C$2*$C$3 -> 270 | D16: =$C$2*$C$3 -> 270 | E16: =$C$2*$C$3 -> 270 | F16: =$C$2*$C$3 -> 270 | G16: =$C$2*$C$3 -> 270 | H16: =$C$2*$C$3 -> 270 | I16: =$C$2*$C$3 -> 270 | J16: =$C$2*$C$3 -> 270 | ... L16: =$C$2*$C$3 -> 270
A17: Invested capital per period | C17: =C14+C15-C16 -> 3730 | D17: =D14+D15-D16 -> 8206 | E17: =E14+E15-E16 -> 13577.2 | F17: =F14+F15-F16 -> 20022.64 | G17: =G14+G15-G16 -> 27757.168 | H17: =H14+H15-H16 -> 26376.881 | I17: =I14+I15-I16 -> 25051.806 | J17: =J14+J15-J16 -> 23779.734 | ... L17: =L14+L15-L16 -> 21386.203
A19: At the end of the year
A20: Plus: Asset growth over year | C20: =C17*$F$2 -> 746 | D20: =D17*$F$2 -> 1641.2 | E20: =E17*$F$2 -> 2715.44 | F20: =F17*$F$2 -> 4004.528 | G20: =G17*$F$2 -> 5551.4336 | H20: =H17*$F$2 -> 5275.3763 | I20: =I17*$F$2 -> 5010.3612 | J20: =J17*$F$2 -> 4755.9468 | ... L20: =L17*$F$2 -> 4277.2405
A21: NAV before distributions | C21: =C17+C20 -> 4476 | D21: =D17+D20 -> 9847.2 | E21: =E17+E20 -> 16292.64 | F21: =F17+F20 -> 24027.168 | G21: =G17+G20 -> 33308.602 | H21: =H17+H20 -> 31652.258 | I21: =I17+I20 -> 30062.167 | J21: =J17+J20 -> 28535.681 | ... L21: =L17+L20 -> 25663.443
A23: Less: Distributions | C23: =C21*C11 -> 0 | D23: =D21*D11 -> 0 | E23: =E21*E11 -> 0 | F23: =F21*F11 -> 0 | G23: =G21*G11 -> 6661.7203 | H23: =H21*H11 -> 6330.4515 | I23: =I21*I11 -> 6012.4334 | J23: =J21*J11 -> 5707.1361 | ... L23: =L21*L11 -> 25663.443
A24: NAV after distributions | C24: =C21-C23 -> 4476 | D24: =D21-D23 -> 9847.2 | E24: =E21-E23 -> 16292.64 | F24: =F21-F23 -> 24027.168 | G24: =G21-G23 -> 26646.881 | H24: =H21-H23 -> 25321.806 | I24: =I21-I23 -> 24049.734 | J24: =J21-J23 -> 22828.544 | ... L24: =L21-L23 -> 0
A26: Distribution waterfall (whole-fund carry: LPs made whole first)
A27: Unreturned LP capital, incl. this year's takedown | C27: =B29+C15 -> 4000 | D27: =C29+D15 -> 8000 | E27: =D29+E15 -> 12000 | F27: =E29+F15 -> 16000 | G27: =F29+G15 -> 20000 | H27: =G29+H15 -> 13338.28 | I27: =H29+I15 -> 7007.8282 | J27: =I29+J15 -> 995.39473 | ... L27: =K29+L15 -> 0
A28: Tier 1 – Return of capital to LPs | C28: =MIN(C23,C27) -> 0 | D28: =MIN(D23,D27) -> 0 | E28: =MIN(E23,E27) -> 0 | F28: =MIN(F23,F27) -> 0 | G28: =MIN(G23,G27) -> 6661.7203 | H28: =MIN(H23,H27) -> 6330.4515 | I28: =MIN(I23,I27) -> 6012.4334 | J28: =MIN(J23,J27) -> 995.39473 | ... L28: =MIN(L23,L27) -> 0
A29: Unreturned LP capital, end of year | C29: =C27-C28 -> 4000 | D29: =D27-D28 -> 8000 | E29: =E27-E28 -> 12000 | F29: =F27-F28 -> 16000 | G29: =G27-G28 -> 13338.28 | H29: =H27-H28 -> 7007.8282 | I29: =I27-I28 -> 995.39473 | J29: =J27-J28 -> 0 | ... L29: =L27-L28 -> 0
A30: Preferred return due (hurdle accrual + unpaid) | C30: =B32+$I$2*(C27+B32) -> 320 | D30: =C32+$I$2*(D27+C32) -> 985.6 | E30: =D32+$I$2*(E27+D32) -> 2024.448 | F30: =E32+$I$2*(F27+E32) -> 3466.4038 | G30: =F32+$I$2*(G27+F32) -> 5343.7161 | H30: =G32+$I$2*(H27+G32) -> 6838.2758 | I30: =H32+$I$2*(I27+H32) -> 7945.9641 | J30: =I32+$I$2*(J27+I32) -> 8661.2728 | ... L30: =K32+$I$2*(L27+K32) -> 0
A31: Tier 2 – Preferred return paid to LPs | C31: =MIN(C23-C28,C30) -> 0 | D31: =MIN(D23-D28,D30) -> 0 | E31: =MIN(E23-E28,E30) -> 0 | F31: =MIN(F23-F28,F30) -> 0 | G31: =MIN(G23-G28,G30) -> 0 | H31: =MIN(H23-H28,H30) -> 0 | I31: =MIN(I23-I28,I30) -> 0 | J31: =MIN(J23-J28,J30) -> 4711.7414 | ... L31: =MIN(L23-L28,L30) -> 0
A32: Unpaid preferred return, end of year | C32: =C30-C31 -> 320 | D32: =D30-D31 -> 985.6 | E32: =E30-E31 -> 2024.448 | F32: =F30-F31 -> 3466.4038 | G32: =G30-G31 -> 5343.7161 | H32: =H30-H31 -> 6838.2758 | I32: =I30-I31 -> 7945.9641 | J32: =J30-J31 -> 3949.5315 | ... L32: =L30-L31 -> 0
A33: Tier 3 – GP catch-up (soft hurdle only) | C33: =IF($I$3=1,MIN(C23-C28-C31,MAX(0,$F$4/(1-$F$4)*(B37+C31)-B38)),0) -> 0 | D33: =IF($I$3=1,MIN(D23-D28-D31,MAX(0,$F$4/(1-$F$4)*(C37+D31)-C38)),0) -> 0 | E33: =IF($I$3=1,MIN(E23-E28-E31,MAX(0,$F$4/(1-$F$4)*(D37+E31)-D38)),0) -> 0 | F33: =IF($I$3=1,MIN(F23-F28-F31,MAX(0,$F$4/(1-$F$4)*(E37+F31)-E38)),0) -> 0 | G33: =IF($I$3=1,MIN(G23-G28-G31,MAX(0,$F$4/(1-$F$4)*(F37+G31)-F38)),0) -> 0 | H33: =IF($I$3=1,MIN(H23-H28-H31,MAX(0,$F$4/(1-$F$4)*(G37+H31)-G38)),0) -> 0 | I33: =IF($I$3=1,MIN(I23-I28-I31,MAX(0,$F$4/(1-$F$4)*(H37+I31)-H38)),0) -> 0 | J33: =IF($I$3=1,MIN(J23-J28-J31,MAX(0,$F$4/(1-$F$4)*(I37+J31)-I38)),0) -> 0 | ... L33: =IF($I$3=1,MIN(L23-L28-L31,MAX(0,$F$4/(1-$F$4)*(K37+L31)-K38)),0) -> 0
A34: Tier 4 – Remaining profit split LP/GP | C34: =C23-C28-C31-C33 -> 0 | D34: =D23-D28-D31-D33 -> 0 | E34: =E23-E28-E31-E33 -> 0 | F34: =F23-F28-F31-F33 -> 0 | G34: =G23-G28-G31-G33 -> 0 | H34: =H23-H28-H31-H33 -> 0 | I34: =I23-I28-I31-I33 -> 0 | J34: =J23-J28-J31-J33 -> 0 | ... L34: =L23-L28-L31-L33 -> 25663.443
A35: Total distributions to LPs | C35: =C28+C31+$C$4*C34 -> 0 | D35: =D28+D31+$C$4*D34 -> 0 | E35: =E28+E31+$C$4*E34 -> 0 | F35: =F28+F31+$C$4*F34 -> 0 | G35: =G28+G31+$C$4*G34 -> 6661.7203 | H35: =H28+H31+$C$4*H34 -> 6330.4515 | I35: =I28+I31+$C$4*I34 -> 6012.4334 | J35: =J28+J31+$C$4*J34 -> 5707.1361 | ... L35: =L28+L31+$C$4*L34 -> 20530.755
A36: Total carried interest to GP | C36: =C33+$F$4*C34 -> 0 | D36: =D33+$F$4*D34 -> 0 | E36: =E33+$F$4*E34 -> 0 | F36: =F33+$F$4*F34 -> 0 | G36: =G33+$F$4*G34 -> 0 | H36: =H33+$F$4*H34 -> 0 | I36: =I33+$F$4*I34 -> 0 | J36: =J33+$F$4*J34 -> 0 | ... L36: =L33+$F$4*L34 -> 5132.6886
A37: Cumulative LP profit received | C37: =B37+C31+$C$4*C34 -> 0 | D37: =C37+D31+$C$4*D34 -> 0 | E37: =D37+E31+$C$4*E34 -> 0 | F37: =E37+F31+$C$4*F34 -> 0 | G37: =F37+G31+$C$4*G34 -> 0 | H37: =G37+H31+$C$4*H34 -> 0 | I37: =H37+I31+$C$4*I34 -> 0 | J37: =I37+J31+$C$4*J34 -> 4711.7414 | ... L37: =K37+L31+$C$4*L34 -> 30426.835
A38: Cumulative GP carried interest | C38: =B38+C36 -> 0 | D38: =C38+D36 -> 0 | E38: =D38+E36 -> 0 | F38: =E38+F36 -> 0 | G38: =F38+G36 -> 0 | H38: =G38+H36 -> 0 | I38: =H38+I36 -> 0 | J38: =I38+J36 -> 0 | ... L38: =K38+L36 -> 5362.4
A40: Cash flows by date (column = point in time t: the start of Year n is t = n − 1; the end of Year n is t = n)
A41: LP: capital calls (takedowns) | B41: =IF(B$8>=COLUMNS($C$15:$L$15),0,-INDEX($C$15:$L$15,B$8+1)) -> -4000 | C41: =IF(C$8>=COLUMNS($C$15:$L$15),0,-INDEX($C$15:$L$15,C$8+1)) -> -4000 | D41: =IF(D$8>=COLUMNS($C$15:$L$15),0,-INDEX($C$15:$L$15,D$8+1)) -> -4000 | E41: =IF(E$8>=COLUMNS($C$15:$L$15),0,-INDEX($C$15:$L$15,E$8+1)) -> -4000 | F41: =IF(F$8>=COLUMNS($C$15:$L$15),0,-INDEX($C$15:$L$15,F$8+1)) -> -4000 | G41: =IF(G$8>=COLUMNS($C$15:$L$15),0,-INDEX($C$15:$L$15,G$8+1)) -> 0 | H41: =IF(H$8>=COLUMNS($C$15:$L$15),0,-INDEX($C$15:$L$15,H$8+1)) -> 0 | I41: =IF(I$8>=COLUMNS($C$15:$L$15),0,-INDEX($C$15:$L$15,I$8+1)) -> 0 | ... L41: =IF(L$8>=COLUMNS($C$15:$L$15),0,-INDEX($C$15:$L$15,L$8+1)) -> 0
A42: LP: distributions received | B42: =IF(B$8=0,0,INDEX($C$35:$L$35,B$8)) -> 0 | C42: =IF(C$8=0,0,INDEX($C$35:$L$35,C$8)) -> 0 | D42: =IF(D$8=0,0,INDEX($C$35:$L$35,D$8)) -> 0 | E42: =IF(E$8=0,0,INDEX($C$35:$L$35,E$8)) -> 0 | F42: =IF(F$8=0,0,INDEX($C$35:$L$35,F$8)) -> 0 | G42: =IF(G$8=0,0,INDEX($C$35:$L$35,G$8)) -> 6661.7203 | H42: =IF(H$8=0,0,INDEX($C$35:$L$35,H$8)) -> 6330.4515 | I42: =IF(I$8=0,0,INDEX($C$35:$L$35,I$8)) -> 6012.4334 | ... L42: =IF(L$8=0,0,INDEX($C$35:$L$35,L$8)) -> 20530.755
A43: LP: net cash flow | B43: =B41+B42 -> -4000 | C43: =C41+C42 -> -4000 | D43: =D41+D42 -> -4000 | E43: =E41+E42 -> -4000 | F43: =F41+F42 -> -4000 | G43: =G41+G42 -> 6661.7203 | H43: =H41+H42 -> 6330.4515 | I43: =I41+I42 -> 6012.4334 | ... L43: =L41+L42 -> 20530.755
A44: GP: management fees received | B44: =IF(B$8>=COLUMNS($C$16:$L$16),0,INDEX($C$16:$L$16,B$8+1)) -> 270 | C44: =IF(C$8>=COLUMNS($C$16:$L$16),0,INDEX($C$16:$L$16,C$8+1)) -> 270 | D44: =IF(D$8>=COLUMNS($C$16:$L$16),0,INDEX($C$16:$L$16,D$8+1)) -> 270 | E44: =IF(E$8>=COLUMNS($C$16:$L$16),0,INDEX($C$16:$L$16,E$8+1)) -> 270 | F44: =IF(F$8>=COLUMNS($C$16:$L$16),0,INDEX($C$16:$L$16,F$8+1)) -> 270 | G44: =IF(G$8>=COLUMNS($C$16:$L$16),0,INDEX($C$16:$L$16,G$8+1)) -> 270 | H44: =IF(H$8>=COLUMNS($C$16:$L$16),0,INDEX($C$16:$L$16,H$8+1)) -> 270 | I44: =IF(I$8>=COLUMNS($C$16:$L$16),0,INDEX($C$16:$L$16,I$8+1)) -> 270 | ... L44: =IF(L$8>=COLUMNS($C$16:$L$16),0,INDEX($C$16:$L$16,L$8+1)) -> 0
A45: GP: carried interest received | B45: =IF(B$8=0,0,INDEX($C$36:$L$36,B$8)) -> 0 | C45: =IF(C$8=0,0,INDEX($C$36:$L$36,C$8)) -> 0 | D45: =IF(D$8=0,0,INDEX($C$36:$L$36,D$8)) -> 0 | E45: =IF(E$8=0,0,INDEX($C$36:$L$36,E$8)) -> 0 | F45: =IF(F$8=0,0,INDEX($C$36:$L$36,F$8)) -> 0 | G45: =IF(G$8=0,0,INDEX($C$36:$L$36,G$8)) -> 0 | H45: =IF(H$8=0,0,INDEX($C$36:$L$36,H$8)) -> 0 | I45: =IF(I$8=0,0,INDEX($C$36:$L$36,I$8)) -> 0 | ... L45: =IF(L$8=0,0,INDEX($C$36:$L$36,L$8)) -> 5132.6886
A46: GP: total compensation | B46: =B44+B45 -> 270 | C46: =C44+C45 -> 270 | D46: =D44+D45 -> 270 | E46: =E44+E45 -> 270 | F46: =F44+F45 -> 270 | G46: =G44+G45 -> 270 | H46: =H44+H45 -> 270 | I46: =I44+I45 -> 270 | ... L46: =L44+L45 -> 5132.6886
A47: OPERF: net cash flow (pro-rata share of LP) | B47: =$C$63*B43 -> -150 | C47: =$C$63*C43 -> -150 | D47: =$C$63*D43 -> -150 | E47: =$C$63*E43 -> -150 | F47: =$C$63*F43 -> -150 | G47: =$C$63*G43 -> 249.81451 | H47: =$C$63*H43 -> 237.39193 | I47: =$C$63*I43 -> 225.46625 | ... L47: =$C$63*L43 -> 769.9033
A49: Results ($ millions unless stated)
A50: LP net IRR (after fees and carry) | C50: =IRR(B43:L43,0.1) -> 0.16591822 | E50: IRR of LP net cash flows (row 43)
A51: LP NPV at the discount rate | C51: =B43+NPV($F$3,C43:L43) -> 1303.5385 | E51: Positive = beats the 15% required return
A52: LP total contributions | C52: =-SUM(B41:L41) -> 20000 | E52: Includes capital later used to pay fees
A53: LP total distributions | C53: =SUM(B42:L42) -> 50426.835
A54: LP multiple of contributed capital (TVPI) | C54: =IF(C52=0,0,C53/C52) -> 2.5213418
A55: GP management fees, total (nominal) | C55: =SUM(B44:L44) -> 2700
A56: GP carried interest, total (nominal) | C56: =SUM(B45:L45) -> 5362.4
A57: PV of management fees at the discount rate | C57: =B44+NPV($F$3,C44:L44) -> 1558.3277 | E57: Fees paid at the start of each year
A58: PV of carried interest at the discount rate | C58: =B45+NPV($F$3,C45:L45) -> 1334.0204
A59: PV of total GP compensation | C59: =C57+C58 -> 2892.3481
A60: Management fees as % of GP compensation (PV) | C60: =IF(C59=0,0,C57/C59) -> 0.53877597 | E60: Fixed pay share; the rest is performance pay
A61: Gross asset return less LP net IRR (fee + carry drag) | C61: =$F$2-C50 -> 0.034081776
A62: First year the GP receives carried interest | C62: =IF(MAX(C38:L38)<=0,"None",IFERROR(INDEX(C8:L8,MATCH(0,C38:L38,1)+1),C8)) -> 9
A63: OPERF share of the fund's LP cash flows | C63: =IF($C$2=0,0,$I$4/$C$2) -> 0.0375 | E63: OPERF commitment ÷ committed capital
A64: OPERF NPV at the discount rate | C64: =C63*C51 -> 48.882693
A65: OPERF share of management fees paid (nominal) | C65: =C63*C55 -> 101.25
A66: OPERF distributions received (nominal) | C66: =C63*C53 -> 1891.0063
A68: Checks (0 = OK)
A69: NAV fully liquidated at end of Year 10 | C69: =ROUND(L24,6) -> 0
A70: Distributions = LP distributions + GP carry | C70: =ROUND(SUM(C23:L23)-SUM(C35:L35)-SUM(C36:L36),6) -> 0
A71: Distributions = takedowns − fees + asset growth | C71: =ROUND(SUM(C23:L23)-(SUM(C15:L15)-SUM(C16:L16)+SUM(C20:L20)),6) -> 0
A72: All checks | C72: =IF(ABS(C69)+ABS(C70)+ABS(C71)<0.001,"OK","CHECK") -> OK
A74: Source: Layout follows the Template sheet of the Darden supplementary spreadsheet (UV5624); waterfall, cash-flow and results rows added by the team.

Sheet Q5b Soft hurdle
A1: OREGON PUBLIC EMPLOYEES RETIREMENT FUND
B2: Committed capital ($ millions) | C2: =Inputs!$C$6 -> 20000 | E2: Asset growth rate (%) | F2: =Inputs!$C$8 -> 0.2 | H2: Hurdle rate (%) | I2: =Inputs!$C$22 -> 0.08
B3: Management fee (%) | C3: =Inputs!$C$19 -> 0.0135 | E3: Discount rate (%) | F3: =Inputs!$C$9 -> 0.15 | H3: GP catch-up (1 = yes) | I3: =Inputs!$C$23 -> 1
B4: LP share of profit (%) | C4: =1-F4 -> 0.8 | E4: GP share of profit (%) | F4: =Inputs!$C$20 -> 0.2 | H4: OPERF ($ millions) | I4: =Inputs!$C$26 -> 750
A6: ="Scenario: "&"TPG offer + soft hurdle — "&TEXT(C3,"0.00%")&" fee on committed capital, "&TEXT(F4,"0%")&" carry, "&IF(I2=0,"no hurdle",TEXT(I2,"0%")&" hurdle"&IF(I3=1," with 100% GP catch-up (soft)"," with no catch-up (hard)")) -> Scenario: TPG offer + soft hurdle — 1.35% fee on committed capital, 20% carry, 8% hurdle with 100% GP catch-up (soft) | J6: Prep Q5 — 8% hurdle with GP catch-up
A8: Year | B8: 0 | C8: 1 | D8: 2 | E8: 3 | F8: 4 | G8: 5 | H8: 6 | I8: 7 | J8: 8 | K8: 9 | L8: 10
A9: Assumptions
A10: % Drawn of committed capital | C10: =Inputs!C$13 -> 0.2 | D10: =Inputs!D$13 -> 0.2 | E10: =Inputs!E$13 -> 0.2 | F10: =Inputs!F$13 -> 0.2 | G10: =Inputs!G$13 -> 0.2 | H10: =Inputs!H$13 -> 0 | I10: =Inputs!I$13 -> 0 | J10: =Inputs!J$13 -> 0 | ... L10: =Inputs!L$13 -> 0
A11: Distribution rate | C11: =Inputs!C$14 -> 0 | D11: =Inputs!D$14 -> 0 | E11: =Inputs!E$14 -> 0 | F11: =Inputs!F$14 -> 0 | G11: =Inputs!G$14 -> 0.2 | H11: =Inputs!H$14 -> 0.2 | I11: =Inputs!I$14 -> 0.2 | J11: =Inputs!J$14 -> 0.2 | ... L11: =Inputs!L$14 -> 1
A13: At the beginning of the year
A14: Assets | C14: =B24 -> 0 | D14: =C24 -> 4476 | E14: =D24 -> 9847.2 | F14: =E24 -> 16292.64 | G14: =F24 -> 24027.168 | H14: =G24 -> 26646.881 | I14: =H24 -> 25321.806 | J14: =I24 -> 24049.734 | ... L14: =K24 -> 21656.203
A15: Plus: Takedown | C15: =$C$2*C10 -> 4000 | D15: =$C$2*D10 -> 4000 | E15: =$C$2*E10 -> 4000 | F15: =$C$2*F10 -> 4000 | G15: =$C$2*G10 -> 4000 | H15: =$C$2*H10 -> 0 | I15: =$C$2*I10 -> 0 | J15: =$C$2*J10 -> 0 | ... L15: =$C$2*L10 -> 0
A16: Less: Management fee | C16: =$C$2*$C$3 -> 270 | D16: =$C$2*$C$3 -> 270 | E16: =$C$2*$C$3 -> 270 | F16: =$C$2*$C$3 -> 270 | G16: =$C$2*$C$3 -> 270 | H16: =$C$2*$C$3 -> 270 | I16: =$C$2*$C$3 -> 270 | J16: =$C$2*$C$3 -> 270 | ... L16: =$C$2*$C$3 -> 270
A17: Invested capital per period | C17: =C14+C15-C16 -> 3730 | D17: =D14+D15-D16 -> 8206 | E17: =E14+E15-E16 -> 13577.2 | F17: =F14+F15-F16 -> 20022.64 | G17: =G14+G15-G16 -> 27757.168 | H17: =H14+H15-H16 -> 26376.881 | I17: =I14+I15-I16 -> 25051.806 | J17: =J14+J15-J16 -> 23779.734 | ... L17: =L14+L15-L16 -> 21386.203
A19: At the end of the year
A20: Plus: Asset growth over year | C20: =C17*$F$2 -> 746 | D20: =D17*$F$2 -> 1641.2 | E20: =E17*$F$2 -> 2715.44 | F20: =F17*$F$2 -> 4004.528 | G20: =G17*$F$2 -> 5551.4336 | H20: =H17*$F$2 -> 5275.3763 | I20: =I17*$F$2 -> 5010.3612 | J20: =J17*$F$2 -> 4755.9468 | ... L20: =L17*$F$2 -> 4277.2405
A21: NAV before distributions | C21: =C17+C20 -> 4476 | D21: =D17+D20 -> 9847.2 | E21: =E17+E20 -> 16292.64 | F21: =F17+F20 -> 24027.168 | G21: =G17+G20 -> 33308.602 | H21: =H17+H20 -> 31652.258 | I21: =I17+I20 -> 30062.167 | J21: =J17+J20 -> 28535.681 | ... L21: =L17+L20 -> 25663.443
A23: Less: Distributions | C23: =C21*C11 -> 0 | D23: =D21*D11 -> 0 | E23: =E21*E11 -> 0 | F23: =F21*F11 -> 0 | G23: =G21*G11 -> 6661.7203 | H23: =H21*H11 -> 6330.4515 | I23: =I21*I11 -> 6012.4334 | J23: =J21*J11 -> 5707.1361 | ... L23: =L21*L11 -> 25663.443
A24: NAV after distributions | C24: =C21-C23 -> 4476 | D24: =D21-D23 -> 9847.2 | E24: =E21-E23 -> 16292.64 | F24: =F21-F23 -> 24027.168 | G24: =G21-G23 -> 26646.881 | H24: =H21-H23 -> 25321.806 | I24: =I21-I23 -> 24049.734 | J24: =J21-J23 -> 22828.544 | ... L24: =L21-L23 -> 0
A26: Distribution waterfall (whole-fund carry: LPs made whole first)
A27: Unreturned LP capital, incl. this year's takedown | C27: =B29+C15 -> 4000 | D27: =C29+D15 -> 8000 | E27: =D29+E15 -> 12000 | F27: =E29+F15 -> 16000 | G27: =F29+G15 -> 20000 | H27: =G29+H15 -> 13338.28 | I27: =H29+I15 -> 7007.8282 | J27: =I29+J15 -> 995.39473 | ... L27: =K29+L15 -> 0
A28: Tier 1 – Return of capital to LPs | C28: =MIN(C23,C27) -> 0 | D28: =MIN(D23,D27) -> 0 | E28: =MIN(E23,E27) -> 0 | F28: =MIN(F23,F27) -> 0 | G28: =MIN(G23,G27) -> 6661.7203 | H28: =MIN(H23,H27) -> 6330.4515 | I28: =MIN(I23,I27) -> 6012.4334 | J28: =MIN(J23,J27) -> 995.39473 | ... L28: =MIN(L23,L27) -> 0
A29: Unreturned LP capital, end of year | C29: =C27-C28 -> 4000 | D29: =D27-D28 -> 8000 | E29: =E27-E28 -> 12000 | F29: =F27-F28 -> 16000 | G29: =G27-G28 -> 13338.28 | H29: =H27-H28 -> 7007.8282 | I29: =I27-I28 -> 995.39473 | J29: =J27-J28 -> 0 | ... L29: =L27-L28 -> 0
A30: Preferred return due (hurdle accrual + unpaid) | C30: =B32+$I$2*(C27+B32) -> 320 | D30: =C32+$I$2*(D27+C32) -> 985.6 | E30: =D32+$I$2*(E27+D32) -> 2024.448 | F30: =E32+$I$2*(F27+E32) -> 3466.4038 | G30: =F32+$I$2*(G27+F32) -> 5343.7161 | H30: =G32+$I$2*(H27+G32) -> 6838.2758 | I30: =H32+$I$2*(I27+H32) -> 7945.9641 | J30: =I32+$I$2*(J27+I32) -> 8661.2728 | ... L30: =K32+$I$2*(L27+K32) -> 0
A31: Tier 2 – Preferred return paid to LPs | C31: =MIN(C23-C28,C30) -> 0 | D31: =MIN(D23-D28,D30) -> 0 | E31: =MIN(E23-E28,E30) -> 0 | F31: =MIN(F23-F28,F30) -> 0 | G31: =MIN(G23-G28,G30) -> 0 | H31: =MIN(H23-H28,H30) -> 0 | I31: =MIN(I23-I28,I30) -> 0 | J31: =MIN(J23-J28,J30) -> 4711.7414 | ... L31: =MIN(L23-L28,L30) -> 0
A32: Unpaid preferred return, end of year | C32: =C30-C31 -> 320 | D32: =D30-D31 -> 985.6 | E32: =E30-E31 -> 2024.448 | F32: =F30-F31 -> 3466.4038 | G32: =G30-G31 -> 5343.7161 | H32: =H30-H31 -> 6838.2758 | I32: =I30-I31 -> 7945.9641 | J32: =J30-J31 -> 3949.5315 | ... L32: =L30-L31 -> 0
A33: Tier 3 – GP catch-up (soft hurdle only) | C33: =IF($I$3=1,MIN(C23-C28-C31,MAX(0,$F$4/(1-$F$4)*(B37+C31)-B38)),0) -> 0 | D33: =IF($I$3=1,MIN(D23-D28-D31,MAX(0,$F$4/(1-$F$4)*(C37+D31)-C38)),0) -> 0 | E33: =IF($I$3=1,MIN(E23-E28-E31,MAX(0,$F$4/(1-$F$4)*(D37+E31)-D38)),0) -> 0 | F33: =IF($I$3=1,MIN(F23-F28-F31,MAX(0,$F$4/(1-$F$4)*(E37+F31)-E38)),0) -> 0 | G33: =IF($I$3=1,MIN(G23-G28-G31,MAX(0,$F$4/(1-$F$4)*(F37+G31)-F38)),0) -> 0 | H33: =IF($I$3=1,MIN(H23-H28-H31,MAX(0,$F$4/(1-$F$4)*(G37+H31)-G38)),0) -> 0 | I33: =IF($I$3=1,MIN(I23-I28-I31,MAX(0,$F$4/(1-$F$4)*(H37+I31)-H38)),0) -> 0 | J33: =IF($I$3=1,MIN(J23-J28-J31,MAX(0,$F$4/(1-$F$4)*(I37+J31)-I38)),0) -> 0 | ... L33: =IF($I$3=1,MIN(L23-L28-L31,MAX(0,$F$4/(1-$F$4)*(K37+L31)-K38)),0) -> 1095.7521
A34: Tier 4 – Remaining profit split LP/GP | C34: =C23-C28-C31-C33 -> 0 | D34: =D23-D28-D31-D33 -> 0 | E34: =E23-E28-E31-E33 -> 0 | F34: =F23-F28-F31-F33 -> 0 | G34: =G23-G28-G31-G33 -> 0 | H34: =H23-H28-H31-H33 -> 0 | I34: =I23-I28-I31-I33 -> 0 | J34: =J23-J28-J31-J33 -> 0 | ... L34: =L23-L28-L31-L33 -> 24567.691
A35: Total distributions to LPs | C35: =C28+C31+$C$4*C34 -> 0 | D35: =D28+D31+$C$4*D34 -> 0 | E35: =E28+E31+$C$4*E34 -> 0 | F35: =F28+F31+$C$4*F34 -> 0 | G35: =G28+G31+$C$4*G34 -> 6661.7203 | H35: =H28+H31+$C$4*H34 -> 6330.4515 | I35: =I28+I31+$C$4*I34 -> 6012.4334 | J35: =J28+J31+$C$4*J34 -> 5707.1361 | ... L35: =L28+L31+$C$4*L34 -> 19654.153
A36: Total carried interest to GP | C36: =C33+$F$4*C34 -> 0 | D36: =D33+$F$4*D34 -> 0 | E36: =E33+$F$4*E34 -> 0 | F36: =F33+$F$4*F34 -> 0 | G36: =G33+$F$4*G34 -> 0 | H36: =H33+$F$4*H34 -> 0 | I36: =I33+$F$4*I34 -> 0 | J36: =J33+$F$4*J34 -> 0 | ... L36: =L33+$F$4*L34 -> 6009.2904
A37: Cumulative LP profit received | C37: =B37+C31+$C$4*C34 -> 0 | D37: =C37+D31+$C$4*D34 -> 0 | E37: =D37+E31+$C$4*E34 -> 0 | F37: =E37+F31+$C$4*F34 -> 0 | G37: =F37+G31+$C$4*G34 -> 0 | H37: =G37+H31+$C$4*H34 -> 0 | I37: =H37+I31+$C$4*I34 -> 0 | J37: =I37+J31+$C$4*J34 -> 4711.7414 | ... L37: =K37+L31+$C$4*L34 -> 28631.388
A38: Cumulative GP carried interest | C38: =B38+C36 -> 0 | D38: =C38+D36 -> 0 | E38: =D38+E36 -> 0 | F38: =E38+F36 -> 0 | G38: =F38+G36 -> 0 | H38: =G38+H36 -> 0 | I38: =H38+I36 -> 0 | J38: =I38+J36 -> 0 | ... L38: =K38+L36 -> 7157.847
A40: Cash flows by date (column = point in time t: the start of Year n is t = n − 1; the end of Year n is t = n)
A41: LP: capital calls (takedowns) | B41: =IF(B$8>=COLUMNS($C$15:$L$15),0,-INDEX($C$15:$L$15,B$8+1)) -> -4000 | C41: =IF(C$8>=COLUMNS($C$15:$L$15),0,-INDEX($C$15:$L$15,C$8+1)) -> -4000 | D41: =IF(D$8>=COLUMNS($C$15:$L$15),0,-INDEX($C$15:$L$15,D$8+1)) -> -4000 | E41: =IF(E$8>=COLUMNS($C$15:$L$15),0,-INDEX($C$15:$L$15,E$8+1)) -> -4000 | F41: =IF(F$8>=COLUMNS($C$15:$L$15),0,-INDEX($C$15:$L$15,F$8+1)) -> -4000 | G41: =IF(G$8>=COLUMNS($C$15:$L$15),0,-INDEX($C$15:$L$15,G$8+1)) -> 0 | H41: =IF(H$8>=COLUMNS($C$15:$L$15),0,-INDEX($C$15:$L$15,H$8+1)) -> 0 | I41: =IF(I$8>=COLUMNS($C$15:$L$15),0,-INDEX($C$15:$L$15,I$8+1)) -> 0 | ... L41: =IF(L$8>=COLUMNS($C$15:$L$15),0,-INDEX($C$15:$L$15,L$8+1)) -> 0
A42: LP: distributions received | B42: =IF(B$8=0,0,INDEX($C$35:$L$35,B$8)) -> 0 | C42: =IF(C$8=0,0,INDEX($C$35:$L$35,C$8)) -> 0 | D42: =IF(D$8=0,0,INDEX($C$35:$L$35,D$8)) -> 0 | E42: =IF(E$8=0,0,INDEX($C$35:$L$35,E$8)) -> 0 | F42: =IF(F$8=0,0,INDEX($C$35:$L$35,F$8)) -> 0 | G42: =IF(G$8=0,0,INDEX($C$35:$L$35,G$8)) -> 6661.7203 | H42: =IF(H$8=0,0,INDEX($C$35:$L$35,H$8)) -> 6330.4515 | I42: =IF(I$8=0,0,INDEX($C$35:$L$35,I$8)) -> 6012.4334 | ... L42: =IF(L$8=0,0,INDEX($C$35:$L$35,L$8)) -> 19654.153
A43: LP: net cash flow | B43: =B41+B42 -> -4000 | C43: =C41+C42 -> -4000 | D43: =D41+D42 -> -4000 | E43: =E41+E42 -> -4000 | F43: =F41+F42 -> -4000 | G43: =G41+G42 -> 6661.7203 | H43: =H41+H42 -> 6330.4515 | I43: =I41+I42 -> 6012.4334 | ... L43: =L41+L42 -> 19654.153
A44: GP: management fees received | B44: =IF(B$8>=COLUMNS($C$16:$L$16),0,INDEX($C$16:$L$16,B$8+1)) -> 270 | C44: =IF(C$8>=COLUMNS($C$16:$L$16),0,INDEX($C$16:$L$16,C$8+1)) -> 270 | D44: =IF(D$8>=COLUMNS($C$16:$L$16),0,INDEX($C$16:$L$16,D$8+1)) -> 270 | E44: =IF(E$8>=COLUMNS($C$16:$L$16),0,INDEX($C$16:$L$16,E$8+1)) -> 270 | F44: =IF(F$8>=COLUMNS($C$16:$L$16),0,INDEX($C$16:$L$16,F$8+1)) -> 270 | G44: =IF(G$8>=COLUMNS($C$16:$L$16),0,INDEX($C$16:$L$16,G$8+1)) -> 270 | H44: =IF(H$8>=COLUMNS($C$16:$L$16),0,INDEX($C$16:$L$16,H$8+1)) -> 270 | I44: =IF(I$8>=COLUMNS($C$16:$L$16),0,INDEX($C$16:$L$16,I$8+1)) -> 270 | ... L44: =IF(L$8>=COLUMNS($C$16:$L$16),0,INDEX($C$16:$L$16,L$8+1)) -> 0
A45: GP: carried interest received | B45: =IF(B$8=0,0,INDEX($C$36:$L$36,B$8)) -> 0 | C45: =IF(C$8=0,0,INDEX($C$36:$L$36,C$8)) -> 0 | D45: =IF(D$8=0,0,INDEX($C$36:$L$36,D$8)) -> 0 | E45: =IF(E$8=0,0,INDEX($C$36:$L$36,E$8)) -> 0 | F45: =IF(F$8=0,0,INDEX($C$36:$L$36,F$8)) -> 0 | G45: =IF(G$8=0,0,INDEX($C$36:$L$36,G$8)) -> 0 | H45: =IF(H$8=0,0,INDEX($C$36:$L$36,H$8)) -> 0 | I45: =IF(I$8=0,0,INDEX($C$36:$L$36,I$8)) -> 0 | ... L45: =IF(L$8=0,0,INDEX($C$36:$L$36,L$8)) -> 6009.2904
A46: GP: total compensation | B46: =B44+B45 -> 270 | C46: =C44+C45 -> 270 | D46: =D44+D45 -> 270 | E46: =E44+E45 -> 270 | F46: =F44+F45 -> 270 | G46: =G44+G45 -> 270 | H46: =H44+H45 -> 270 | I46: =I44+I45 -> 270 | ... L46: =L44+L45 -> 6009.2904
A47: OPERF: net cash flow (pro-rata share of LP) | B47: =$C$63*B43 -> -150 | C47: =$C$63*C43 -> -150 | D47: =$C$63*D43 -> -150 | E47: =$C$63*E43 -> -150 | F47: =$C$63*F43 -> -150 | G47: =$C$63*G43 -> 249.81451 | H47: =$C$63*H43 -> 237.39193 | I47: =$C$63*I43 -> 225.46625 | ... L47: =$C$63*L43 -> 737.03073
A49: Results ($ millions unless stated)
A50: LP net IRR (after fees and carry) | C50: =IRR(B43:L43,0.1) -> 0.16029224 | E50: IRR of LP net cash flows (row 43)
A51: LP NPV at the discount rate | C51: =B43+NPV($F$3,C43:L43) -> 825.66274 | E51: Positive = beats the 15% required return
A52: LP total contributions | C52: =-SUM(B41:L41) -> 20000 | E52: Includes capital later used to pay fees
A53: LP total distributions | C53: =SUM(B42:L42) -> 48631.388
A54: LP multiple of contributed capital (TVPI) | C54: =IF(C52=0,0,C53/C52) -> 2.4315694
A55: GP management fees, total (nominal) | C55: =SUM(B44:L44) -> 2700
A56: GP carried interest, total (nominal) | C56: =SUM(B45:L45) -> 7157.847
A57: PV of management fees at the discount rate | C57: =B44+NPV($F$3,C44:L44) -> 1558.3277 | E57: Fees paid at the start of each year
A58: PV of carried interest at the discount rate | C58: =B45+NPV($F$3,C45:L45) -> 1811.8962
A59: PV of total GP compensation | C59: =C57+C58 -> 3370.2238
A60: Management fees as % of GP compensation (PV) | C60: =IF(C59=0,0,C57/C59) -> 0.46238106 | E60: Fixed pay share; the rest is performance pay
A61: Gross asset return less LP net IRR (fee + carry drag) | C61: =$F$2-C50 -> 0.039707762
A62: First year the GP receives carried interest | C62: =IF(MAX(C38:L38)<=0,"None",IFERROR(INDEX(C8:L8,MATCH(0,C38:L38,1)+1),C8)) -> 9
A63: OPERF share of the fund's LP cash flows | C63: =IF($C$2=0,0,$I$4/$C$2) -> 0.0375 | E63: OPERF commitment ÷ committed capital
A64: OPERF NPV at the discount rate | C64: =C63*C51 -> 30.962353
A65: OPERF share of management fees paid (nominal) | C65: =C63*C55 -> 101.25
A66: OPERF distributions received (nominal) | C66: =C63*C53 -> 1823.6771
A68: Checks (0 = OK)
A69: NAV fully liquidated at end of Year 10 | C69: =ROUND(L24,6) -> 0
A70: Distributions = LP distributions + GP carry | C70: =ROUND(SUM(C23:L23)-SUM(C35:L35)-SUM(C36:L36),6) -> 0
A71: Distributions = takedowns − fees + asset growth | C71: =ROUND(SUM(C23:L23)-(SUM(C15:L15)-SUM(C16:L16)+SUM(C20:L20)),6) -> 0
A72: All checks | C72: =IF(ABS(C69)+ABS(C70)+ABS(C71)<0.001,"OK","CHECK") -> OK
A74: Source: Layout follows the Template sheet of the Darden supplementary spreadsheet (UV5624); waterfall, cash-flow and results rows added by the team.

Sheet Q5c Lower carry
A1: OREGON PUBLIC EMPLOYEES RETIREMENT FUND
B2: Committed capital ($ millions) | C2: =Inputs!$C$6 -> 20000 | E2: Asset growth rate (%) | F2: =Inputs!$C$8 -> 0.2 | H2: Hurdle rate (%) | I2: 0
B3: Management fee (%) | C3: =Inputs!$C$19 -> 0.0135 | E3: Discount rate (%) | F3: =Inputs!$C$9 -> 0.15 | H3: GP catch-up (1 = yes) | I3: 0
B4: LP share of profit (%) | C4: =1-F4 -> 0.85 | E4: GP share of profit (%) | F4: =Inputs!$C$21 -> 0.15 | H4: OPERF ($ millions) | I4: =Inputs!$C$26 -> 750
A6: ="Scenario: "&"TPG offer + lower carry — "&TEXT(C3,"0.00%")&" fee on committed capital, "&TEXT(F4,"0%")&" carry, "&IF(I2=0,"no hurdle",TEXT(I2,"0%")&" hurdle"&IF(I3=1," with 100% GP catch-up (soft)"," with no catch-up (hard)")) -> Scenario: TPG offer + lower carry — 1.35% fee on committed capital, 15% carry, no hurdle | J6: Prep Q5 — carry cut to 15%
A8: Year | B8: 0 | C8: 1 | D8: 2 | E8: 3 | F8: 4 | G8: 5 | H8: 6 | I8: 7 | J8: 8 | K8: 9 | L8: 10
A9: Assumptions
A10: % Drawn of committed capital | C10: =Inputs!C$13 -> 0.2 | D10: =Inputs!D$13 -> 0.2 | E10: =Inputs!E$13 -> 0.2 | F10: =Inputs!F$13 -> 0.2 | G10: =Inputs!G$13 -> 0.2 | H10: =Inputs!H$13 -> 0 | I10: =Inputs!I$13 -> 0 | J10: =Inputs!J$13 -> 0 | ... L10: =Inputs!L$13 -> 0
A11: Distribution rate | C11: =Inputs!C$14 -> 0 | D11: =Inputs!D$14 -> 0 | E11: =Inputs!E$14 -> 0 | F11: =Inputs!F$14 -> 0 | G11: =Inputs!G$14 -> 0.2 | H11: =Inputs!H$14 -> 0.2 | I11: =Inputs!I$14 -> 0.2 | J11: =Inputs!J$14 -> 0.2 | ... L11: =Inputs!L$14 -> 1
A13: At the beginning of the year
A14: Assets | C14: =B24 -> 0 | D14: =C24 -> 4476 | E14: =D24 -> 9847.2 | F14: =E24 -> 16292.64 | G14: =F24 -> 24027.168 | H14: =G24 -> 26646.881 | I14: =H24 -> 25321.806 | J14: =I24 -> 24049.734 | ... L14: =K24 -> 21656.203
A15: Plus: Takedown | C15: =$C$2*C10 -> 4000 | D15: =$C$2*D10 -> 4000 | E15: =$C$2*E10 -> 4000 | F15: =$C$2*F10 -> 4000 | G15: =$C$2*G10 -> 4000 | H15: =$C$2*H10 -> 0 | I15: =$C$2*I10 -> 0 | J15: =$C$2*J10 -> 0 | ... L15: =$C$2*L10 -> 0
A16: Less: Management fee | C16: =$C$2*$C$3 -> 270 | D16: =$C$2*$C$3 -> 270 | E16: =$C$2*$C$3 -> 270 | F16: =$C$2*$C$3 -> 270 | G16: =$C$2*$C$3 -> 270 | H16: =$C$2*$C$3 -> 270 | I16: =$C$2*$C$3 -> 270 | J16: =$C$2*$C$3 -> 270 | ... L16: =$C$2*$C$3 -> 270
A17: Invested capital per period | C17: =C14+C15-C16 -> 3730 | D17: =D14+D15-D16 -> 8206 | E17: =E14+E15-E16 -> 13577.2 | F17: =F14+F15-F16 -> 20022.64 | G17: =G14+G15-G16 -> 27757.168 | H17: =H14+H15-H16 -> 26376.881 | I17: =I14+I15-I16 -> 25051.806 | J17: =J14+J15-J16 -> 23779.734 | ... L17: =L14+L15-L16 -> 21386.203
A19: At the end of the year
A20: Plus: Asset growth over year | C20: =C17*$F$2 -> 746 | D20: =D17*$F$2 -> 1641.2 | E20: =E17*$F$2 -> 2715.44 | F20: =F17*$F$2 -> 4004.528 | G20: =G17*$F$2 -> 5551.4336 | H20: =H17*$F$2 -> 5275.3763 | I20: =I17*$F$2 -> 5010.3612 | J20: =J17*$F$2 -> 4755.9468 | ... L20: =L17*$F$2 -> 4277.2405
A21: NAV before distributions | C21: =C17+C20 -> 4476 | D21: =D17+D20 -> 9847.2 | E21: =E17+E20 -> 16292.64 | F21: =F17+F20 -> 24027.168 | G21: =G17+G20 -> 33308.602 | H21: =H17+H20 -> 31652.258 | I21: =I17+I20 -> 30062.167 | J21: =J17+J20 -> 28535.681 | ... L21: =L17+L20 -> 25663.443
A23: Less: Distributions | C23: =C21*C11 -> 0 | D23: =D21*D11 -> 0 | E23: =E21*E11 -> 0 | F23: =F21*F11 -> 0 | G23: =G21*G11 -> 6661.7203 | H23: =H21*H11 -> 6330.4515 | I23: =I21*I11 -> 6012.4334 | J23: =J21*J11 -> 5707.1361 | ... L23: =L21*L11 -> 25663.443
A24: NAV after distributions | C24: =C21-C23 -> 4476 | D24: =D21-D23 -> 9847.2 | E24: =E21-E23 -> 16292.64 | F24: =F21-F23 -> 24027.168 | G24: =G21-G23 -> 26646.881 | H24: =H21-H23 -> 25321.806 | I24: =I21-I23 -> 24049.734 | J24: =J21-J23 -> 22828.544 | ... L24: =L21-L23 -> 0
A26: Distribution waterfall (whole-fund carry: LPs made whole first)
A27: Unreturned LP capital, incl. this year's takedown | C27: =B29+C15 -> 4000 | D27: =C29+D15 -> 8000 | E27: =D29+E15 -> 12000 | F27: =E29+F15 -> 16000 | G27: =F29+G15 -> 20000 | H27: =G29+H15 -> 13338.28 | I27: =H29+I15 -> 7007.8282 | J27: =I29+J15 -> 995.39473 | ... L27: =K29+L15 -> 0
A28: Tier 1 – Return of capital to LPs | C28: =MIN(C23,C27) -> 0 | D28: =MIN(D23,D27) -> 0 | E28: =MIN(E23,E27) -> 0 | F28: =MIN(F23,F27) -> 0 | G28: =MIN(G23,G27) -> 6661.7203 | H28: =MIN(H23,H27) -> 6330.4515 | I28: =MIN(I23,I27) -> 6012.4334 | J28: =MIN(J23,J27) -> 995.39473 | ... L28: =MIN(L23,L27) -> 0
A29: Unreturned LP capital, end of year | C29: =C27-C28 -> 4000 | D29: =D27-D28 -> 8000 | E29: =E27-E28 -> 12000 | F29: =F27-F28 -> 16000 | G29: =G27-G28 -> 13338.28 | H29: =H27-H28 -> 7007.8282 | I29: =I27-I28 -> 995.39473 | J29: =J27-J28 -> 0 | ... L29: =L27-L28 -> 0
A30: Preferred return due (hurdle accrual + unpaid) | C30: =B32+$I$2*(C27+B32) -> 0 | D30: =C32+$I$2*(D27+C32) -> 0 | E30: =D32+$I$2*(E27+D32) -> 0 | F30: =E32+$I$2*(F27+E32) -> 0 | G30: =F32+$I$2*(G27+F32) -> 0 | H30: =G32+$I$2*(H27+G32) -> 0 | I30: =H32+$I$2*(I27+H32) -> 0 | J30: =I32+$I$2*(J27+I32) -> 0 | ... L30: =K32+$I$2*(L27+K32) -> 0
A31: Tier 2 – Preferred return paid to LPs | C31: =MIN(C23-C28,C30) -> 0 | D31: =MIN(D23-D28,D30) -> 0 | E31: =MIN(E23-E28,E30) -> 0 | F31: =MIN(F23-F28,F30) -> 0 | G31: =MIN(G23-G28,G30) -> 0 | H31: =MIN(H23-H28,H30) -> 0 | I31: =MIN(I23-I28,I30) -> 0 | J31: =MIN(J23-J28,J30) -> 0 | ... L31: =MIN(L23-L28,L30) -> 0
A32: Unpaid preferred return, end of year | C32: =C30-C31 -> 0 | D32: =D30-D31 -> 0 | E32: =E30-E31 -> 0 | F32: =F30-F31 -> 0 | G32: =G30-G31 -> 0 | H32: =H30-H31 -> 0 | I32: =I30-I31 -> 0 | J32: =J30-J31 -> 0 | ... L32: =L30-L31 -> 0
A33: Tier 3 – GP catch-up (soft hurdle only) | C33: =IF($I$3=1,MIN(C23-C28-C31,MAX(0,$F$4/(1-$F$4)*(B37+C31)-B38)),0) -> 0 | D33: =IF($I$3=1,MIN(D23-D28-D31,MAX(0,$F$4/(1-$F$4)*(C37+D31)-C38)),0) -> 0 | E33: =IF($I$3=1,MIN(E23-E28-E31,MAX(0,$F$4/(1-$F$4)*(D37+E31)-D38)),0) -> 0 | F33: =IF($I$3=1,MIN(F23-F28-F31,MAX(0,$F$4/(1-$F$4)*(E37+F31)-E38)),0) -> 0 | G33: =IF($I$3=1,MIN(G23-G28-G31,MAX(0,$F$4/(1-$F$4)*(F37+G31)-F38)),0) -> 0 | H33: =IF($I$3=1,MIN(H23-H28-H31,MAX(0,$F$4/(1-$F$4)*(G37+H31)-G38)),0) -> 0 | I33: =IF($I$3=1,MIN(I23-I28-I31,MAX(0,$F$4/(1-$F$4)*(H37+I31)-H38)),0) -> 0 | J33: =IF($I$3=1,MIN(J23-J28-J31,MAX(0,$F$4/(1-$F$4)*(I37+J31)-I38)),0) -> 0 | ... L33: =IF($I$3=1,MIN(L23-L28-L31,MAX(0,$F$4/(1-$F$4)*(K37+L31)-K38)),0) -> 0
A34: Tier 4 – Remaining profit split LP/GP | C34: =C23-C28-C31-C33 -> 0 | D34: =D23-D28-D31-D33 -> 0 | E34: =E23-E28-E31-E33 -> 0 | F34: =F23-F28-F31-F33 -> 0 | G34: =G23-G28-G31-G33 -> 0 | H34: =H23-H28-H31-H33 -> 0 | I34: =I23-I28-I31-I33 -> 0 | J34: =J23-J28-J31-J33 -> 4711.7414 | ... L34: =L23-L28-L31-L33 -> 25663.443
A35: Total distributions to LPs | C35: =C28+C31+$C$4*C34 -> 0 | D35: =D28+D31+$C$4*D34 -> 0 | E35: =E28+E31+$C$4*E34 -> 0 | F35: =F28+F31+$C$4*F34 -> 0 | G35: =G28+G31+$C$4*G34 -> 6661.7203 | H35: =H28+H31+$C$4*H34 -> 6330.4515 | I35: =I28+I31+$C$4*I34 -> 6012.4334 | J35: =J28+J31+$C$4*J34 -> 5000.3749 | ... L35: =L28+L31+$C$4*L34 -> 21813.927
A36: Total carried interest to GP | C36: =C33+$F$4*C34 -> 0 | D36: =D33+$F$4*D34 -> 0 | E36: =E33+$F$4*E34 -> 0 | F36: =F33+$F$4*F34 -> 0 | G36: =G33+$F$4*G34 -> 0 | H36: =H33+$F$4*H34 -> 0 | I36: =I33+$F$4*I34 -> 0 | J36: =J33+$F$4*J34 -> 706.76121 | ... L36: =L33+$F$4*L34 -> 3849.5165
A37: Cumulative LP profit received | C37: =B37+C31+$C$4*C34 -> 0 | D37: =C37+D31+$C$4*D34 -> 0 | E37: =D37+E31+$C$4*E34 -> 0 | F37: =E37+F31+$C$4*F34 -> 0 | G37: =F37+G31+$C$4*G34 -> 0 | H37: =G37+H31+$C$4*H34 -> 0 | I37: =H37+I31+$C$4*I34 -> 0 | J37: =I37+J31+$C$4*J34 -> 4004.9802 | ... L37: =K37+L31+$C$4*L34 -> 30420.85
A38: Cumulative GP carried interest | C38: =B38+C36 -> 0 | D38: =C38+D36 -> 0 | E38: =D38+E36 -> 0 | F38: =E38+F36 -> 0 | G38: =F38+G36 -> 0 | H38: =G38+H36 -> 0 | I38: =H38+I36 -> 0 | J38: =I38+J36 -> 706.76121 | ... L38: =K38+L36 -> 5368.3853
A40: Cash flows by date (column = point in time t: the start of Year n is t = n − 1; the end of Year n is t = n)
A41: LP: capital calls (takedowns) | B41: =IF(B$8>=COLUMNS($C$15:$L$15),0,-INDEX($C$15:$L$15,B$8+1)) -> -4000 | C41: =IF(C$8>=COLUMNS($C$15:$L$15),0,-INDEX($C$15:$L$15,C$8+1)) -> -4000 | D41: =IF(D$8>=COLUMNS($C$15:$L$15),0,-INDEX($C$15:$L$15,D$8+1)) -> -4000 | E41: =IF(E$8>=COLUMNS($C$15:$L$15),0,-INDEX($C$15:$L$15,E$8+1)) -> -4000 | F41: =IF(F$8>=COLUMNS($C$15:$L$15),0,-INDEX($C$15:$L$15,F$8+1)) -> -4000 | G41: =IF(G$8>=COLUMNS($C$15:$L$15),0,-INDEX($C$15:$L$15,G$8+1)) -> 0 | H41: =IF(H$8>=COLUMNS($C$15:$L$15),0,-INDEX($C$15:$L$15,H$8+1)) -> 0 | I41: =IF(I$8>=COLUMNS($C$15:$L$15),0,-INDEX($C$15:$L$15,I$8+1)) -> 0 | ... L41: =IF(L$8>=COLUMNS($C$15:$L$15),0,-INDEX($C$15:$L$15,L$8+1)) -> 0
A42: LP: distributions received | B42: =IF(B$8=0,0,INDEX($C$35:$L$35,B$8)) -> 0 | C42: =IF(C$8=0,0,INDEX($C$35:$L$35,C$8)) -> 0 | D42: =IF(D$8=0,0,INDEX($C$35:$L$35,D$8)) -> 0 | E42: =IF(E$8=0,0,INDEX($C$35:$L$35,E$8)) -> 0 | F42: =IF(F$8=0,0,INDEX($C$35:$L$35,F$8)) -> 0 | G42: =IF(G$8=0,0,INDEX($C$35:$L$35,G$8)) -> 6661.7203 | H42: =IF(H$8=0,0,INDEX($C$35:$L$35,H$8)) -> 6330.4515 | I42: =IF(I$8=0,0,INDEX($C$35:$L$35,I$8)) -> 6012.4334 | ... L42: =IF(L$8=0,0,INDEX($C$35:$L$35,L$8)) -> 21813.927
A43: LP: net cash flow | B43: =B41+B42 -> -4000 | C43: =C41+C42 -> -4000 | D43: =D41+D42 -> -4000 | E43: =E41+E42 -> -4000 | F43: =F41+F42 -> -4000 | G43: =G41+G42 -> 6661.7203 | H43: =H41+H42 -> 6330.4515 | I43: =I41+I42 -> 6012.4334 | ... L43: =L41+L42 -> 21813.927
A44: GP: management fees received | B44: =IF(B$8>=COLUMNS($C$16:$L$16),0,INDEX($C$16:$L$16,B$8+1)) -> 270 | C44: =IF(C$8>=COLUMNS($C$16:$L$16),0,INDEX($C$16:$L$16,C$8+1)) -> 270 | D44: =IF(D$8>=COLUMNS($C$16:$L$16),0,INDEX($C$16:$L$16,D$8+1)) -> 270 | E44: =IF(E$8>=COLUMNS($C$16:$L$16),0,INDEX($C$16:$L$16,E$8+1)) -> 270 | F44: =IF(F$8>=COLUMNS($C$16:$L$16),0,INDEX($C$16:$L$16,F$8+1)) -> 270 | G44: =IF(G$8>=COLUMNS($C$16:$L$16),0,INDEX($C$16:$L$16,G$8+1)) -> 270 | H44: =IF(H$8>=COLUMNS($C$16:$L$16),0,INDEX($C$16:$L$16,H$8+1)) -> 270 | I44: =IF(I$8>=COLUMNS($C$16:$L$16),0,INDEX($C$16:$L$16,I$8+1)) -> 270 | ... L44: =IF(L$8>=COLUMNS($C$16:$L$16),0,INDEX($C$16:$L$16,L$8+1)) -> 0
A45: GP: carried interest received | B45: =IF(B$8=0,0,INDEX($C$36:$L$36,B$8)) -> 0 | C45: =IF(C$8=0,0,INDEX($C$36:$L$36,C$8)) -> 0 | D45: =IF(D$8=0,0,INDEX($C$36:$L$36,D$8)) -> 0 | E45: =IF(E$8=0,0,INDEX($C$36:$L$36,E$8)) -> 0 | F45: =IF(F$8=0,0,INDEX($C$36:$L$36,F$8)) -> 0 | G45: =IF(G$8=0,0,INDEX($C$36:$L$36,G$8)) -> 0 | H45: =IF(H$8=0,0,INDEX($C$36:$L$36,H$8)) -> 0 | I45: =IF(I$8=0,0,INDEX($C$36:$L$36,I$8)) -> 0 | ... L45: =IF(L$8=0,0,INDEX($C$36:$L$36,L$8)) -> 3849.5165
A46: GP: total compensation | B46: =B44+B45 -> 270 | C46: =C44+C45 -> 270 | D46: =D44+D45 -> 270 | E46: =E44+E45 -> 270 | F46: =F44+F45 -> 270 | G46: =G44+G45 -> 270 | H46: =H44+H45 -> 270 | I46: =I44+I45 -> 270 | ... L46: =L44+L45 -> 3849.5165
A47: OPERF: net cash flow (pro-rata share of LP) | B47: =$C$63*B43 -> -150 | C47: =$C$63*C43 -> -150 | D47: =$C$63*D43 -> -150 | E47: =$C$63*E43 -> -150 | F47: =$C$63*F43 -> -150 | G47: =$C$63*G43 -> 249.81451 | H47: =$C$63*H43 -> 237.39193 | I47: =$C$63*I43 -> 225.46625 | ... L47: =$C$63*L43 -> 818.02225
A49: Results ($ millions unless stated)
A50: LP net IRR (after fees and carry) | C50: =IRR(B43:L43,0.1) -> 0.16491098 | E50: IRR of LP net cash flows (row 43)
A51: LP NPV at the discount rate | C51: =B43+NPV($F$3,C43:L43) -> 1224.1241 | E51: Positive = beats the 15% required return
A52: LP total contributions | C52: =-SUM(B41:L41) -> 20000 | E52: Includes capital later used to pay fees
A53: LP total distributions | C53: =SUM(B42:L42) -> 50420.85
A54: LP multiple of contributed capital (TVPI) | C54: =IF(C52=0,0,C53/C52) -> 2.5210425
A55: GP management fees, total (nominal) | C55: =SUM(B44:L44) -> 2700
A56: GP carried interest, total (nominal) | C56: =SUM(B45:L45) -> 5368.3853
A57: PV of management fees at the discount rate | C57: =B44+NPV($F$3,C44:L44) -> 1558.3277 | E57: Fees paid at the start of each year
A58: PV of carried interest at the discount rate | C58: =B45+NPV($F$3,C45:L45) -> 1413.4348
A59: PV of total GP compensation | C59: =C57+C58 -> 2971.7624
A60: Management fees as % of GP compensation (PV) | C60: =IF(C59=0,0,C57/C59) -> 0.52437828 | E60: Fixed pay share; the rest is performance pay
A61: Gross asset return less LP net IRR (fee + carry drag) | C61: =$F$2-C50 -> 0.035089017
A62: First year the GP receives carried interest | C62: =IF(MAX(C38:L38)<=0,"None",IFERROR(INDEX(C8:L8,MATCH(0,C38:L38,1)+1),C8)) -> 8
A63: OPERF share of the fund's LP cash flows | C63: =IF($C$2=0,0,$I$4/$C$2) -> 0.0375 | E63: OPERF commitment ÷ committed capital
A64: OPERF NPV at the discount rate | C64: =C63*C51 -> 45.904656
A65: OPERF share of management fees paid (nominal) | C65: =C63*C55 -> 101.25
A66: OPERF distributions received (nominal) | C66: =C63*C53 -> 1890.7819
A68: Checks (0 = OK)
A69: NAV fully liquidated at end of Year 10 | C69: =ROUND(L24,6) -> 0
A70: Distributions = LP distributions + GP carry | C70: =ROUND(SUM(C23:L23)-SUM(C35:L35)-SUM(C36:L36),6) -> 0
A71: Distributions = takedowns − fees + asset growth | C71: =ROUND(SUM(C23:L23)-(SUM(C15:L15)-SUM(C16:L16)+SUM(C20:L20)),6) -> 0
A72: All checks | C72: =IF(ABS(C69)+ABS(C70)+ABS(C71)<0.001,"OK","CHECK") -> OK
A74: Source: Layout follows the Template sheet of the Darden supplementary spreadsheet (UV5624); waterfall, cash-flow and results rows added by the team.

Sheet Q5 Analysis
A1: Q5 — SHOULD OPERF ASK FOR AN 8% HURDLE OR A CUT IN CARRY FROM 20% TO 15%?
A2: All alternatives are layered on TPG's offer (1.35% fee), which every LP gets anyway. Hard hurdle = no catch-up; soft hurdle = 100% GP catch-up after the 8% preferred return.
A4: A. Base-case comparison (assets grow 20% a year)
A5: Metric | B5: TPG offer (baseline) | C5: + 8% hard hurdle | D5: + 8% soft hurdle | E5: + 15% carry | F5: + hard hurdle & 15% carry | G5: + soft hurdle & 15% carry
A6: LP net IRR | B6: ='Q4 Fee cut'!$C$50 -> 0.15936141 | C6: ='Q5a Hard hurdle'!$C$50 -> 0.16591822 | D6: ='Q5b Soft hurdle'!$C$50 -> 0.16029224 | E6: ='Q5c Lower carry'!$C$50 -> 0.16491098 | F6: =Engine!$K$12 -> 0.1696833 | G6: =Engine!$K$13 -> 0.16547005
A7: Change vs TPG offer | B7: =(B6-$B$6)*10000 -> 0 | C7: =(C6-$B$6)*10000 -> 65.568158 | D7: =(D6-$B$6)*10000 -> 9.3082914 | E7: =(E6-$B$6)*10000 -> 55.49574 | F7: =(F6-$B$6)*10000 -> 103.21888 | G7: =(G6-$B$6)*10000 -> 61.086427
A8: LP NPV at 15% ($m) | B8: ='Q4 Fee cut'!$C$51 -> 752.97923 | C8: ='Q5a Hard hurdle'!$C$51 -> 1303.5385 | D8: ='Q5b Soft hurdle'!$C$51 -> 825.66274 | E8: ='Q5c Lower carry'!$C$51 -> 1224.1241 | F8: =Engine!$L$12 -> 1637.0436 | G8: =Engine!$L$13 -> 1267.9903
A9: Change vs TPG offer ($m) | B9: =B8-$B$8 -> 0 | C9: =C8-$B$8 -> 550.55924 | D9: =D8-$B$8 -> 72.68351 | E9: =E8-$B$8 -> 471.14492 | F9: =F8-$B$8 -> 884.06435 | G9: =G8-$B$8 -> 515.01109
A10: OPERF NPV change vs TPG offer ($m) | B10: =B9*'Q4 Fee cut'!$C$63 -> 0 | C10: =C9*'Q4 Fee cut'!$C$63 -> 20.645972 | D10: =D9*'Q4 Fee cut'!$C$63 -> 2.7256316 | E10: =E9*'Q4 Fee cut'!$C$63 -> 17.667934 | F10: =F9*'Q4 Fee cut'!$C$63 -> 33.152413 | G10: =G9*'Q4 Fee cut'!$C$63 -> 19.312916
A11: GP carried interest, nominal ($m) | B11: ='Q4 Fee cut'!$C$56 -> 7157.847 | C11: ='Q5a Hard hurdle'!$C$56 -> 5362.4 | D11: ='Q5b Soft hurdle'!$C$56 -> 7157.847 | E11: ='Q5c Lower carry'!$C$56 -> 5368.3853 | F11: =Engine!$P$12 -> 4021.8 | G11: =Engine!$P$13 -> 5368.3853
A12: Change in carry vs TPG offer ($m) | B12: =B11-$B$11 -> 0 | C12: =C11-$B$11 -> -1795.4471 | D12: =D11-$B$11 -> 0 | E12: =E11-$B$11 -> -1789.4618 | F12: =F11-$B$11 -> -3136.0471 | G12: =G11-$B$11 -> -1789.4618
A13: PV of total GP compensation ($m) | B13: ='Q4 Fee cut'!$C$59 -> 3442.9073 | C13: ='Q5a Hard hurdle'!$C$59 -> 2892.3481 | D13: ='Q5b Soft hurdle'!$C$59 -> 3370.2238 | E13: ='Q5c Lower carry'!$C$59 -> 2971.7624 | F13: =Engine!$S$12 -> 2558.843 | G13: =Engine!$S$13 -> 2927.8962
A14: Change vs TPG offer ($m) | B14: =B13-$B$13 -> 0 | C14: =C13-$B$13 -> -550.55924 | D14: =D13-$B$13 -> -72.68351 | E14: =E13-$B$13 -> -471.14492 | F14: =F13-$B$13 -> -884.06435 | G14: =G13-$B$13 -> -515.01109
A15: Equivalent cut in management fee (bps) | B15: =IF($C$18=0,0,B9/$C$18) -> 0 | C15: =IF($C$18=0,0,C9/$C$18) -> 47.255035 | D15: =IF($C$18=0,0,D9/$C$18) -> 6.2384963 | E15: =IF($C$18=0,0,E9/$C$18) -> 40.438827 | F15: =IF($C$18=0,0,F9/$C$18) -> 75.880103 | G15: =IF($C$18=0,0,G9/$C$18) -> 44.203903
A16: First year TPG receives carry | B16: ='Q4 Fee cut'!$C$62 -> 8 | C16: ='Q5a Hard hurdle'!$C$62 -> 9 | D16: ='Q5b Soft hurdle'!$C$62 -> 9 | E16: ='Q5c Lower carry'!$C$62 -> 8 | F16: n/a | G16: n/a
A18: Memo: LP NPV gained per 1 bp of management fee ($m) | C18: =IF((Inputs!$C$18-Inputs!$C$19)=0,0,('Q4 Fee cut'!$C$51-'Q3 Base case'!$C$51)/((Inputs!$C$18-Inputs!$C$19)*10000)) -> 11.650806 | D18: Row 15 restates each concession as an equivalent fee cut
A20: B. Downside protection — LP net IRR across fund outcomes
A21: Asset growth | B21: TPG offer | C21: + hard hurdle | D21: + soft hurdle | E21: + 15% carry | F21: Gain: hard hurdle (bps) | G21: Gain: soft hurdle (bps) | H21: Gain: 15% carry (bps)
A22: =Engine!$I$52 -> 0 | B22: =Engine!$K$52 -> -0.025625198 | C22: =Engine!$K$83 -> -0.025625198 | D22: =Engine!$K$114 -> -0.025625198 | E22: =Engine!$K$145 -> -0.025625198 | F22: =(C22-$B22)*10000 -> 0 | G22: =(D22-$B22)*10000 -> 0 | H22: =(E22-$B22)*10000 -> 0
A23: =Engine!$I$57 -> 0.05 | B23: =Engine!$K$57 -> 0.021836081 | C23: =Engine!$K$88 -> 0.026685192 | D23: =Engine!$K$119 -> 0.026685192 | E23: =Engine!$K$150 -> 0.023068031 | F23: =(C23-$B23)*10000 -> 48.49111 | G23: =(D23-$B23)*10000 -> 48.49111 | H23: =(E23-$B23)*10000 -> 12.319506
A24: =Engine!$I$62 -> 0.1 | B24: =Engine!$K$62 -> 0.066474587 | C24: =Engine!$K$93 -> 0.078335477 | D24: =Engine!$K$124 -> 0.078335477 | E24: =Engine!$K$155 -> 0.069554885 | F24: =(C24-$B24)*10000 -> 118.6089 | G24: =(D24-$B24)*10000 -> 118.6089 | H24: =(E24-$B24)*10000 -> 30.802977
A25: =Engine!$I$67 -> 0.15 | B25: =Engine!$K$67 -> 0.11263957 | C25: =Engine!$K$98 -> 0.12113278 | D25: =Engine!$K$129 -> 0.11302767 | E25: =Engine!$K$160 -> 0.11707413 | F25: =(C25-$B25)*10000 -> 84.932034 | G25: =(D25-$B25)*10000 -> 3.8809714 | H25: =(E25-$B25)*10000 -> 44.345563
A26: =Engine!$I$72 -> 0.2 | B26: =Engine!$K$72 -> 0.15936141 | C26: =Engine!$K$103 -> 0.16591822 | D26: =Engine!$K$134 -> 0.16029224 | E26: =Engine!$K$165 -> 0.16491098 | F26: =(C26-$B26)*10000 -> 65.568158 | G26: =(D26-$B26)*10000 -> 9.3082914 | H26: =(E26-$B26)*10000 -> 55.49574
A27: =Engine!$I$77 -> 0.25 | B27: =Engine!$K$77 -> 0.20638488 | C27: =Engine!$K$108 -> 0.21180159 | D27: =Engine!$K$139 -> 0.20674553 | E27: =Engine!$K$170 -> 0.21289765 | F27: =(C27-$B27)*10000 -> 54.167092 | G27: =(D27-$B27)*10000 -> 3.6064816 | H27: =(E27-$B27)*10000 -> 65.127695
A28: =Engine!$I$82 -> 0.3 | B28: =Engine!$K$82 -> 0.25369121 | C28: =Engine!$K$113 -> 0.25832909 | D28: =Engine!$K$144 -> 0.25461362 | E28: =Engine!$K$175 -> 0.26103818 | F28: =(C28-$B28)*10000 -> 46.378807 | G28: =(D28-$B28)*10000 -> 9.2241284 | H28: =(E28-$B28)*10000 -> 73.469683
A30: C. Carried interest TPG earns across fund outcomes ($m, nominal)
A31: Asset growth | B31: TPG offer | C31: + hard hurdle | D31: + soft hurdle | E31: + 15% carry | F31: LP IRR below hurdle?
A32: =Engine!$I$52 -> 0 | B32: =Engine!$P$52 -> 0 | C32: =Engine!$P$83 -> 0 | D32: =Engine!$P$114 -> 0 | E32: =Engine!$P$145 -> 0 | F32: =IF(Engine!$K$52<Inputs!$C$22,"Yes","No") -> Yes
A33: =Engine!$I$57 -> 0.05 | B33: =Engine!$P$57 -> 654.92243 | C33: =Engine!$P$88 -> 0 | D33: =Engine!$P$119 -> 0 | E33: =Engine!$P$150 -> 491.19182 | F33: =IF(Engine!$K$57<Inputs!$C$22,"Yes","No") -> Yes
A34: =Engine!$I$62 -> 0.1 | B34: =Engine!$P$62 -> 2248.0201 | C34: =Engine!$P$93 -> 0 | D34: =Engine!$P$124 -> 0 | E34: =Engine!$P$155 -> 1686.0151 | F34: =IF(Engine!$K$62<Inputs!$C$22,"Yes","No") -> Yes
A35: =Engine!$I$67 -> 0.15 | B35: =Engine!$P$67 -> 4362.9523 | C35: =Engine!$P$98 -> 2292.5131 | D35: =Engine!$P$129 -> 4362.9523 | E35: =Engine!$P$160 -> 3272.2142 | F35: =IF(Engine!$K$67<Inputs!$C$22,"Yes","No") -> No
A36: =Engine!$I$72 -> 0.2 | B36: =Engine!$P$72 -> 7157.847 | C36: =Engine!$P$103 -> 5362.4 | D36: =Engine!$P$134 -> 7157.847 | E36: =Engine!$P$165 -> 5368.3853 | F36: =IF(Engine!$K$72<Inputs!$C$22,"Yes","No") -> No
A37: =Engine!$I$77 -> 0.25 | B37: =Engine!$P$77 -> 10833.613 | C37: =Engine!$P$108 -> 9218.711 | D37: =Engine!$P$139 -> 10833.613 | E37: =Engine!$P$170 -> 8125.21 | F37: =IF(Engine!$K$77<Inputs!$C$22,"Yes","No") -> No
A38: =Engine!$I$82 -> 0.3 | B38: =Engine!$P$82 -> 15643.917 | C38: =Engine!$P$113 -> 14164.978 | D38: =Engine!$P$144 -> 15643.917 | E38: =Engine!$P$175 -> 11732.938 | F38: =IF(Engine!$K$82<Inputs!$C$22,"Yes","No") -> No
A39: Without a hurdle TPG earns carry as soon as LPs get their capital back, even when LPs earn far less than 8%; with a hurdle that carry disappears.
A41: D. Context from the case
A42: • TPG typically offered a preferred return on its funds; other OPERF GPs (e.g. KKR) had resisted including one (case p.6, fn 16).
A43: • An 80/20 profit split is the industry standard (case p.4); Exhibit 5 shows carry of 20–30% of gains — 15% would be below market.
A44: • LP survey, Dec 2008 (Exhibit 11): areas requiring improvement — management fees 57%, carry structure & clawback 37%, hurdle 12%.
A45: • LP satisfaction with the compensation structure fell from 76% to 56% (Apr–Dec 2008); strongly dissatisfied rose from 13% to 27% (case p.6, Exhibit 11).
A46: • ILPA principles (Exhibit 12), endorsed by the Oregon Investment Council: the agreed profit split has "typically worked well" — the push is on fees, clawbacks and GP commitment.

Sheet Q6 OPERF decision
A1: Q6 — SHOULD OPERF REDUCE ITS TPG VI COMMITMENT BY 10% ($750m → $675m)?
A2: Economics use TPG's offered terms (sheet "Q4 Fee cut": 1.35% fee, 20% carry, no hurdle). OPERF receives a pro-rata share of LP cash flows.
A4: A. Commitment position ($ millions)
B5: Keep $750m | C5: Cut 10% | D5: Difference
A6: Commitment to TPG VI | B6: =Inputs!$C$26 -> 750 | C6: =B6*(1-Inputs!$C$27) -> 675 | D6: =C6-B6 -> -75
A7: Capital contributed to date (Exhibit 7) | B7: =Inputs!$C$28 -> 79.9 | C7: =Inputs!$C$28 -> 79.9 | D7: =C7-B7 -> 0
A8: Unfunded commitment still to be called | B8: =B6-B7 -> 670.1 | C8: =C6-C7 -> 595.1 | D8: =C8-B8 -> -75
A9: Maximum TPG can call in 2009 (30% cap) | B9: =B6*Inputs!$C$31 -> 225 | C9: =C6*Inputs!$C$31 -> 202.5 | D9: =C9-B9 -> -22.5
A10: Share of the $20bn fund (model) | B10: =IF(Inputs!$C$6=0,0,B6/Inputs!$C$6) -> 0.0375 | C10: =IF(Inputs!$C$6=0,0,C6/Inputs!$C$6) -> 0.03375 | D10: =C10-B10 -> -0.00375
A12: B. Expected economics at the base case (assets grow 20%, 15% discount rate, $ millions)
B13: Keep $750m | C13: Cut 10% | D13: Difference
A14: Capital called over the fund life | B14: =B$10*'Q4 Fee cut'!$C$52 -> 750 | C14: =C$10*'Q4 Fee cut'!$C$52 -> 675 | D14: =C14-B14 -> -75
A15: Management fees paid to TPG (nominal) | B15: =B$10*'Q4 Fee cut'!$C$55 -> 101.25 | C15: =C$10*'Q4 Fee cut'!$C$55 -> 91.125 | D15: =C15-B15 -> -10.125 | E15: cutting saves ~$1m a year in fees...
A16: PV of management fees | B16: =B$10*'Q4 Fee cut'!$C$57 -> 58.437287 | C16: =C$10*'Q4 Fee cut'!$C$57 -> 52.593558 | D16: =C16-B16 -> -5.8437287
A17: Carried interest paid to TPG (nominal) | B17: =B$10*'Q4 Fee cut'!$C$56 -> 268.41926 | C17: =C$10*'Q4 Fee cut'!$C$56 -> 241.57734 | D17: =C17-B17 -> -26.841926
A18: Distributions received | B18: =B$10*'Q4 Fee cut'!$C$53 -> 1823.6771 | C18: =C$10*'Q4 Fee cut'!$C$53 -> 1641.3094 | D18: =C18-B18 -> -182.36771
A19: Net profit (distributions − capital called) | B19: =B18-B14 -> 1073.6771 | C19: =C18-C14 -> 966.30935 | D19: =D18-D14 -> -107.36771
A20: NPV at 15% | B20: =B$10*'Q4 Fee cut'!$C$51 -> 28.236721 | C20: =C$10*'Q4 Fee cut'!$C$51 -> 25.413049 | D20: =C20-B20 -> -2.8236721 | E20: ...but gives up the NPV of the $75m tranche if TPG VI earns its base-case return
A21: LP net IRR (same for both — economics scale pro rata) | B21: ='Q4 Fee cut'!$C$50 -> 0.15936141 | C21: =B21 -> 0.15936141
A22: Multiple of capital (TVPI) | B22: ='Q4 Fee cut'!$C$54 -> 2.4315694 | C22: =B22 -> 2.4315694
A24: C. OPERF net cash flows by date ($ millions; t = 0 is the start of Year 1)
A25: t | B25: 0 | C25: 1 | D25: 2 | E25: 3 | F25: 4 | G25: 5 | H25: 6 | I25: 7 | J25: 8 | K25: 9 | L25: 10
A26: Keep $750m | B26: =$B$10*'Q4 Fee cut'!B$43 -> -150 | C26: =$B$10*'Q4 Fee cut'!C$43 -> -150 | D26: =$B$10*'Q4 Fee cut'!D$43 -> -150 | E26: =$B$10*'Q4 Fee cut'!E$43 -> -150 | F26: =$B$10*'Q4 Fee cut'!F$43 -> -150 | G26: =$B$10*'Q4 Fee cut'!G$43 -> 249.81451 | H26: =$B$10*'Q4 Fee cut'!H$43 -> 237.39193 | I26: =$B$10*'Q4 Fee cut'!I$43 -> 225.46625 | ... L26: =$B$10*'Q4 Fee cut'!L$43 -> 769.9033
A27: Cut to $675m | B27: =$C$10*'Q4 Fee cut'!B$43 -> -135 | C27: =$C$10*'Q4 Fee cut'!C$43 -> -135 | D27: =$C$10*'Q4 Fee cut'!D$43 -> -135 | E27: =$C$10*'Q4 Fee cut'!E$43 -> -135 | F27: =$C$10*'Q4 Fee cut'!F$43 -> -135 | G27: =$C$10*'Q4 Fee cut'!G$43 -> 224.83306 | H27: =$C$10*'Q4 Fee cut'!H$43 -> 213.65274 | I27: =$C$10*'Q4 Fee cut'!I$43 -> 202.91963 | ... L27: =$C$10*'Q4 Fee cut'!L$43 -> 692.91297
A28: Difference (the $75m tranche given up) | B28: =B26-B27 -> -15 | C28: =C26-C27 -> -15 | D28: =D26-D27 -> -15 | E28: =E26-E27 -> -15 | F28: =F26-F27 -> -15 | G28: =G26-G27 -> 24.981451 | H28: =H26-H27 -> 23.739193 | I28: =I26-I27 -> 22.546625 | ... L28: =L26-L27 -> 76.99033
A30: D. How much return does TPG VI need for the $75m to be worth keeping?
A31: Break-even asset growth (LP net IRR = 15%) under TPG offer | C31: =Sensitivity!$C$38 -> 0.19004534 | E31: Below this growth rate the commitment destroys value at a 15% required return — cutting would then help.
A32: Base-case asset growth (Prep Q3) | C32: =Inputs!$C$8 -> 0.2
A33: Cushion: base case above break-even (percentage points) | C33: =IF(ISNUMBER(C31),C32-C31,"n/a") -> 0.0099546646 | E33: Thin margin: a ~1 pp shortfall in annual growth wipes out the NPV.
A34: LP net IRR at base case less 15% required return | C34: =B21-Inputs!$C$9 -> 0.0093614086
A35: OPERF: TPG V (2006) IRR to date / TPG VI multiple to date | C35: =H57 -> -0.167 | D35: =G59 -> 0.6020025
A36: OPERF: TPG VI value to date vs capital contributed ($m) | C36: =Inputs!$C$29+Inputs!$C$30-Inputs!$C$28 -> -31.8
A38: E. NPV of the $75m tranche ($m) — asset growth (rows) × required return (columns)
A39: Asset growth ↓ / Discount rate → | B39: 0.1 | C39: 0.12 | D39: 0.15 | E39: 0.18 | F39: 0.2 | G39: LP IRR | I39: Helper: Engine row of first TPG-offer grid point | L39: =MATCH("S2",Engine!$A:$A,0) -> 52
A40: 0 | B40: =-$D$10*(INDEX(Engine!$W:$W,($L$39+ROUND(($A40-Inputs!$C$38)/Inputs!$C$39,0)))+NPV(B$39,OFFSET(Engine!$X$1,($L$39+ROUND(($A40-Inputs!$C$38)/Inputs!$C$39,0))-1,0,1,Inputs!$C$7))) -> -30.443948 | C40: =-$D$10*(INDEX(Engine!$W:$W,($L$39+ROUND(($A40-Inputs!$C$38)/Inputs!$C$39,0)))+NPV(C$39,OFFSET(Engine!$X$1,($L$39+ROUND(($A40-Inputs!$C$38)/Inputs!$C$39,0))-1,0,1,Inputs!$C$7))) -> -32.346012 | D40: =-$D$10*(INDEX(Engine!$W:$W,($L$39+ROUND(($A40-Inputs!$C$38)/Inputs!$C$39,0)))+NPV(D$39,OFFSET(Engine!$X$1,($L$39+ROUND(($A40-Inputs!$C$38)/Inputs!$C$39,0))-1,0,1,Inputs!$C$7))) -> -34.430108 | E40: =-$D$10*(INDEX(Engine!$W:$W,($L$39+ROUND(($A40-Inputs!$C$38)/Inputs!$C$39,0)))+NPV(E$39,OFFSET(Engine!$X$1,($L$39+ROUND(($A40-Inputs!$C$38)/Inputs!$C$39,0))-1,0,1,Inputs!$C$7))) -> -35.81184 | F40: =-$D$10*(INDEX(Engine!$W:$W,($L$39+ROUND(($A40-Inputs!$C$38)/Inputs!$C$39,0)))+NPV(F$39,OFFSET(Engine!$X$1,($L$39+ROUND(($A40-Inputs!$C$38)/Inputs!$C$39,0))-1,0,1,Inputs!$C$7))) -> -36.436745 | G40: =INDEX(Engine!$K:$K,($L$39+ROUND(($A40-Inputs!$C$38)/Inputs!$C$39,0))) -> -0.025625198
A41: 0.05 | B41: =-$D$10*(INDEX(Engine!$W:$W,($L$39+ROUND(($A41-Inputs!$C$38)/Inputs!$C$39,0)))+NPV(B$39,OFFSET(Engine!$X$1,($L$39+ROUND(($A41-Inputs!$C$38)/Inputs!$C$39,0))-1,0,1,Inputs!$C$7))) -> -21.190389 | C41: =-$D$10*(INDEX(Engine!$W:$W,($L$39+ROUND(($A41-Inputs!$C$38)/Inputs!$C$39,0)))+NPV(C$39,OFFSET(Engine!$X$1,($L$39+ROUND(($A41-Inputs!$C$38)/Inputs!$C$39,0))-1,0,1,Inputs!$C$7))) -> -24.31476 | D41: =-$D$10*(INDEX(Engine!$W:$W,($L$39+ROUND(($A41-Inputs!$C$38)/Inputs!$C$39,0)))+NPV(D$39,OFFSET(Engine!$X$1,($L$39+ROUND(($A41-Inputs!$C$38)/Inputs!$C$39,0))-1,0,1,Inputs!$C$7))) -> -27.892301 | E41: =-$D$10*(INDEX(Engine!$W:$W,($L$39+ROUND(($A41-Inputs!$C$38)/Inputs!$C$39,0)))+NPV(E$39,OFFSET(Engine!$X$1,($L$39+ROUND(($A41-Inputs!$C$38)/Inputs!$C$39,0))-1,0,1,Inputs!$C$7))) -> -30.448621 | F41: =-$D$10*(INDEX(Engine!$W:$W,($L$39+ROUND(($A41-Inputs!$C$38)/Inputs!$C$39,0)))+NPV(F$39,OFFSET(Engine!$X$1,($L$39+ROUND(($A41-Inputs!$C$38)/Inputs!$C$39,0))-1,0,1,Inputs!$C$7))) -> -31.717733 | G41: =INDEX(Engine!$K:$K,($L$39+ROUND(($A41-Inputs!$C$38)/Inputs!$C$39,0))) -> 0.021836081
A42: 0.1 | B42: =-$D$10*(INDEX(Engine!$W:$W,($L$39+ROUND(($A42-Inputs!$C$38)/Inputs!$C$39,0)))+NPV(B$39,OFFSET(Engine!$X$1,($L$39+ROUND(($A42-Inputs!$C$38)/Inputs!$C$39,0))-1,0,1,Inputs!$C$7))) -> -10.093671 | C42: =-$D$10*(INDEX(Engine!$W:$W,($L$39+ROUND(($A42-Inputs!$C$38)/Inputs!$C$39,0)))+NPV(C$39,OFFSET(Engine!$X$1,($L$39+ROUND(($A42-Inputs!$C$38)/Inputs!$C$39,0))-1,0,1,Inputs!$C$7))) -> -14.683152 | D42: =-$D$10*(INDEX(Engine!$W:$W,($L$39+ROUND(($A42-Inputs!$C$38)/Inputs!$C$39,0)))+NPV(D$39,OFFSET(Engine!$X$1,($L$39+ROUND(($A42-Inputs!$C$38)/Inputs!$C$39,0))-1,0,1,Inputs!$C$7))) -> -20.051574 | E42: =-$D$10*(INDEX(Engine!$W:$W,($L$39+ROUND(($A42-Inputs!$C$38)/Inputs!$C$39,0)))+NPV(E$39,OFFSET(Engine!$X$1,($L$39+ROUND(($A42-Inputs!$C$38)/Inputs!$C$39,0))-1,0,1,Inputs!$C$7))) -> -24.017034 | F42: =-$D$10*(INDEX(Engine!$W:$W,($L$39+ROUND(($A42-Inputs!$C$38)/Inputs!$C$39,0)))+NPV(F$39,OFFSET(Engine!$X$1,($L$39+ROUND(($A42-Inputs!$C$38)/Inputs!$C$39,0))-1,0,1,Inputs!$C$7))) -> -26.059225 | G42: =INDEX(Engine!$K:$K,($L$39+ROUND(($A42-Inputs!$C$38)/Inputs!$C$39,0))) -> 0.066474587
A43: 0.15 | B43: =-$D$10*(INDEX(Engine!$W:$W,($L$39+ROUND(($A43-Inputs!$C$38)/Inputs!$C$39,0)))+NPV(B$39,OFFSET(Engine!$X$1,($L$39+ROUND(($A43-Inputs!$C$38)/Inputs!$C$39,0))-1,0,1,Inputs!$C$7))) -> 4.279797 | C43: =-$D$10*(INDEX(Engine!$W:$W,($L$39+ROUND(($A43-Inputs!$C$38)/Inputs!$C$39,0)))+NPV(C$39,OFFSET(Engine!$X$1,($L$39+ROUND(($A43-Inputs!$C$38)/Inputs!$C$39,0))-1,0,1,Inputs!$C$7))) -> -2.2633156 | D43: =-$D$10*(INDEX(Engine!$W:$W,($L$39+ROUND(($A43-Inputs!$C$38)/Inputs!$C$39,0)))+NPV(D$39,OFFSET(Engine!$X$1,($L$39+ROUND(($A43-Inputs!$C$38)/Inputs!$C$39,0))-1,0,1,Inputs!$C$7))) -> -10.006175 | E43: =-$D$10*(INDEX(Engine!$W:$W,($L$39+ROUND(($A43-Inputs!$C$38)/Inputs!$C$39,0)))+NPV(E$39,OFFSET(Engine!$X$1,($L$39+ROUND(($A43-Inputs!$C$38)/Inputs!$C$39,0))-1,0,1,Inputs!$C$7))) -> -15.827402 | F43: =-$D$10*(INDEX(Engine!$W:$W,($L$39+ROUND(($A43-Inputs!$C$38)/Inputs!$C$39,0)))+NPV(F$39,OFFSET(Engine!$X$1,($L$39+ROUND(($A43-Inputs!$C$38)/Inputs!$C$39,0))-1,0,1,Inputs!$C$7))) -> -18.882116 | G43: =INDEX(Engine!$K:$K,($L$39+ROUND(($A43-Inputs!$C$38)/Inputs!$C$39,0))) -> 0.11263957
A44: 0.18 | B44: =-$D$10*(INDEX(Engine!$W:$W,($L$39+ROUND(($A44-Inputs!$C$38)/Inputs!$C$39,0)))+NPV(B$39,OFFSET(Engine!$X$1,($L$39+ROUND(($A44-Inputs!$C$38)/Inputs!$C$39,0))-1,0,1,Inputs!$C$7))) -> 14.824716 | C44: =-$D$10*(INDEX(Engine!$W:$W,($L$39+ROUND(($A44-Inputs!$C$38)/Inputs!$C$39,0)))+NPV(C$39,OFFSET(Engine!$X$1,($L$39+ROUND(($A44-Inputs!$C$38)/Inputs!$C$39,0))-1,0,1,Inputs!$C$7))) -> 6.812857 | D44: =-$D$10*(INDEX(Engine!$W:$W,($L$39+ROUND(($A44-Inputs!$C$38)/Inputs!$C$39,0)))+NPV(D$39,OFFSET(Engine!$X$1,($L$39+ROUND(($A44-Inputs!$C$38)/Inputs!$C$39,0))-1,0,1,Inputs!$C$7))) -> -2.7070055 | E44: =-$D$10*(INDEX(Engine!$W:$W,($L$39+ROUND(($A44-Inputs!$C$38)/Inputs!$C$39,0)))+NPV(E$39,OFFSET(Engine!$X$1,($L$39+ROUND(($A44-Inputs!$C$38)/Inputs!$C$39,0))-1,0,1,Inputs!$C$7))) -> -9.9094551 | F44: =-$D$10*(INDEX(Engine!$W:$W,($L$39+ROUND(($A44-Inputs!$C$38)/Inputs!$C$39,0)))+NPV(F$39,OFFSET(Engine!$X$1,($L$39+ROUND(($A44-Inputs!$C$38)/Inputs!$C$39,0))-1,0,1,Inputs!$C$7))) -> -13.714325 | G44: =INDEX(Engine!$K:$K,($L$39+ROUND(($A44-Inputs!$C$38)/Inputs!$C$39,0))) -> 0.14058131
A45: 0.2 | B45: =-$D$10*(INDEX(Engine!$W:$W,($L$39+ROUND(($A45-Inputs!$C$38)/Inputs!$C$39,0)))+NPV(B$39,OFFSET(Engine!$X$1,($L$39+ROUND(($A45-Inputs!$C$38)/Inputs!$C$39,0))-1,0,1,Inputs!$C$7))) -> 22.840569 | C45: =-$D$10*(INDEX(Engine!$W:$W,($L$39+ROUND(($A45-Inputs!$C$38)/Inputs!$C$39,0)))+NPV(C$39,OFFSET(Engine!$X$1,($L$39+ROUND(($A45-Inputs!$C$38)/Inputs!$C$39,0))-1,0,1,Inputs!$C$7))) -> 13.703344 | D45: =-$D$10*(INDEX(Engine!$W:$W,($L$39+ROUND(($A45-Inputs!$C$38)/Inputs!$C$39,0)))+NPV(D$39,OFFSET(Engine!$X$1,($L$39+ROUND(($A45-Inputs!$C$38)/Inputs!$C$39,0))-1,0,1,Inputs!$C$7))) -> 2.8236721 | E45: =-$D$10*(INDEX(Engine!$W:$W,($L$39+ROUND(($A45-Inputs!$C$38)/Inputs!$C$39,0)))+NPV(E$39,OFFSET(Engine!$X$1,($L$39+ROUND(($A45-Inputs!$C$38)/Inputs!$C$39,0))-1,0,1,Inputs!$C$7))) -> -5.4340427 | F45: =-$D$10*(INDEX(Engine!$W:$W,($L$39+ROUND(($A45-Inputs!$C$38)/Inputs!$C$39,0)))+NPV(F$39,OFFSET(Engine!$X$1,($L$39+ROUND(($A45-Inputs!$C$38)/Inputs!$C$39,0))-1,0,1,Inputs!$C$7))) -> -9.8112554 | G45: =INDEX(Engine!$K:$K,($L$39+ROUND(($A45-Inputs!$C$38)/Inputs!$C$39,0))) -> 0.15936141
A46: 0.22 | B46: =-$D$10*(INDEX(Engine!$W:$W,($L$39+ROUND(($A46-Inputs!$C$38)/Inputs!$C$39,0)))+NPV(B$39,OFFSET(Engine!$X$1,($L$39+ROUND(($A46-Inputs!$C$38)/Inputs!$C$39,0))-1,0,1,Inputs!$C$7))) -> 31.727008 | C46: =-$D$10*(INDEX(Engine!$W:$W,($L$39+ROUND(($A46-Inputs!$C$38)/Inputs!$C$39,0)))+NPV(C$39,OFFSET(Engine!$X$1,($L$39+ROUND(($A46-Inputs!$C$38)/Inputs!$C$39,0))-1,0,1,Inputs!$C$7))) -> 21.331884 | D46: =-$D$10*(INDEX(Engine!$W:$W,($L$39+ROUND(($A46-Inputs!$C$38)/Inputs!$C$39,0)))+NPV(D$39,OFFSET(Engine!$X$1,($L$39+ROUND(($A46-Inputs!$C$38)/Inputs!$C$39,0))-1,0,1,Inputs!$C$7))) -> 8.934274 | E46: =-$D$10*(INDEX(Engine!$W:$W,($L$39+ROUND(($A46-Inputs!$C$38)/Inputs!$C$39,0)))+NPV(E$39,OFFSET(Engine!$X$1,($L$39+ROUND(($A46-Inputs!$C$38)/Inputs!$C$39,0))-1,0,1,Inputs!$C$7))) -> -0.49946986 | F46: =-$D$10*(INDEX(Engine!$W:$W,($L$39+ROUND(($A46-Inputs!$C$38)/Inputs!$C$39,0)))+NPV(F$39,OFFSET(Engine!$X$1,($L$39+ROUND(($A46-Inputs!$C$38)/Inputs!$C$39,0))-1,0,1,Inputs!$C$7))) -> -5.5136124 | G46: =INDEX(Engine!$K:$K,($L$39+ROUND(($A46-Inputs!$C$38)/Inputs!$C$39,0))) -> 0.17819081
A47: 0.25 | B47: =-$D$10*(INDEX(Engine!$W:$W,($L$39+ROUND(($A47-Inputs!$C$38)/Inputs!$C$39,0)))+NPV(B$39,OFFSET(Engine!$X$1,($L$39+ROUND(($A47-Inputs!$C$38)/Inputs!$C$39,0))-1,0,1,Inputs!$C$7))) -> 46.862699 | C47: =-$D$10*(INDEX(Engine!$W:$W,($L$39+ROUND(($A47-Inputs!$C$38)/Inputs!$C$39,0)))+NPV(C$39,OFFSET(Engine!$X$1,($L$39+ROUND(($A47-Inputs!$C$38)/Inputs!$C$39,0))-1,0,1,Inputs!$C$7))) -> 34.299466 | D47: =-$D$10*(INDEX(Engine!$W:$W,($L$39+ROUND(($A47-Inputs!$C$38)/Inputs!$C$39,0)))+NPV(D$39,OFFSET(Engine!$X$1,($L$39+ROUND(($A47-Inputs!$C$38)/Inputs!$C$39,0))-1,0,1,Inputs!$C$7))) -> 19.290518 | E47: =-$D$10*(INDEX(Engine!$W:$W,($L$39+ROUND(($A47-Inputs!$C$38)/Inputs!$C$39,0)))+NPV(E$39,OFFSET(Engine!$X$1,($L$39+ROUND(($A47-Inputs!$C$38)/Inputs!$C$39,0))-1,0,1,Inputs!$C$7))) -> 7.8384526 | F47: =-$D$10*(INDEX(Engine!$W:$W,($L$39+ROUND(($A47-Inputs!$C$38)/Inputs!$C$39,0)))+NPV(F$39,OFFSET(Engine!$X$1,($L$39+ROUND(($A47-Inputs!$C$38)/Inputs!$C$39,0))-1,0,1,Inputs!$C$7))) -> 1.733461 | G47: =INDEX(Engine!$K:$K,($L$39+ROUND(($A47-Inputs!$C$38)/Inputs!$C$39,0))) -> 0.20638488
A48: 0.3 | B48: =-$D$10*(INDEX(Engine!$W:$W,($L$39+ROUND(($A48-Inputs!$C$38)/Inputs!$C$39,0)))+NPV(B$39,OFFSET(Engine!$X$1,($L$39+ROUND(($A48-Inputs!$C$38)/Inputs!$C$39,0))-1,0,1,Inputs!$C$7))) -> 77.933117 | C48: =-$D$10*(INDEX(Engine!$W:$W,($L$39+ROUND(($A48-Inputs!$C$38)/Inputs!$C$39,0)))+NPV(C$39,OFFSET(Engine!$X$1,($L$39+ROUND(($A48-Inputs!$C$38)/Inputs!$C$39,0))-1,0,1,Inputs!$C$7))) -> 60.873315 | D48: =-$D$10*(INDEX(Engine!$W:$W,($L$39+ROUND(($A48-Inputs!$C$38)/Inputs!$C$39,0)))+NPV(D$39,OFFSET(Engine!$X$1,($L$39+ROUND(($A48-Inputs!$C$38)/Inputs!$C$39,0))-1,0,1,Inputs!$C$7))) -> 40.457463 | E48: =-$D$10*(INDEX(Engine!$W:$W,($L$39+ROUND(($A48-Inputs!$C$38)/Inputs!$C$39,0)))+NPV(E$39,OFFSET(Engine!$X$1,($L$39+ROUND(($A48-Inputs!$C$38)/Inputs!$C$39,0))-1,0,1,Inputs!$C$7))) -> 24.834946 | F48: =-$D$10*(INDEX(Engine!$W:$W,($L$39+ROUND(($A48-Inputs!$C$38)/Inputs!$C$39,0)))+NPV(F$39,OFFSET(Engine!$X$1,($L$39+ROUND(($A48-Inputs!$C$38)/Inputs!$C$39,0))-1,0,1,Inputs!$C$7))) -> 16.479941 | G48: =INDEX(Engine!$K:$K,($L$39+ROUND(($A48-Inputs!$C$38)/Inputs!$C$39,0))) -> 0.25369121
A49: Growth rates must lie on the 1% grid (Inputs C38:C39). Positive = keeping the $75m adds value; negative = cutting adds value.
A51: F. OPERF's history with TPG (Exhibit 7, $ millions)
A52: Partnership | B52: Vintage | C52: Commitment | D52: Contributed | E52: Distributed | F52: Fair value | G52: TVPI | H52: IRR
A53: TPG Partners | B53: 1994 | C53: 50 | D53: 51.3 | E53: 181.1 | F53: 0 | G53: =IF(D53=0,0,(E53+F53)/D53) -> 3.5302144 | H53: 0.363
A54: TPG Partners II | B54: 1997 | C54: 300 | D54: 327.4 | E54: 547.8 | F54: 4.8 | G54: =IF(D54=0,0,(E54+F54)/D54) -> 1.6878436 | H54: 0.099
A55: TPG Partners III | B55: 2000 | C55: 300 | D55: 284.5 | E55: 565.7 | F55: 83.7 | G55: =IF(D55=0,0,(E55+F55)/D55) -> 2.2826011 | H55: 0.245
A56: TPG Partners IV | B56: 2003 | C56: 300 | D56: 330.8 | E56: 198.8 | F56: 226.9 | G56: =IF(D56=0,0,(E56+F56)/D56) -> 1.2868803 | H56: 0.112
A57: TPG Partners V | B57: 2006 | C57: 300 | D57: 253.1 | E57: 48.5 | F57: 131.3 | G57: =IF(D57=0,0,(E57+F57)/D57) -> 0.71039115 | H57: -0.167
A58: TPG STAR | B58: 2007 | C58: 100 | D58: 29.9 | E58: 0.2 | F58: 23.6 | G58: =IF(D58=0,0,(E58+F58)/D58) -> 0.79598662 | H58: NM
A59: TPG Partners VI | B59: 2008 | C59: 750 | D59: 79.9 | E59: 0.6 | F59: 47.5 | G59: =IF(D59=0,0,(E59+F59)/D59) -> 0.6020025 | H59: NM
A60: Total | C60: =SUM(C53:C59) -> 2100 | D60: =SUM(D53:D59) -> 1356.9 | E60: =SUM(E53:E59) -> 1542.7 | F60: =SUM(F53:F59) -> 517.8 | G60: =IF(D60=0,0,(E60+F60)/D60) -> 1.5185349 | H60: ~27%
A61: TVPI = (distributed + fair value) ÷ contributed; IRR from Exhibit 7; cumulative IRR of about 27% from case p.5. Note TPG VI was hit by the $437m WaMu loss (case p.5).
A63: G. Portfolio context — the denominator effect ($ millions)
A64: OPERF total fund value (Dec 2008) | C64: =Inputs!$C$32 -> 45800
A65: Private equity allocation ($) | C65: =Inputs!$C$33 -> 9800
A66: Private equity actual allocation (reported) | C66: =Inputs!$C$34 -> 0.219
A67: Private equity target allocation | C67: =Inputs!$C$35 -> 0.16
A68: Private equity at target ($) | C68: =Inputs!$C$32*Inputs!$C$35 -> 7328
A69: Over-allocation to private equity ($, reported %) | C69: =(Inputs!$C$34-Inputs!$C$35)*Inputs!$C$32 -> 2702.2
A70: $75m cut as % of the over-allocation | C70: =IF(C69=0,0,-$D$6/C69) -> 0.027755162
A71: $75m cut as % of OPERF total fund | C71: =-$D$6/Inputs!$C$32 -> 0.0016375546
A72: Unfunded TPG VI commitment as % of OPERF total fund (keep) | C72: =$B$8/Inputs!$C$32 -> 0.014631004
A73: The cut barely dents the over-allocation, and OPERF says it can meet future capital calls (case p.5) — liquidity is not the binding constraint.
A75: H. Decision summary (numbers update with the model)
A76: ="Keeping the full $750m is worth $"&TEXT(B20,"#,##0.0")&"m NPV at 15%; the $75m tranche alone is worth $"&TEXT(-D20,"#,##0.0")&"m." -> Keeping the full $750m is worth $28.2m NPV at 15%; the $75m tranche alone is worth $2.8m.
A77: ="Cutting saves $"&TEXT(-D15,"#,##0.0")&"m of fees over 10 years, but the $75m only destroys value if TPG VI assets grow less than "&IF(ISNUMBER(C31),TEXT(C31,"0.0%"),"n/a")&" a year." -> Cutting saves $10.1m of fees over 10 years, but the $75m only destroys value if TPG VI assets grow less than 19.0% a year.
A78: ="Base case sits only "&IF(ISNUMBER(C33),TEXT(C33*100,"0.0"),"n/a")&" percentage points above break-even — the decision turns on OPERF's view of 2009–13 buyout returns, not on fees." -> Base case sits only 1.0 percentage points above break-even — the decision turns on OPERF's view of 2009–13 buyout returns, not on fees.
A79: ="Section E: at a 15% required return the $75m is worth $"&TEXT(D45,"#,##0.0")&"m at 20% growth but $"&TEXT(D43,"#,##0.0")&"m at 15% growth." -> Section E: at a 15% required return the $75m is worth $2.8m at 20% growth but $-10.0m at 15% growth.

Sheet Sensitivity
A1: SENSITIVITY — how each fee structure performs as fund returns change
A2: Rows = annual growth of invested assets (all other Prep Q3 assumptions unchanged). Values come from the Engine grid.
A4: Table 1 — LP net IRR | I4: Table 2 — LP NPV at the discount rate ($m)
A5: Asset growth | B5: Current terms 1.50% / 20% | C5: TPG offer 1.35% / 20% | D5: Offer + 8% hard hurdle | E5: Offer + 8% soft hurdle | F5: Offer + 15% carry | G5: Required return | I5: Asset growth | J5: Current terms 1.50% / 20% | K5: TPG offer 1.35% / 20% | L5: Offer + 8% hard hurdle | M5: Offer + 8% soft hurdle | N5: Offer + 15% carry
A6: =Engine!$I$21 -> 0 | B6: =Engine!$K$21 -> -0.028740632 | C6: =Engine!$K$52 -> -0.025625198 | D6: =Engine!$K$83 -> -0.025625198 | E6: =Engine!$K$114 -> -0.025625198 | F6: =Engine!$K$145 -> -0.025625198 | G6: =Inputs!$C$9 -> 0.15 | I6: =A6 -> 0 | J6: =Engine!$L$21 -> -9275.938 | K6: =Engine!$L$52 -> -9181.3622 | L6: =Engine!$L$83 -> -9181.3622 | M6: =Engine!$L$114 -> -9181.3622 | N6: =Engine!$L$145 -> -9181.3622
A7: =Engine!$I$22 -> 0.01 | B7: =Engine!$K$22 -> -0.018139558 | C7: =Engine!$K$53 -> -0.01509821 | D7: =Engine!$K$84 -> -0.01509821 | E7: =Engine!$K$115 -> -0.01509821 | F7: =Engine!$K$146 -> -0.01509821 | G7: =Inputs!$C$9 -> 0.15 | I7: =A7 -> 0.01 | J7: =Engine!$L$22 -> -8938.1447 | K7: =Engine!$L$53 -> -8839.821 | L7: =Engine!$L$84 -> -8839.821 | M7: =Engine!$L$115 -> -8839.821 | N7: =Engine!$L$146 -> -8839.821
A8: =Engine!$I$23 -> 0.02 | B8: =Engine!$K$23 -> -0.0075786649 | C8: =Engine!$K$54 -> -0.0046060678 | D8: =Engine!$K$85 -> -0.0046060678 | E8: =Engine!$K$116 -> -0.0046060678 | F8: =Engine!$K$147 -> -0.0046060678 | G8: =Inputs!$C$9 -> 0.15 | I8: =A8 -> 0.02 | J8: =Engine!$L$23 -> -8581.7911 | K8: =Engine!$L$54 -> -8479.5492 | L8: =Engine!$L$85 -> -8479.5492 | M8: =Engine!$L$116 -> -8479.5492 | N8: =Engine!$L$147 -> -8479.5492
A9: =Engine!$I$24 -> 0.03 | B9: =Engine!$K$24 -> 0.0023622052 | C9: =Engine!$K$55 -> 0.0047073955 | D9: =Engine!$K$86 -> 0.0058537279 | E9: =Engine!$K$117 -> 0.0058537279 | F9: =Engine!$K$148 -> 0.0049950858 | G9: =Inputs!$C$9 -> 0.15 | I9: =A9 -> 0.03 | J9: =Engine!$L$24 -> -8222.5364 | K9: =Engine!$L$55 -> -8132.9392 | L9: =Engine!$L$86 -> -8099.5434 | M9: =Engine!$L$117 -> -8099.5434 | N9: =Engine!$L$148 -> -8124.5902
A10: =Engine!$I$25 -> 0.04 | B10: =Engine!$K$25 -> 0.010874067 | C10: =Engine!$K$56 -> 0.013212039 | D10: =Engine!$K$87 -> 0.016283454 | E10: =Engine!$K$118 -> 0.016283454 | F10: =Engine!$K$149 -> 0.013987815 | G10: =Inputs!$C$9 -> 0.15 | I10: =A10 -> 0.04 | J10: =Engine!$L$25 -> -7887.7204 | K10: =Engine!$L$56 -> -7794.5375 | L10: =Engine!$L$87 -> -7698.7494 | M10: =Engine!$L$118 -> -7698.7494 | N10: =Engine!$L$149 -> -7770.5905
A11: =Engine!$I$26 -> 0.05 | B11: =Engine!$K$26 -> 0.019506054 | C11: =Engine!$K$57 -> 0.021836081 | D11: =Engine!$K$88 -> 0.026685192 | E11: =Engine!$K$119 -> 0.026685192 | F11: =Engine!$K$150 -> 0.023068031 | G11: =Inputs!$C$9 -> 0.15 | I11: =A11 -> 0.05 | J11: =Engine!$L$26 -> -7534.8785 | K11: =Engine!$L$57 -> -7437.9469 | L11: =Engine!$L$88 -> -7276.0601 | M11: =Engine!$L$119 -> -7276.0601 | N11: =Engine!$L$150 -> -7397.4752
A12: =Engine!$I$27 -> 0.06 | B12: =Engine!$K$27 -> 0.02824991 | C12: =Engine!$K$58 -> 0.030571398 | D12: =Engine!$K$89 -> 0.037060845 | E12: =Engine!$K$120 -> 0.037060845 | F12: =Engine!$K$151 -> 0.032228853 | G12: =Inputs!$C$9 -> 0.15 | I12: =A12 -> 0.06 | J12: =Engine!$L$27 -> -7163.0649 | K12: =Engine!$L$58 -> -7062.2135 | L12: =Engine!$L$89 -> -6830.3127 | M12: =Engine!$L$120 -> -6830.3127 | N12: =Engine!$L$151 -> -7004.2383
A13: =Engine!$I$28 -> 0.07 | B13: =Engine!$K$28 -> 0.037097702 | C13: =Engine!$K$59 -> 0.039410186 | D13: =Engine!$K$90 -> 0.04741216 | E13: =Engine!$K$121 -> 0.04741216 | F13: =Engine!$K$152 -> 0.04146381 | G13: =Inputs!$C$9 -> 0.15 | I13: =A13 -> 0.07 | J13: =Engine!$L$28 -> -6771.2873 | K13: =Engine!$L$59 -> -6666.3366 | L13: =Engine!$L$90 -> -6360.2869 | M13: =Engine!$L$121 -> -6360.2869 | N13: =Engine!$L$152 -> -6589.8242
A14: =Engine!$I$29 -> 0.08 | B14: =Engine!$K$29 -> 0.046041852 | C14: =Engine!$K$60 -> 0.048344985 | D14: =Engine!$K$91 -> 0.057740739 | E14: =Engine!$K$122 -> 0.057740739 | F14: =Engine!$K$153 -> 0.050766843 | G14: =Inputs!$C$9 -> 0.15 | I14: =A14 -> 0.08 | J14: =Engine!$L$29 -> -6358.5045 | K14: =Engine!$L$60 -> -6249.2662 | L14: =Engine!$L$91 -> -5864.7017 | M14: =Engine!$L$122 -> -5864.7017 | N14: =Engine!$L$153 -> -6153.1251
A15: =Engine!$I$30 -> 0.09 | B15: =Engine!$K$30 -> 0.055075155 | C15: =Engine!$K$61 -> 0.057368694 | D15: =Engine!$K$92 -> 0.068048059 | E15: =Engine!$K$123 -> 0.068048059 | F15: =Engine!$K$154 -> 0.060132291 | G15: =Inputs!$C$9 -> 0.15 | I15: =A15 -> 0.09 | J15: =Engine!$L$30 -> -5923.6244 | K15: =Engine!$L$61 -> -5809.9011 | L15: =Engine!$L$92 -> -5342.2129 | M15: =Engine!$L$123 -> -5342.2129 | N15: =Engine!$L$154 -> -5692.979
A16: =Engine!$I$31 -> 0.1 | B16: =Engine!$K$31 -> 0.064190788 | C16: =Engine!$K$62 -> 0.066474587 | D16: =Engine!$K$93 -> 0.078335477 | E16: =Engine!$K$124 -> 0.078335477 | F16: =Engine!$K$155 -> 0.069554885 | G16: =Inputs!$C$9 -> 0.15 | I16: =A16 -> 0.1 | J16: =Engine!$L$31 -> -5465.5015 | K16: =Engine!$L$62 -> -5347.0863 | L16: =Engine!$L$93 -> -4791.4101 | M16: =Engine!$L$124 -> -4791.4101 | N16: =Engine!$L$155 -> -5208.1672
A17: =Engine!$I$32 -> 0.11 | B17: =Engine!$K$32 -> 0.073382315 | C17: =Engine!$K$63 -> 0.075649634 | D17: =Engine!$K$94 -> 0.086932782 | E17: =Engine!$K$125 -> 0.08 | F17: =Engine!$K$156 -> 0.079024641 | G17: =Inputs!$C$9 -> 0.15 | I17: =A17 -> 0.11 | J17: =Engine!$L$32 -> -4982.9351 | K17: =Engine!$L$63 -> -4860.2387 | L17: =Engine!$L$94 -> -4298.6282 | M17: =Engine!$L$125 -> -4649.8843 | N17: =Engine!$L$156 -> -4697.8825
A18: =Engine!$I$33 -> 0.12 | B18: =Engine!$K$33 -> 0.082579186 | C18: =Engine!$K$64 -> 0.084823201 | D18: =Engine!$K$95 -> 0.09531737 | E18: =Engine!$K$126 -> 0.084907908 | F18: =Engine!$K$157 -> 0.088488038 | G18: =Inputs!$C$9 -> 0.15 | I18: =A18 -> 0.12 | J18: =Engine!$L$33 -> -4480.4887 | K18: =Engine!$L$64 -> -4353.763 | L18: =Engine!$L$95 -> -3796.8531 | M18: =Engine!$L$126 -> -4346.2052 | N18: =Engine!$L$157 -> -4165.0407
A19: =Engine!$I$34 -> 0.13 | B19: =Engine!$K$34 -> 0.091818991 | C19: =Engine!$K$65 -> 0.094051125 | D19: =Engine!$K$96 -> 0.10381685 | E19: =Engine!$K$127 -> 0.094223763 | F19: =Engine!$K$158 -> 0.097987849 | G19: =Inputs!$C$9 -> 0.15 | I19: =A19 -> 0.13 | J19: =Engine!$L$34 -> -3952.3666 | K19: =Engine!$L$65 -> -3820.3318 | L19: =Engine!$L$96 -> -3268.254 | M19: =Engine!$L$127 -> -3805.5391 | N19: =Engine!$L$158 -> -3603.7396
A20: =Engine!$I$35 -> 0.14 | B20: =Engine!$K$35 -> 0.10110885 | C20: =Engine!$K$66 -> 0.1033296 | D20: =Engine!$K$97 -> 0.11242424 | E20: =Engine!$K$128 -> 0.10359865 | F20: =Engine!$K$159 -> 0.1075213 | G20: =Inputs!$C$9 -> 0.15 | I20: =A20 -> 0.14 | J20: =Engine!$L$35 -> -3396.155 | K20: =Engine!$L$66 -> -3258.5637 | L20: =Engine!$L$97 -> -2711.4518 | M20: =Engine!$L$128 -> -3236.2184 | N20: =Engine!$L$159 -> -3012.5169
A21: =Engine!$I$36 -> 0.15 | B21: =Engine!$K$36 -> 0.1104452 | C21: =Engine!$K$67 -> 0.11263957 | D21: =Engine!$K$98 -> 0.12113278 | E21: =Engine!$K$129 -> 0.11302767 | F21: =Engine!$K$160 -> 0.11707413 | G21: =Inputs!$C$9 -> 0.15 | I21: =A21 -> 0.15 | J21: =Engine!$L$36 -> -2810.4186 | K21: =Engine!$L$67 -> -2668.3133 | L21: =Engine!$L$98 -> -2125.0018 | M21: =Engine!$L$129 -> -2636.7827 | N21: =Engine!$L$160 -> -2390.8169
A22: =Engine!$I$37 -> 0.16 | B22: =Engine!$K$37 -> 0.1197434 | C22: =Engine!$K$68 -> 0.12192045 | D22: =Engine!$K$99 -> 0.12993594 | E22: =Engine!$K$130 -> 0.1225063 | F22: =Engine!$K$161 -> 0.12660091 | G22: =Inputs!$C$9 -> 0.15 | I22: =A22 -> 0.16 | J22: =Engine!$L$37 -> -2200.3512 | K22: =Engine!$L$68 -> -2052.6596 | L22: =Engine!$L$99 -> -1507.3904 | M22: =Engine!$L$130 -> -2005.7024 | N22: =Engine!$L$161 -> -1740.4809
A23: =Engine!$I$38 -> 0.17 | B23: =Engine!$K$38 -> 0.12906936 | C23: =Engine!$K$69 -> 0.13123503 | D23: =Engine!$K$100 -> 0.13882749 | E23: =Engine!$K$131 -> 0.1320303 | F23: =Engine!$K$162 -> 0.13614932 | G23: =Inputs!$C$9 -> 0.15 | I23: =A23 -> 0.17 | J23: =Engine!$L$38 -> -1558.3954 | K23: =Engine!$L$69 -> -1404.3955 | L23: =Engine!$L$100 -> -857.0324 | M23: =Engine!$L$131 -> -1341.3756 | N23: =Engine!$L$162 -> -1055.6135
A24: =Engine!$I$39 -> 0.18 | B24: =Engine!$K$39 -> 0.13842629 | C24: =Engine!$K$70 -> 0.14058131 | D24: =Engine!$K$101 -> 0.14780145 | E24: =Engine!$K$132 -> 0.14159577 | F24: =Engine!$K$163 -> 0.14571799 | G24: =Inputs!$C$9 -> 0.15 | I24: =A24 -> 0.18 | J24: =Engine!$L$39 -> -882.47286 | K24: =Engine!$L$70 -> -721.86812 | L24: =Engine!$L$101 -> -172.26781 | M24: =Engine!$L$132 -> -642.1254 | N24: =Engine!$L$163 -> -334.46138
A25: =Engine!$I$40 -> 0.19 | B25: =Engine!$K$40 -> 0.14781229 | C25: =Engine!$K$71 -> 0.14995737 | D25: =Engine!$K$102 -> 0.15685212 | E25: =Engine!$K$133 -> 0.15119909 | F25: =Engine!$K$164 -> 0.15530561 | G25: =Inputs!$C$9 -> 0.15 | I25: =A25 -> 0.19 | J25: =Engine!$L$40 -> -170.86748 | K25: =Engine!$L$71 -> -3.346981 | L25: =Engine!$L$102 -> 548.64108 | M25: =Engine!$L$133 -> 93.803665 | N25: =Engine!$L$164 -> 424.81074
A26: =Engine!$I$41 -> 0.2 | B26: =Engine!$K$41 -> 0.15722559 | C26: =Engine!$K$72 -> 0.15936141 | D26: =Engine!$K$103 -> 0.16591822 | E26: =Engine!$K$134 -> 0.16029224 | F26: =Engine!$K$165 -> 0.16491098 | G26: =Inputs!$C$9 -> 0.15 | I26: =A26 -> 0.2 | J26: =Engine!$L$41 -> 578.21714 | K26: =Engine!$L$72 -> 752.97923 | L26: =Engine!$L$103 -> 1303.5385 | M26: =Engine!$L$134 -> 825.66274 | N26: =Engine!$L$165 -> 1224.1241
A27: =Engine!$I$42 -> 0.21 | B27: =Engine!$K$42 -> 0.16666452 | C27: =Engine!$K$73 -> 0.16879174 | D27: =Engine!$K$104 -> 0.17502424 | E27: =Engine!$K$135 -> 0.16942162 | F27: =Engine!$K$166 -> 0.17453297 | G27: =Inputs!$C$9 -> 0.15 | I27: =A27 -> 0.21 | J27: =Engine!$L$42 -> 1366.6608 | K27: =Engine!$L$73 -> 1549.006 | L27: =Engine!$L$104 -> 2096.8383 | M27: =Engine!$L$135 -> 1597.8779 | N27: =Engine!$L$166 -> 2065.4894
A28: =Engine!$I$43 -> 0.22 | B28: =Engine!$K$43 -> 0.17609589 | C28: =Engine!$K$74 -> 0.17819081 | D28: =Engine!$K$105 -> 0.18418323 | E28: =Engine!$K$136 -> 0.17899352 | F28: =Engine!$K$167 -> 0.18412859 | G28: =Inputs!$C$9 -> 0.15 | I28: =A28 -> 0.22 | J28: =Engine!$L$43 -> 2194.0279 | K28: =Engine!$L$74 -> 2382.4731 | L28: =Engine!$L$105 -> 2931.7696 | M28: =Engine!$L$136 -> 2444.6088 | N28: =Engine!$L$167 -> 2947.8278
A29: =Engine!$I$44 -> 0.23 | B29: =Engine!$K$44 -> 0.18548467 | C29: =Engine!$K$75 -> 0.18757116 | D29: =Engine!$K$106 -> 0.19339183 | E29: =Engine!$K$137 -> 0.18859103 | F29: =Engine!$K$168 -> 0.19370752 | G29: =Inputs!$C$9 -> 0.15 | I29: =A29 -> 0.23 | J29: =Engine!$L$44 -> 3059.8898 | K29: =Engine!$L$75 -> 3256.589 | L29: =Engine!$L$106 -> 3810.4068 | M29: =Engine!$L$137 -> 3335.4387 | N29: =Engine!$L$168 -> 3874.1904
A30: =Engine!$I$45 -> 0.24 | B30: =Engine!$K$45 -> 0.19489071 | C30: =Engine!$K$76 -> 0.19696947 | D30: =Engine!$K$107 -> 0.20259235 | E30: =Engine!$K$138 -> 0.19775975 | F30: =Engine!$K$169 -> 0.20329739 | G30: =Inputs!$C$9 -> 0.15 | I30: =A30 -> 0.24 | J30: =Engine!$L$45 -> 3971.0462 | K30: =Engine!$L$76 -> 4176.3903 | L30: =Engine!$L$107 -> 4731.63 | M30: =Engine!$L$138 -> 4237.3076 | N30: =Engine!$L$169 -> 4849.0289
A31: =Engine!$I$46 -> 0.25 | B31: =Engine!$K$46 -> 0.20431317 | C31: =Engine!$K$77 -> 0.20638488 | D31: =Engine!$K$108 -> 0.21180159 | E31: =Engine!$K$139 -> 0.20674553 | F31: =Engine!$K$170 -> 0.21289765 | G31: =Inputs!$C$9 -> 0.15 | I31: =A31 -> 0.25 | J31: =Engine!$L$46 -> 4929.74 | K31: =Engine!$L$77 -> 5144.1382 | L31: =Engine!$L$108 -> 5699.0875 | M31: =Engine!$L$139 -> 5171.173 | N31: =Engine!$L$170 -> 5874.7447
A32: =Engine!$I$47 -> 0.26 | B32: =Engine!$K$47 -> 0.21375128 | C32: =Engine!$K$78 -> 0.21581657 | D32: =Engine!$K$109 -> 0.22104536 | E32: =Engine!$K$140 -> 0.21628522 | F32: =Engine!$K$171 -> 0.22250781 | G32: =Inputs!$C$9 -> 0.15 | I32: =A32 -> 0.26 | J32: =Engine!$L$47 -> 5938.316 | K32: =Engine!$L$78 -> 6162.197 | L32: =Engine!$L$109 -> 6716.869 | M32: =Engine!$L$140 -> 6197.3323 | N32: =Engine!$L$171 -> 6953.8481
A33: =Engine!$I$48 -> 0.27 | B33: =Engine!$K$48 -> 0.22320427 | C33: =Engine!$K$79 -> 0.22526377 | D33: =Engine!$K$110 -> 0.23032176 | E33: =Engine!$K$141 -> 0.22584295 | F33: =Engine!$K$172 -> 0.23212738 | G33: =Inputs!$C$9 -> 0.15 | I33: =A33 -> 0.27 | J33: =Engine!$L$48 -> 6999.2249 | K33: =Engine!$L$79 -> 7233.0378 | L33: =Engine!$L$110 -> 7787.4467 | M33: =Engine!$L$141 -> 7276.537 | N33: =Engine!$L$172 -> 8088.9632
A34: =Engine!$I$49 -> 0.28 | B34: =Engine!$K$49 -> 0.23267145 | C34: =Engine!$K$80 -> 0.23472574 | D34: =Engine!$K$111 -> 0.23962897 | E34: =Engine!$K$142 -> 0.23541761 | F34: =Engine!$K$173 -> 0.24175592 | G34: =Inputs!$C$9 -> 0.15 | I34: =A34 -> 0.28 | J34: =Engine!$L$49 -> 8115.0278 | K34: =Engine!$L$80 -> 8359.2427 | L34: =Engine!$L$111 -> 8913.4039 | M34: =Engine!$L$142 -> 8411.377 | N34: =Engine!$L$173 -> 9282.8321
A35: =Engine!$I$50 -> 0.29 | B35: =Engine!$K$50 -> 0.24215213 | C35: =Engine!$K$81 -> 0.24420178 | D35: =Engine!$K$112 -> 0.24896529 | E35: =Engine!$K$143 -> 0.24500816 | F35: =Engine!$K$174 -> 0.25139299 | G35: =Inputs!$C$9 -> 0.15 | I35: =A35 -> 0.29 | J35: =Engine!$L$50 -> 9288.4004 | K35: =Engine!$L$81 -> 9543.5097 | L35: =Engine!$L$112 -> 10097.439 | M35: =Engine!$L$143 -> 9604.5576 | N35: =Engine!$L$174 -> 10538.32
A36: =Engine!$I$51 -> 0.3 | B36: =Engine!$K$51 -> 0.25164567 | C36: =Engine!$K$82 -> 0.25369121 | D36: =Engine!$K$113 -> 0.25832909 | E36: =Engine!$K$144 -> 0.25461362 | F36: =Engine!$K$175 -> 0.26103818 | G36: =Inputs!$C$9 -> 0.15 | I36: =A36 -> 0.3 | J36: =Engine!$L$51 -> 10522.138 | K36: =Engine!$L$82 -> 10788.657 | L36: =Engine!$L$113 -> 11342.373 | M36: =Engine!$L$144 -> 10858.905 | N36: =Engine!$L$175 -> 11858.419
A38: Break-even asset growth (LP IRR = required return) | B38: =IFERROR(INDEX($A$6:$A$36,MATCH(Inputs!$C$9,B$6:B$36,1))+(Inputs!$C$9-INDEX(B$6:B$36,MATCH(Inputs!$C$9,B$6:B$36,1)))/(INDEX(B$6:B$36,MATCH(Inputs!$C$9,B$6:B$36,1)+1)-INDEX(B$6:B$36,MATCH(Inputs!$C$9,B$6:B$36,1)))*(INDEX($A$6:$A$36,MATCH(Inputs!$C$9,B$6:B$36,1)+1)-INDEX($A$6:$A$36,MATCH(Inputs!$C$9,B$6:B$36,1))),"n/a") -> 0.19232406 | C38: =IFERROR(INDEX($A$6:$A$36,MATCH(Inputs!$C$9,C$6:C$36,1))+(Inputs!$C$9-INDEX(C$6:C$36,MATCH(Inputs!$C$9,C$6:C$36,1)))/(INDEX(C$6:C$36,MATCH(Inputs!$C$9,C$6:C$36,1)+1)-INDEX(C$6:C$36,MATCH(Inputs!$C$9,C$6:C$36,1)))*(INDEX($A$6:$A$36,MATCH(Inputs!$C$9,C$6:C$36,1)+1)-INDEX($A$6:$A$36,MATCH(Inputs!$C$9,C$6:C$36,1))),"n/a") -> 0.19004534 | D38: =IFERROR(INDEX($A$6:$A$36,MATCH(Inputs!$C$9,D$6:D$36,1))+(Inputs!$C$9-INDEX(D$6:D$36,MATCH(Inputs!$C$9,D$6:D$36,1)))/(INDEX(D$6:D$36,MATCH(Inputs!$C$9,D$6:D$36,1)+1)-INDEX(D$6:D$36,MATCH(Inputs!$C$9,D$6:D$36,1)))*(INDEX($A$6:$A$36,MATCH(Inputs!$C$9,D$6:D$36,1)+1)-INDEX($A$6:$A$36,MATCH(Inputs!$C$9,D$6:D$36,1))),"n/a") -> 0.18242916 | E38: =IFERROR(INDEX($A$6:$A$36,MATCH(Inputs!$C$9,E$6:E$36,1))+(Inputs!$C$9-INDEX(E$6:E$36,MATCH(Inputs!$C$9,E$6:E$36,1)))/(INDEX(E$6:E$36,MATCH(Inputs!$C$9,E$6:E$36,1)+1)-INDEX(E$6:E$36,MATCH(Inputs!$C$9,E$6:E$36,1)))*(INDEX($A$6:$A$36,MATCH(Inputs!$C$9,E$6:E$36,1)+1)-INDEX($A$6:$A$36,MATCH(Inputs!$C$9,E$6:E$36,1))),"n/a") -> 0.18875137 | F38: =IFERROR(INDEX($A$6:$A$36,MATCH(Inputs!$C$9,F$6:F$36,1))+(Inputs!$C$9-INDEX(F$6:F$36,MATCH(Inputs!$C$9,F$6:F$36,1)))/(INDEX(F$6:F$36,MATCH(Inputs!$C$9,F$6:F$36,1)+1)-INDEX(F$6:F$36,MATCH(Inputs!$C$9,F$6:F$36,1)))*(INDEX($A$6:$A$36,MATCH(Inputs!$C$9,F$6:F$36,1)+1)-INDEX($A$6:$A$36,MATCH(Inputs!$C$9,F$6:F$36,1))),"n/a") -> 0.18446619
A39: Interpolated from Table 1; above this growth rate the commitment has positive NPV.
A42: Table 3 — LP IRR gain vs current terms (bps) | I42: Table 4 — TPG compensation under current terms (PV at discount rate, $m)
A43: Asset growth | B43: LP IRR — current terms | C43: TPG offer 1.35% / 20% | D43: Offer + 8% hard hurdle | E43: Offer + 8% soft hurdle | F43: Offer + 15% carry | I43: Asset growth | J43: PV mgmt fees | K43: PV carried interest | L43: PV total GP comp | M43: Fees as % of GP comp | N43: LP NPV
A44: =A6 -> 0 | B44: =B6 -> -0.028740632 | C44: =(C6-$B6)*10000 -> 31.154342 | D44: =(D6-$B6)*10000 -> 31.154342 | E44: =(E6-$B6)*10000 -> 31.154342 | F44: =(F6-$B6)*10000 -> 31.154342 | I44: =A6 -> 0 | J44: =Engine!$Q$21 -> 1731.4752 | K44: =Engine!$R$21 -> 0 | L44: =J44+K44 -> 1731.4752 | M44: =IF(L44=0,0,J44/L44) -> 1 | N44: =J6 -> -9275.938
A45: =A7 -> 0.01 | B45: =B7 -> -0.018139558 | C45: =(C7-$B7)*10000 -> 30.413478 | D45: =(D7-$B7)*10000 -> 30.413478 | E45: =(E7-$B7)*10000 -> 30.413478 | F45: =(F7-$B7)*10000 -> 30.413478 | I45: =A7 -> 0.01 | J45: =Engine!$Q$22 -> 1731.4752 | K45: =Engine!$R$22 -> 0 | L45: =J45+K45 -> 1731.4752 | M45: =IF(L45=0,0,J45/L45) -> 1 | N45: =J7 -> -8938.1447
A46: =A8 -> 0.02 | B46: =B8 -> -0.0075786649 | C46: =(C8-$B8)*10000 -> 29.725971 | D46: =(D8-$B8)*10000 -> 29.725971 | E46: =(E8-$B8)*10000 -> 29.725971 | F46: =(F8-$B8)*10000 -> 29.725971 | I46: =A8 -> 0.02 | J46: =Engine!$Q$23 -> 1731.4752 | K46: =Engine!$R$23 -> 0 | L46: =J46+K46 -> 1731.4752 | M46: =IF(L46=0,0,J46/L46) -> 1 | N46: =J8 -> -8581.7911
A47: =A9 -> 0.03 | B47: =B9 -> 0.0023622052 | C47: =(C9-$B9)*10000 -> 23.451903 | D47: =(D9-$B9)*10000 -> 34.915227 | E47: =(E9-$B9)*10000 -> 34.915227 | F47: =(F9-$B9)*10000 -> 26.328805 | I47: =A9 -> 0.03 | J47: =Engine!$Q$24 -> 1731.4752 | K47: =Engine!$R$24 -> 16.654056 | L47: =J47+K47 -> 1748.1292 | M47: =IF(L47=0,0,J47/L47) -> 0.99047321 | N47: =J9 -> -8222.5364
A48: =A10 -> 0.04 | B48: =B10 -> 0.010874067 | C48: =(C10-$B10)*10000 -> 23.379725 | D48: =(D10-$B10)*10000 -> 54.093876 | E48: =(E10-$B10)*10000 -> 54.093876 | F48: =(F10-$B10)*10000 -> 31.137479 | I48: =A10 -> 0.04 | J48: =Engine!$Q$25 -> 1731.4752 | K48: =Engine!$R$25 -> 78.347339 | L48: =J48+K48 -> 1809.8225 | M48: =IF(L48=0,0,J48/L48) -> 0.95670993 | N48: =J10 -> -7887.7204
A49: =A11 -> 0.05 | B49: =B11 -> 0.019506054 | C49: =(C11-$B11)*10000 -> 23.300264 | D49: =(D11-$B11)*10000 -> 71.791374 | E49: =(E11-$B11)*10000 -> 71.791374 | F49: =(F11-$B11)*10000 -> 35.61977 | I49: =A11 -> 0.05 | J49: =Engine!$Q$26 -> 1731.4752 | K49: =Engine!$R$26 -> 143.71312 | L49: =J49+K49 -> 1875.1883 | M49: =IF(L49=0,0,J49/L49) -> 0.9233607 | N49: =J11 -> -7534.8785
A50: =A12 -> 0.06 | B50: =B12 -> 0.02824991 | C50: =(C12-$B12)*10000 -> 23.214882 | D50: =(D12-$B12)*10000 -> 88.10935 | E50: =(E12-$B12)*10000 -> 88.10935 | F50: =(F12-$B12)*10000 -> 39.789432 | I50: =A12 -> 0.06 | J50: =Engine!$Q$27 -> 1731.4752 | K50: =Engine!$R$27 -> 212.95852 | L50: =J50+K50 -> 1944.4337 | M50: =IF(L50=0,0,J50/L50) -> 0.89047787 | N50: =J12 -> -7163.0649
A51: =A13 -> 0.07 | B51: =B13 -> 0.037097702 | C51: =(C13-$B13)*10000 -> 23.124846 | D51: =(D13-$B13)*10000 -> 103.14458 | E51: =(E13-$B13)*10000 -> 103.14458 | F51: =(F13-$B13)*10000 -> 43.661086 | I51: =A13 -> 0.07 | J51: =Engine!$Q$28 -> 1731.4752 | K51: =Engine!$R$28 -> 286.30141 | L51: =J51+K51 -> 2017.7766 | M51: =IF(L51=0,0,J51/L51) -> 0.85811045 | N51: =J13 -> -6771.2873
A52: =A14 -> 0.08 | B52: =B14 -> 0.046041852 | C52: =(C14-$B14)*10000 -> 23.031324 | D52: =(D14-$B14)*10000 -> 116.98887 | E52: =(E14-$B14)*10000 -> 116.98887 | F52: =(F14-$B14)*10000 -> 47.249907 | I52: =A14 -> 0.08 | J52: =Engine!$Q$29 -> 1731.4752 | K52: =Engine!$R$29 -> 363.97092 | L52: =J52+K52 -> 2095.4461 | M52: =IF(L52=0,0,J52/L52) -> 0.82630385 | N52: =J14 -> -6358.5045
A53: =A15 -> 0.09 | B53: =B15 -> 0.055075155 | C53: =(C15-$B15)*10000 -> 22.935384 | D53: =(D15-$B15)*10000 -> 129.72903 | E53: =(E15-$B15)*10000 -> 129.72903 | F53: =(F15-$B15)*10000 -> 50.57136 | I53: =A15 -> 0.09 | J53: =Engine!$Q$30 -> 1731.4752 | K53: =Engine!$R$30 -> 446.20792 | L53: =J53+K53 -> 2177.6831 | M53: =IF(L53=0,0,J53/L53) -> 0.7950997 | N53: =J15 -> -5923.6244
A54: =A16 -> 0.1 | B54: =B16 -> 0.064190788 | C54: =(C16-$B16)*10000 -> 22.83799 | D54: =(D16-$B16)*10000 -> 141.44689 | E54: =(E16-$B16)*10000 -> 141.44689 | F54: =(F16-$B16)*10000 -> 53.640967 | I54: =A16 -> 0.1 | J54: =Engine!$Q$31 -> 1731.4752 | K54: =Engine!$R$31 -> 533.26558 | L54: =J54+K54 -> 2264.7408 | M54: =IF(L54=0,0,J54/L54) -> 0.76453571 | N54: =J16 -> -5465.5015
A55: =A17 -> 0.11 | B55: =B17 -> 0.073382315 | C55: =(C17-$B17)*10000 -> 22.673185 | D55: =(D17-$B17)*10000 -> 135.50466 | E55: =(E17-$B17)*10000 -> 66.176848 | F55: =(F17-$B17)*10000 -> 56.423259 | I55: =A17 -> 0.11 | J55: =Engine!$Q$32 -> 1731.4752 | K55: =Engine!$R$32 -> 625.40993 | L55: =J55+K55 -> 2356.8851 | M55: =IF(L55=0,0,J55/L55) -> 0.73464556 | N55: =J17 -> -4982.9351
A56: =A18 -> 0.12 | B56: =B18 -> 0.082579186 | C56: =(C18-$B18)*10000 -> 22.440149 | D56: =(D18-$B18)*10000 -> 127.38184 | E56: =(E18-$B18)*10000 -> 23.287221 | F56: =(F18-$B18)*10000 -> 59.088525 | I56: =A18 -> 0.12 | J56: =Engine!$Q$33 -> 1731.4752 | K56: =Engine!$R$33 -> 728.74287 | L56: =J56+K56 -> 2460.218 | M56: =IF(L56=0,0,J56/L56) -> 0.70378932 | N56: =J18 -> -4480.4887
A57: =A19 -> 0.13 | B57: =B19 -> 0.091818991 | C57: =(C19-$B19)*10000 -> 22.321339 | D57: =(D19-$B19)*10000 -> 119.9786 | E57: =(E19-$B19)*10000 -> 24.047724 | F57: =(F19-$B19)*10000 -> 61.688585 | I57: =A19 -> 0.13 | J57: =Engine!$Q$34 -> 1731.4752 | K57: =Engine!$R$34 -> 839.08159 | L57: =J57+K57 -> 2570.5568 | M57: =IF(L57=0,0,J57/L57) -> 0.67357983 | N57: =J19 -> -3952.3666
A58: =A20 -> 0.14 | B58: =B20 -> 0.10110885 | C58: =(C20-$B20)*10000 -> 22.207502 | D58: =(D20-$B20)*10000 -> 113.15386 | E58: =(E20-$B20)*10000 -> 24.897905 | F58: =(F20-$B20)*10000 -> 64.124499 | I58: =A20 -> 0.14 | J58: =Engine!$Q$35 -> 1731.4752 | K58: =Engine!$R$35 -> 955.70301 | L58: =J58+K58 -> 2687.1782 | M58: =IF(L58=0,0,J58/L58) -> 0.64434699 | N58: =J20 -> -3396.155
A59: =A21 -> 0.15 | B59: =B21 -> 0.1104452 | C59: =(C21-$B21)*10000 -> 21.943758 | D59: =(D21-$B21)*10000 -> 106.87579 | E59: =(E21-$B21)*10000 -> 25.82473 | F59: =(F21-$B21)*10000 -> 66.289321 | I59: =A21 -> 0.15 | J59: =Engine!$Q$36 -> 1731.4752 | K59: =Engine!$R$36 -> 1078.9434 | L59: =J59+K59 -> 2810.4186 | M59: =IF(L59=0,0,J59/L59) -> 0.61609156 | N59: =J21 -> -2810.4186
A60: =A22 -> 0.16 | B60: =B22 -> 0.1197434 | C60: =(C22-$B22)*10000 -> 21.770523 | D60: =(D22-$B22)*10000 -> 101.92548 | E60: =(E22-$B22)*10000 -> 27.628993 | F60: =(F22-$B22)*10000 -> 68.575143 | I60: =A22 -> 0.16 | J60: =Engine!$Q$37 -> 1731.4752 | K60: =Engine!$R$37 -> 1215.8532 | L60: =J60+K60 -> 2947.3284 | M60: =IF(L60=0,0,J60/L60) -> 0.58747277 | N60: =J22 -> -2200.3512
A61: =A23 -> 0.17 | B61: =B23 -> 0.12906936 | C61: =(C23-$B23)*10000 -> 21.656698 | D61: =(D23-$B23)*10000 -> 97.58127 | E61: =(E23-$B23)*10000 -> 29.609346 | F61: =(F23-$B23)*10000 -> 70.799565 | I61: =A23 -> 0.17 | J61: =Engine!$Q$38 -> 1731.4752 | K61: =Engine!$R$38 -> 1360.8195 | L61: =J61+K61 -> 3092.2947 | M61: =IF(L61=0,0,J61/L61) -> 0.55993213 | N61: =J23 -> -1558.3954
A62: =A24 -> 0.18 | B62: =B24 -> 0.13842629 | C62: =(C24-$B24)*10000 -> 21.550175 | D62: =(D24-$B24)*10000 -> 93.751547 | E62: =(E24-$B24)*10000 -> 31.694801 | F62: =(F24-$B24)*10000 -> 72.916929 | I62: =A24 -> 0.18 | J62: =Engine!$Q$39 -> 1731.4752 | K62: =Engine!$R$39 -> 1513.8009 | L62: =J62+K62 -> 3245.2761 | M62: =IF(L62=0,0,J62/L62) -> 0.5335371 | N62: =J24 -> -882.47286
A63: =A25 -> 0.19 | B63: =B25 -> 0.14781229 | C63: =(C25-$B25)*10000 -> 21.45073 | D63: =(D25-$B25)*10000 -> 90.398287 | E63: =(E25-$B25)*10000 -> 33.868015 | F63: =(F25-$B25)*10000 -> 74.93316 | I63: =A25 -> 0.19 | J63: =Engine!$Q$40 -> 1731.4752 | K63: =Engine!$R$40 -> 1675.2136 | L63: =J63+K63 -> 3406.6887 | M63: =IF(L63=0,0,J63/L63) -> 0.50825752 | N63: =J25 -> -170.86748
A64: =A26 -> 0.2 | B64: =B26 -> 0.15722559 | C64: =(C26-$B26)*10000 -> 21.358143 | D64: =(D26-$B26)*10000 -> 86.926301 | E64: =(E26-$B26)*10000 -> 30.666435 | F64: =(F26-$B26)*10000 -> 76.853883 | I64: =A26 -> 0.2 | J64: =Engine!$Q$41 -> 1731.4752 | K64: =Engine!$R$41 -> 1845.4937 | L64: =J64+K64 -> 3576.9689 | M64: =IF(L64=0,0,J64/L64) -> 0.48406213 | N64: =J26 -> 578.21714
A65: =A27 -> 0.21 | B65: =B27 -> 0.16666452 | C65: =(C27-$B27)*10000 -> 21.272191 | D65: =(D27-$B27)*10000 -> 83.597169 | E65: =(E27-$B27)*10000 -> 27.570915 | F65: =(F27-$B27)*10000 -> 78.684441 | I65: =A27 -> 0.21 | J65: =Engine!$Q$42 -> 1731.4752 | K65: =Engine!$R$42 -> 2025.0981 | L65: =J65+K65 -> 3756.5733 | M65: =IF(L65=0,0,J65/L65) -> 0.46091878 | N65: =J27 -> 1366.6608
A66: =A28 -> 0.22 | B66: =B28 -> 0.17609589 | C66: =(C28-$B28)*10000 -> 20.94921 | D66: =(D28-$B28)*10000 -> 80.873413 | E66: =(E28-$B28)*10000 -> 28.976292 | F66: =(F28-$B28)*10000 -> 80.327011 | I66: =A28 -> 0.22 | J66: =Engine!$Q$43 -> 1731.4752 | K66: =Engine!$R$43 -> 2216.9074 | L66: =J66+K66 -> 3948.3826 | M66: =IF(L66=0,0,J66/L66) -> 0.43852771 | N66: =J28 -> 2194.0279
A67: =A29 -> 0.23 | B67: =B29 -> 0.18548467 | C67: =(C29-$B29)*10000 -> 20.864883 | D67: =(D29-$B29)*10000 -> 79.07158 | E67: =(E29-$B29)*10000 -> 31.063598 | F67: =(F29-$B29)*10000 -> 82.228507 | I67: =A29 -> 0.23 | J67: =Engine!$Q$44 -> 1731.4752 | K67: =Engine!$R$44 -> 2423.908 | L67: =J67+K67 -> 4155.3832 | M67: =IF(L67=0,0,J67/L67) -> 0.41668243 | N67: =J29 -> 3059.8898
A68: =A30 -> 0.24 | B68: =B30 -> 0.19489071 | C68: =(C30-$B30)*10000 -> 20.787596 | D68: =(D30-$B30)*10000 -> 77.016381 | E68: =(E30-$B30)*10000 -> 28.690428 | F68: =(F30-$B30)*10000 -> 84.066756 | I68: =A30 -> 0.24 | J68: =Engine!$Q$45 -> 1731.4752 | K68: =Engine!$R$45 -> 2641.9757 | L68: =J68+K68 -> 4373.4509 | M68: =IF(L68=0,0,J68/L68) -> 0.39590594 | N68: =J30 -> 3971.0462
A69: =A31 -> 0.25 | B69: =B31 -> 0.20431317 | C69: =(C31-$B31)*10000 -> 20.717042 | D69: =(D31-$B31)*10000 -> 74.884134 | E69: =(E31-$B31)*10000 -> 24.323523 | F69: =(F31-$B31)*10000 -> 85.844736 | I69: =A31 -> 0.25 | J69: =Engine!$Q$46 -> 1731.4752 | K69: =Engine!$R$46 -> 2871.6653 | L69: =J69+K69 -> 4603.1405 | M69: =IF(L69=0,0,J69/L69) -> 0.37615084 | N69: =J31 -> 4929.74
A70: =A32 -> 0.26 | B70: =B32 -> 0.21375128 | C70: =(C32-$B32)*10000 -> 20.652925 | D70: =(D32-$B32)*10000 -> 72.94081 | E70: =(E32-$B32)*10000 -> 25.339438 | F70: =(F32-$B32)*10000 -> 87.565281 | I70: =A32 -> 0.26 | J70: =Engine!$Q$47 -> 1731.4752 | K70: =Engine!$R$47 -> 3113.5572 | L70: =J70+K70 -> 4845.0323 | M70: =IF(L70=0,0,J70/L70) -> 0.35737123 | N70: =J32 -> 5938.316
A71: =A33 -> 0.27 | B71: =B33 -> 0.22320427 | C71: =(C33-$B33)*10000 -> 20.594966 | D71: =(D33-$B33)*10000 -> 71.174813 | E71: =(E33-$B33)*10000 -> 26.386778 | F71: =(F33-$B33)*10000 -> 89.231085 | I71: =A33 -> 0.27 | J71: =Engine!$Q$48 -> 1731.4752 | K71: =Engine!$R$48 -> 3368.258 | L71: =J71+K71 -> 5099.7331 | M71: =IF(L71=0,0,J71/L71) -> 0.3395227 | N71: =J33 -> 6999.2249
A72: =A34 -> 0.28 | B72: =B34 -> 0.23267145 | C72: =(C34-$B34)*10000 -> 20.542895 | D72: =(D34-$B34)*10000 -> 69.575182 | E72: =(E34-$B34)*10000 -> 27.461607 | F72: =(F34-$B34)*10000 -> 90.844714 | I72: =A34 -> 0.28 | J72: =Engine!$Q$49 -> 1731.4752 | K72: =Engine!$R$49 -> 3636.4019 | L72: =J72+K72 -> 5367.877 | M72: =IF(L72=0,0,J72/L72) -> 0.32256238 | N72: =J34 -> 8115.0278
A73: =A35 -> 0.29 | B73: =B35 -> 0.24215213 | C73: =(C35-$B35)*10000 -> 20.496457 | D73: =(D35-$B35)*10000 -> 68.131571 | E73: =(E35-$B35)*10000 -> 28.560303 | F73: =(F35-$B35)*10000 -> 92.408608 | I73: =A35 -> 0.29 | J73: =Engine!$Q$50 -> 1731.4752 | K73: =Engine!$R$50 -> 3918.6516 | L73: =J73+K73 -> 5650.1268 | M73: =IF(L73=0,0,J73/L73) -> 0.30644891 | N73: =J35 -> 9288.4004
A74: =A36 -> 0.3 | B74: =B36 -> 0.25164567 | C74: =(C36-$B36)*10000 -> 20.455408 | D74: =(D36-$B36)*10000 -> 66.834214 | E74: =(E36-$B36)*10000 -> 29.679536 | F74: =(F36-$B36)*10000 -> 93.92509 | I74: =A36 -> 0.3 | J74: =Engine!$Q$51 -> 1731.4752 | K74: =Engine!$R$51 -> 4215.6996 | L74: =J74+K74 -> 5947.1748 | M74: =IF(L74=0,0,J74/L74) -> 0.29114247 | N74: =J36 -> 10522.138
A76: Reading Table 3: the fee cut is a roughly constant gain; a hurdle pays off most when returns are weak (GP earns no carry below 8%); a carry cut pays off most when returns are strong.

Sheet Engine
A1: ENGINE — the same fund model laid out one scenario per row (feeds Summary, Sensitivity, Q3–Q6 analysis sheets)
A2: Each row repeats the template logic year by year (columns AT onward). Main scenarios M1–M5 must reconcile to the template-style sheets (see Summary row 36). Do not edit — change Inputs instead.
A4: Scenario | D4: Terms and assumptions | K4: Outputs ($ millions) | W4: LP net cash flows, t = 0 … 10 | AH4: GP cash flows (fees + carry), t = 0 … 10 | AT4: Year 1 | BJ4: Year 2 | BZ4: Year 3 | CP4: Year 4 | DF4: Year 5 | DV4: Year 6 | EL4: Year 7 | FB4: Year 8 | FR4: Year 9 | GH4: Year 10
A5: ID | B5: Scenario | C5: Grid step | D5: Committed | E5: Mgmt fee | F5: Carry | G5: Hurdle | H5: Catch-up | I5: Asset growth | J5: Discount rate | K5: LP IRR | L5: LP NPV | M5: LP distributions | N5: LP TVPI | O5: GP fees (nominal) | P5: GP carry (nominal) | Q5: PV fees | R5: PV carry | S5: PV GP total | T5: Fee share of GP PV | U5: Check (0 = OK) | W5: t=0 | X5: t=1 | Y5: t=2 | Z5: t=3 | AA5: t=4 | AB5: t=5 | AC5: t=6 | AD5: t=7 | AE5: t=8 | AF5: t=9 | AG5: t=10 | AH5: t=0 | AI5: t=1 | AJ5: t=2 | AK5: t=3 | AL5: t=4 | AM5: t=5 | AN5: t=6 | AO5: t=7 | AP5: t=8 | AQ5: t=9 | AR5: t=10 | AT5: Invested capital | AU5: NAV before dist. | AV5: Distribution | AW5: NAV after dist. | AX5: Unreturned capital (open) | AY5: Return of capital | AZ5: Unreturned capital (close) | BA5: Pref. due | BB5: Pref. paid | BC5: Unpaid pref. (close) | BD5: GP catch-up | BE5: Profit pool split | BF5: LP distribution | BG5: GP carry | BH5: Cum. LP profit | BI5: Cum. GP carry | BJ5: Invested capital | BK5: NAV before dist. | BL5: Distribution | BM5: NAV after dist. | BN5: Unreturned capital (open) | BO5: Return of capital | BP5: Unreturned capital (close) | BQ5: Pref. due | BR5: Pref. paid | BS5: Unpaid pref. (close) | BT5: GP catch-up | BU5: Profit pool split | BV5: LP distribution | BW5: GP carry | BX5: Cum. LP profit | BY5: Cum. GP carry | BZ5: Invested capital | CA5: NAV before dist. | CB5: Distribution | CC5: NAV after dist. | CD5: Unreturned capital (open) | CE5: Return of capital | CF5: Unreturned capital (close) | CG5: Pref. due | CH5: Pref. paid | CI5: Unpaid pref. (close) | CJ5: GP catch-up | CK5: Profit pool split | CL5: LP distribution | CM5: GP carry | CN5: Cum. LP profit | CO5: Cum. GP carry | CP5: Invested capital | CQ5: NAV before dist. | CR5: Distribution | CS5: NAV after dist. | CT5: Unreturned capital (open) | CU5: Return of capital | CV5: Unreturned capital (close) | CW5: Pref. due | CX5: Pref. paid | CY5: Unpaid pref. (close) | CZ5: GP catch-up | DA5: Profit pool split | DB5: LP distribution | DC5: GP carry | DD5: Cum. LP profit | DE5: Cum. GP carry | DF5: Invested capital | DG5: NAV before dist. | DH5: Distribution | DI5: NAV after dist. | DJ5: Unreturned capital (open) | DK5: Return of capital | DL5: Unreturned capital (close) | DM5: Pref. due | DN5: Pref. paid | DO5: Unpaid pref. (close) | DP5: GP catch-up | DQ5: Profit pool split | DR5: LP distribution | DS5: GP carry | DT5: Cum. LP profit | DU5: Cum. GP carry | DV5: Invested capital | DW5: NAV before dist. | DX5: Distribution | DY5: NAV after dist. | DZ5: Unreturned capital (open) | EA5: Return of capital | EB5: Unreturned capital (close) | EC5: Pref. due | ED5: Pref. paid | EE5: Unpaid pref. (close) | EF5: GP catch-up | EG5: Profit pool split | EH5: LP distribution | EI5: GP carry | EJ5: Cum. LP profit | EK5: Cum. GP carry | EL5: Invested capital | EM5: NAV before dist. | EN5: Distribution | EO5: NAV after dist. | EP5: Unreturned capital (open) | EQ5: Return of capital | ER5: Unreturned capital (close) | ES5: Pref. due | ET5: Pref. paid | EU5: Unpaid pref. (close) | EV5: GP catch-up | EW5: Profit pool split | EX5: LP distribution | EY5: GP carry | EZ5: Cum. LP profit | FA5: Cum. GP carry | FB5: Invested capital | FC5: NAV before dist. | FD5: Distribution | FE5: NAV after dist. | FF5: Unreturned capital (open) | FG5: Return of capital | FH5: Unreturned capital (close) | FI5: Pref. due | FJ5: Pref. paid | FK5: Unpaid pref. (close) | FL5: GP catch-up | FM5: Profit pool split | FN5: LP distribution | FO5: GP carry | FP5: Cum. LP profit | FQ5: Cum. GP carry | FR5: Invested capital | FS5: NAV before dist. | FT5: Distribution | FU5: NAV after dist. | FV5: Unreturned capital (open) | FW5: Return of capital | FX5: Unreturned capital (close) | FY5: Pref. due | FZ5: Pref. paid | GA5: Unpaid pref. (close) | GB5: GP catch-up | GC5: Profit pool split | GD5: LP distribution | GE5: GP carry | GF5: Cum. LP profit | GG5: Cum. GP carry | GH5: Invested capital | GI5: NAV before dist. | GJ5: Distribution | GK5: NAV after dist. | GL5: Unreturned capital (open) | GM5: Return of capital | GN5: Unreturned capital (close) | GO5: Pref. due | GP5: Pref. paid | GQ5: Unpaid pref. (close) | GR5: GP catch-up | GS5: Profit pool split | GT5: LP distribution | GU5: GP carry | GV5: Cum. LP profit | GW5: Cum. GP carry
A7: M1 | B7: Current terms (1.50% fee, 20% carry, no hurdle) | D7: =Inputs!$C$6 -> 20000 | E7: =Inputs!$C$18 -> 0.015 | F7: =Inputs!$C$20 -> 0.2 | G7: 0 | H7: 0 | I7: =Inputs!$C$8 -> 0.2 | J7: =Inputs!$C$9 -> 0.15 | K7: =IRR(W7:AG7,0.1) -> 0.15722559 | L7: =W7+NPV($J7,X7:AG7) -> 578.21714 | M7: =SUM(BF7,BV7,CL7,DB7,DR7,EH7,EX7,FN7,GD7,GT7) -> 48070.521 | N7: =IF($D7*SUM(Inputs!$C$13:$L$13)=0,0,M7/($D7*SUM(Inputs!$C$13:$L$13))) -> 2.403526 | O7: =$D7*$E7*COLUMNS(Inputs!$C$13:$L$13) -> 3000 | P7: =SUM(BG7,BW7,CM7,DC7,DS7,EI7,EY7,FO7,GE7,GU7) -> 7017.6302 | Q7: =PV($J7,COLUMNS(Inputs!$C$13:$L$13),-$D7*$E7,0,1) -> 1731.4752 | R7: =NPV($J7,BG7,BW7,CM7,DC7,DS7,EI7,EY7,FO7,GE7,GU7) -> 1845.4937 | S7: =Q7+R7 -> 3576.9689 | T7: =IF(S7=0,0,Q7/S7) -> 0.48406213 | U7: =ROUND(ABS(GK7)+ABS(SUM(AV7,BL7,CB7,CR7,DH7,DX7,EN7,FD7,FT7,GJ7)-M7-P7)+ABS(S7-(AH7+NPV($J7,AI7:AR7))),6) -> 0 | W7: =-$D7*Inputs!$C$13 -> -4000 | X7: =BF7-$D7*Inputs!$D$13 -> -4000 | Y7: =BV7-$D7*Inputs!$E$13 -> -4000 | Z7: =CL7-$D7*Inputs!$F$13 -> -4000 | AA7: =DB7-$D7*Inputs!$G$13 -> -4000 | AB7: =DR7-$D7*Inputs!$H$13 -> 6608.1408 | AC7: =EH7-$D7*Inputs!$I$13 -> 6271.8152 | AD7: =EX7-$D7*Inputs!$J$13 -> 5948.9426 | AE7: =FN7-$D7*Inputs!$K$13 -> 4745.4082 | AF7: =GD7-$D7*Inputs!$L$13 -> 4273.1404 | AG7: =GT7 -> 20223.074 | AH7: =$D7*$E7 -> 300 | AI7: =BG7+$D7*$E7 -> 300 | AJ7: =BW7+$D7*$E7 -> 300 | AK7: =CM7+$D7*$E7 -> 300 | AL7: =DC7+$D7*$E7 -> 300 | AM7: =DS7+$D7*$E7 -> 300 | AN7: =EI7+$D7*$E7 -> 300 | AO7: =EY7+$D7*$E7 -> 300 | AP7: =FO7+$D7*$E7 -> 1193.5767 | AQ7: =GE7+$D7*$E7 -> 1368.2851 | AR7: =GU7 -> 5055.7684 | AT7: =$D7*Inputs!$C$13-$D7*$E7 -> 3700 | AU7: =AT7*(1+$I7) -> 4440 | AV7: =AU7*Inputs!$C$14 -> 0 | AW7: =AU7-AV7 -> 4440 | AX7: =$D7*Inputs!$C$13 -> 4000 | AY7: =MIN(AV7,AX7) -> 0 | AZ7: =AX7-AY7 -> 4000 | BA7: =$G7*AX7 -> 0 | BB7: =MIN(AV7-AY7,BA7) -> 0 | BC7: =BA7-BB7 -> 0 | BD7: =IF($H7=1,MIN(AV7-AY7-BB7,MAX(0,$F7/(1-$F7)*BB7)),0) -> 0 | BE7: =AV7-AY7-BB7-BD7 -> 0 | BF7: =AY7+BB7+(1-$F7)*BE7 -> 0 | BG7: =BD7+$F7*BE7 -> 0 | BH7: =BB7+(1-$F7)*BE7 -> 0 | BI7: =BG7 -> 0 | BJ7: =AW7+$D7*Inputs!$D$13-$D7*$E7 -> 8140 | BK7: =BJ7*(1+$I7) -> 9768 | BL7: =BK7*Inputs!$D$14 -> 0 | BM7: =BK7-BL7 -> 9768 | BN7: =AZ7+$D7*Inputs!$D$13 -> 8000 | BO7: =MIN(BL7,BN7) -> 0 | BP7: =BN7-BO7 -> 8000 | BQ7: =BC7+$G7*(BN7+BC7) -> 0 | BR7: =MIN(BL7-BO7,BQ7) -> 0 | BS7: =BQ7-BR7 -> 0 | BT7: =IF($H7=1,MIN(BL7-BO7-BR7,MAX(0,$F7/(1-$F7)*(BH7+BR7)-BI7)),0) -> 0 | BU7: =BL7-BO7-BR7-BT7 -> 0 | BV7: =BO7+BR7+(1-$F7)*BU7 -> 0 | BW7: =BT7+$F7*BU7 -> 0 | BX7: =BH7+BR7+(1-$F7)*BU7 -> 0 | BY7: =BI7+BW7 -> 0 | BZ7: =BM7+$D7*Inputs!$E$13-$D7*$E7 -> 13468 | CA7: =BZ7*(1+$I7) -> 16161.6 | CB7: =CA7*Inputs!$E$14 -> 0 | CC7: =CA7-CB7 -> 16161.6 | CD7: =BP7+$D7*Inputs!$E$13 -> 12000 | CE7: =MIN(CB7,CD7) -> 0 | CF7: =CD7-CE7 -> 12000 | CG7: =BS7+$G7*(CD7+BS7) -> 0 | CH7: =MIN(CB7-CE7,CG7) -> 0 | CI7: =CG7-CH7 -> 0 | CJ7: =IF($H7=1,MIN(CB7-CE7-CH7,MAX(0,$F7/(1-$F7)*(BX7+CH7)-BY7)),0) -> 0 | CK7: =CB7-CE7-CH7-CJ7 -> 0 | CL7: =CE7+CH7+(1-$F7)*CK7 -> 0 | CM7: =CJ7+$F7*CK7 -> 0 | CN7: =BX7+CH7+(1-$F7)*CK7 -> 0 | CO7: =BY7+CM7 -> 0 | CP7: =CC7+$D7*Inputs!$F$13-$D7*$E7 -> 19861.6 | CQ7: =CP7*(1+$I7) -> 23833.92 | CR7: =CQ7*Inputs!$F$14 -> 0 | CS7: =CQ7-CR7 -> 23833.92 | CT7: =CF7+$D7*Inputs!$F$13 -> 16000 | CU7: =MIN(CR7,CT7) -> 0 | CV7: =CT7-CU7 -> 16000 | CW7: =CI7+$G7*(CT7+CI7) -> 0 | CX7: =MIN(CR7-CU7,CW7) -> 0 | CY7: =CW7-CX7 -> 0 | CZ7: =IF($H7=1,MIN(CR7-CU7-CX7,MAX(0,$F7/(1-$F7)*(CN7+CX7)-CO7)),0) -> 0 | DA7: =CR7-CU7-CX7-CZ7 -> 0 | DB7: =CU7+CX7+(1-$F7)*DA7 -> 0 | DC7: =CZ7+$F7*DA7 -> 0 | DD7: =CN7+CX7+(1-$F7)*DA7 -> 0 | DE7: =CO7+DC7 -> 0 | DF7: =CS7+$D7*Inputs!$G$13-$D7*$E7 -> 27533.92 | DG7: =DF7*(1+$I7) -> 33040.704 | DH7: =DG7*Inputs!$G$14 -> 6608.1408 | DI7: =DG7-DH7 -> 26432.563 | DJ7: =CV7+$D7*Inputs!$G$13 -> 20000 | DK7: =MIN(DH7,DJ7) -> 6608.1408 | DL7: =DJ7-DK7 -> 13391.859 | DM7: =CY7+$G7*(DJ7+CY7) -> 0 | DN7: =MIN(DH7-DK7,DM7) -> 0 | DO7: =DM7-DN7 -> 0 | DP7: =IF($H7=1,MIN(DH7-DK7-DN7,MAX(0,$F7/(1-$F7)*(DD7+DN7)-DE7)),0) -> 0 | DQ7: =DH7-DK7-DN7-DP7 -> 0 | DR7: =DK7+DN7+(1-$F7)*DQ7 -> 6608.1408 | DS7: =DP7+$F7*DQ7 -> 0 | DT7: =DD7+DN7+(1-$F7)*DQ7 -> 0 | DU7: =DE7+DS7 -> 0 | DV7: =DI7+$D7*Inputs!$H$13-$D7*$E7 -> 26132.563 | DW7: =DV7*(1+$I7) -> 31359.076 | DX7: =DW7*Inputs!$H$14 -> 6271.8152 | DY7: =DW7-DX7 -> 25087.261 | DZ7: =DL7+$D7*Inputs!$H$13 -> 13391.859 | EA7: =MIN(DX7,DZ7) -> 6271.8152 | EB7: =DZ7-EA7 -> 7120.044 | EC7: =DO7+$G7*(DZ7+DO7) -> 0 | ED7: =MIN(DX7-EA7,EC7) -> 0 | EE7: =EC7-ED7 -> 0 | EF7: =IF($H7=1,MIN(DX7-EA7-ED7,MAX(0,$F7/(1-$F7)*(DT7+ED7)-DU7)),0) -> 0 | EG7: =DX7-EA7-ED7-EF7 -> 0 | EH7: =EA7+ED7+(1-$F7)*EG7 -> 6271.8152 | EI7: =EF7+$F7*EG7 -> 0 | EJ7: =DT7+ED7+(1-$F7)*EG7 -> 0 | EK7: =DU7+EI7 -> 0 | EL7: =DY7+$D7*Inputs!$I$13-$D7*$E7 -> 24787.261 | EM7: =EL7*(1+$I7) -> 29744.713 | EN7: =EM7*Inputs!$I$14 -> 5948.9426 | EO7: =EM7-EN7 -> 23795.77 | EP7: =EB7+$D7*Inputs!$I$13 -> 7120.044 | EQ7: =MIN(EN7,EP7) -> 5948.9426 | ER7: =EP7-EQ7 -> 1171.1015 | ES7: =EE7+$G7*(EP7+EE7) -> 0 | ET7: =MIN(EN7-EQ7,ES7) -> 0 | EU7: =ES7-ET7 -> 0 | EV7: =IF($H7=1,MIN(EN7-EQ7-ET7,MAX(0,$F7/(1-$F7)*(EJ7+ET7)-EK7)),0) -> 0 | EW7: =EN7-EQ7-ET7-EV7 -> 0 | EX7: =EQ7+ET7+(1-$F7)*EW7 -> 5948.9426 | EY7: =EV7+$F7*EW7 -> 0 | EZ7: =EJ7+ET7+(1-$F7)*EW7 -> 0 | FA7: =EK7+EY7 -> 0 | FB7: =EO7+$D7*Inputs!$J$13-$D7*$E7 -> 23495.77 | FC7: =FB7*(1+$I7) -> 28194.924 | FD7: =FC7*Inputs!$J$14 -> 5638.9849 | FE7: =FC7-FD7 -> 22555.939 | FF7: =ER7+$D7*Inputs!$J$13 -> 1171.1015 | FG7: =MIN(FD7,FF7) -> 1171.1015 | FH7: =FF7-FG7 -> 0 | FI7: =EU7+$G7*(FF7+EU7) -> 0 | FJ7: =MIN(FD7-FG7,FI7) -> 0 | FK7: =FI7-FJ7 -> 0 | FL7: =IF($H7=1,MIN(FD7-FG7-FJ7,MAX(0,$F7/(1-$F7)*(EZ7+FJ7)-FA7)),0) -> 0 | FM7: =FD7-FG7-FJ7-FL7 -> 4467.8834 | FN7: =FG7+FJ7+(1-$F7)*FM7 -> 4745.4082 | FO7: =FL7+$F7*FM7 -> 893.57668 | FP7: =EZ7+FJ7+(1-$F7)*FM7 -> 3574.3067 | FQ7: =FA7+FO7 -> 893.57668 | FR7: =FE7+$D7*Inputs!$K$13-$D7*$E7 -> 22255.939 | FS7: =FR7*(1+$I7) -> 26707.127 | FT7: =FS7*Inputs!$K$14 -> 5341.4255 | FU7: =FS7-FT7 -> 21365.702 | FV7: =FH7+$D7*Inputs!$K$13 -> 0 | FW7: =MIN(FT7,FV7) -> 0 | FX7: =FV7-FW7 -> 0 | FY7: =FK7+$G7*(FV7+FK7) -> 0 | FZ7: =MIN(FT7-FW7,FY7) -> 0 | GA7: =FY7-FZ7 -> 0 | GB7: =IF($H7=1,MIN(FT7-FW7-FZ7,MAX(0,$F7/(1-$F7)*(FP7+FZ7)-FQ7)),0) -> 0 | GC7: =FT7-FW7-FZ7-GB7 -> 5341.4255 | GD7: =FW7+FZ7+(1-$F7)*GC7 -> 4273.1404 | GE7: =GB7+$F7*GC7 -> 1068.2851 | GF7: =FP7+FZ7+(1-$F7)*GC7 -> 7847.4471 | GG7: =FQ7+GE7 -> 1961.8618 | GH7: =FU7+$D7*Inputs!$L$13-$D7*$E7 -> 21065.702 | GI7: =GH7*(1+$I7) -> 25278.842 | GJ7: =GI7*Inputs!$L$14 -> 25278.842 | GK7: =GI7-GJ7 -> 0 | GL7: =FX7+$D7*Inputs!$L$13 -> 0 | GM7: =MIN(GJ7,GL7) -> 0 | GN7: =GL7-GM7 -> 0 | GO7: =GA7+$G7*(GL7+GA7) -> 0 | GP7: =MIN(GJ7-GM7,GO7) -> 0 | GQ7: =GO7-GP7 -> 0 | GR7: =IF($H7=1,MIN(GJ7-GM7-GP7,MAX(0,$F7/(1-$F7)*(GF7+GP7)-GG7)),0) -> 0 | GS7: =GJ7-GM7-GP7-GR7 -> 25278.842 | GT7: =GM7+GP7+(1-$F7)*GS7 -> 20223.074 | GU7: =GR7+$F7*GS7 -> 5055.7684 | GV7: =GF7+GP7+(1-$F7)*GS7 -> 28070.521 | GW7: =GG7+GU7 -> 7017.6302
A8: M2 | B8: TPG offer (1.35% fee, 20% carry, no hurdle) | D8: =Inputs!$C$6 -> 20000 | E8: =Inputs!$C$19 -> 0.0135 | F8: =Inputs!$C$20 -> 0.2 | G8: 0 | H8: 0 | I8: =Inputs!$C$8 -> 0.2 | J8: =Inputs!$C$9 -> 0.15 | K8: =IRR(W8:AG8,0.1) -> 0.15936141 | L8: =W8+NPV($J8,X8:AG8) -> 752.97923 | M8: =SUM(BF8,BV8,CL8,DB8,DR8,EH8,EX8,FN8,GD8,GT8) -> 48631.388 | N8: =IF($D8*SUM(Inputs!$C$13:$L$13)=0,0,M8/($D8*SUM(Inputs!$C$13:$L$13))) -> 2.4315694 | O8: =$D8*$E8*COLUMNS(Inputs!$C$13:$L$13) -> 2700 | P8: =SUM(BG8,BW8,CM8,DC8,DS8,EI8,EY8,FO8,GE8,GU8) -> 7157.847 | Q8: =PV($J8,COLUMNS(Inputs!$C$13:$L$13),-$D8*$E8,0,1) -> 1558.3277 | R8: =NPV($J8,BG8,BW8,CM8,DC8,DS8,EI8,EY8,FO8,GE8,GU8) -> 1884.5797 | S8: =Q8+R8 -> 3442.9073 | T8: =IF(S8=0,0,Q8/S8) -> 0.45261969 | U8: =ROUND(ABS(GK8)+ABS(SUM(AV8,BL8,CB8,CR8,DH8,DX8,EN8,FD8,FT8,GJ8)-M8-P8)+ABS(S8-(AH8+NPV($J8,AI8:AR8))),6) -> 0 | W8: =-$D8*Inputs!$C$13 -> -4000 | X8: =BF8-$D8*Inputs!$D$13 -> -4000 | Y8: =BV8-$D8*Inputs!$E$13 -> -4000 | Z8: =CL8-$D8*Inputs!$F$13 -> -4000 | AA8: =DB8-$D8*Inputs!$G$13 -> -4000 | AB8: =DR8-$D8*Inputs!$H$13 -> 6661.7203 | AC8: =EH8-$D8*Inputs!$I$13 -> 6330.4515 | AD8: =EX8-$D8*Inputs!$J$13 -> 6012.4334 | AE8: =FN8-$D8*Inputs!$K$13 -> 4764.7878 | AF8: =GD8-$D8*Inputs!$L$13 -> 4331.2405 | AG8: =GT8 -> 20530.755 | AH8: =$D8*$E8 -> 270 | AI8: =BG8+$D8*$E8 -> 270 | AJ8: =BW8+$D8*$E8 -> 270 | AK8: =CM8+$D8*$E8 -> 270 | AL8: =DC8+$D8*$E8 -> 270 | AM8: =DS8+$D8*$E8 -> 270 | AN8: =EI8+$D8*$E8 -> 270 | AO8: =EY8+$D8*$E8 -> 270 | AP8: =FO8+$D8*$E8 -> 1212.3483 | AQ8: =GE8+$D8*$E8 -> 1352.8101 | AR8: =GU8 -> 5132.6886 | AT8: =$D8*Inputs!$C$13-$D8*$E8 -> 3730 | AU8: =AT8*(1+$I8) -> 4476 | AV8: =AU8*Inputs!$C$14 -> 0 | AW8: =AU8-AV8 -> 4476 | AX8: =$D8*Inputs!$C$13 -> 4000 | AY8: =MIN(AV8,AX8) -> 0 | AZ8: =AX8-AY8 -> 4000 | BA8: =$G8*AX8 -> 0 | BB8: =MIN(AV8-AY8,BA8) -> 0 | BC8: =BA8-BB8 -> 0 | BD8: =IF($H8=1,MIN(AV8-AY8-BB8,MAX(0,$F8/(1-$F8)*BB8)),0) -> 0 | BE8: =AV8-AY8-BB8-BD8 -> 0 | BF8: =AY8+BB8+(1-$F8)*BE8 -> 0 | BG8: =BD8+$F8*BE8 -> 0 | BH8: =BB8+(1-$F8)*BE8 -> 0 | BI8: =BG8 -> 0 | BJ8: =AW8+$D8*Inputs!$D$13-$D8*$E8 -> 8206 | BK8: =BJ8*(1+$I8) -> 9847.2 | BL8: =BK8*Inputs!$D$14 -> 0 | BM8: =BK8-BL8 -> 9847.2 | BN8: =AZ8+$D8*Inputs!$D$13 -> 8000 | BO8: =MIN(BL8,BN8) -> 0 | BP8: =BN8-BO8 -> 8000 | BQ8: =BC8+$G8*(BN8+BC8) -> 0 | BR8: =MIN(BL8-BO8,BQ8) -> 0 | BS8: =BQ8-BR8 -> 0 | BT8: =IF($H8=1,MIN(BL8-BO8-BR8,MAX(0,$F8/(1-$F8)*(BH8+BR8)-BI8)),0) -> 0 | BU8: =BL8-BO8-BR8-BT8 -> 0 | BV8: =BO8+BR8+(1-$F8)*BU8 -> 0 | BW8: =BT8+$F8*BU8 -> 0 | BX8: =BH8+BR8+(1-$F8)*BU8 -> 0 | BY8: =BI8+BW8 -> 0 | BZ8: =BM8+$D8*Inputs!$E$13-$D8*$E8 -> 13577.2 | CA8: =BZ8*(1+$I8) -> 16292.64 | CB8: =CA8*Inputs!$E$14 -> 0 | CC8: =CA8-CB8 -> 16292.64 | CD8: =BP8+$D8*Inputs!$E$13 -> 12000 | CE8: =MIN(CB8,CD8) -> 0 | CF8: =CD8-CE8 -> 12000 | CG8: =BS8+$G8*(CD8+BS8) -> 0 | CH8: =MIN(CB8-CE8,CG8) -> 0 | CI8: =CG8-CH8 -> 0 | CJ8: =IF($H8=1,MIN(CB8-CE8-CH8,MAX(0,$F8/(1-$F8)*(BX8+CH8)-BY8)),0) -> 0 | CK8: =CB8-CE8-CH8-CJ8 -> 0 | CL8: =CE8+CH8+(1-$F8)*CK8 -> 0 | CM8: =CJ8+$F8*CK8 -> 0 | CN8: =BX8+CH8+(1-$F8)*CK8 -> 0 | CO8: =BY8+CM8 -> 0 | CP8: =CC8+$D8*Inputs!$F$13-$D8*$E8 -> 20022.64 | CQ8: =CP8*(1+$I8) -> 24027.168 | CR8: =CQ8*Inputs!$F$14 -> 0 | CS8: =CQ8-CR8 -> 24027.168 | CT8: =CF8+$D8*Inputs!$F$13 -> 16000 | CU8: =MIN(CR8,CT8) -> 0 | CV8: =CT8-CU8 -> 16000 | CW8: =CI8+$G8*(CT8+CI8) -> 0 | CX8: =MIN(CR8-CU8,CW8) -> 0 | CY8: =CW8-CX8 -> 0 | CZ8: =IF($H8=1,MIN(CR8-CU8-CX8,MAX(0,$F8/(1-$F8)*(CN8+CX8)-CO8)),0) -> 0 | DA8: =CR8-CU8-CX8-CZ8 -> 0 | DB8: =CU8+CX8+(1-$F8)*DA8 -> 0 | DC8: =CZ8+$F8*DA8 -> 0 | DD8: =CN8+CX8+(1-$F8)*DA8 -> 0 | DE8: =CO8+DC8 -> 0 | DF8: =CS8+$D8*Inputs!$G$13-$D8*$E8 -> 27757.168 | DG8: =DF8*(1+$I8) -> 33308.602 | DH8: =DG8*Inputs!$G$14 -> 6661.7203 | DI8: =DG8-DH8 -> 26646.881 | DJ8: =CV8+$D8*Inputs!$G$13 -> 20000 | DK8: =MIN(DH8,DJ8) -> 6661.7203 | DL8: =DJ8-DK8 -> 13338.28 | DM8: =CY8+$G8*(DJ8+CY8) -> 0 | DN8: =MIN(DH8-DK8,DM8) -> 0 | DO8: =DM8-DN8 -> 0 | DP8: =IF($H8=1,MIN(DH8-DK8-DN8,MAX(0,$F8/(1-$F8)*(DD8+DN8)-DE8)),0) -> 0 | DQ8: =DH8-DK8-DN8-DP8 -> 0 | DR8: =DK8+DN8+(1-$F8)*DQ8 -> 6661.7203 | DS8: =DP8+$F8*DQ8 -> 0 | DT8: =DD8+DN8+(1-$F8)*DQ8 -> 0 | DU8: =DE8+DS8 -> 0 | DV8: =DI8+$D8*Inputs!$H$13-$D8*$E8 -> 26376.881 | DW8: =DV8*(1+$I8) -> 31652.258 | DX8: =DW8*Inputs!$H$14 -> 6330.4515 | DY8: =DW8-DX8 -> 25321.806 | DZ8: =DL8+$D8*Inputs!$H$13 -> 13338.28 | EA8: =MIN(DX8,DZ8) -> 6330.4515 | EB8: =DZ8-EA8 -> 7007.8282 | EC8: =DO8+$G8*(DZ8+DO8) -> 0 | ED8: =MIN(DX8-EA8,EC8) -> 0 | EE8: =EC8-ED8 -> 0 | EF8: =IF($H8=1,MIN(DX8-EA8-ED8,MAX(0,$F8/(1-$F8)*(DT8+ED8)-DU8)),0) -> 0 | EG8: =DX8-EA8-ED8-EF8 -> 0 | EH8: =EA8+ED8+(1-$F8)*EG8 -> 6330.4515 | EI8: =EF8+$F8*EG8 -> 0 | EJ8: =DT8+ED8+(1-$F8)*EG8 -> 0 | EK8: =DU8+EI8 -> 0 | EL8: =DY8+$D8*Inputs!$I$13-$D8*$E8 -> 25051.806 | EM8: =EL8*(1+$I8) -> 30062.167 | EN8: =EM8*Inputs!$I$14 -> 6012.4334 | EO8: =EM8-EN8 -> 24049.734 | EP8: =EB8+$D8*Inputs!$I$13 -> 7007.8282 | EQ8: =MIN(EN8,EP8) -> 6012.4334 | ER8: =EP8-EQ8 -> 995.39473 | ES8: =EE8+$G8*(EP8+EE8) -> 0 | ET8: =MIN(EN8-EQ8,ES8) -> 0 | EU8: =ES8-ET8 -> 0 | EV8: =IF($H8=1,MIN(EN8-EQ8-ET8,MAX(0,$F8/(1-$F8)*(EJ8+ET8)-EK8)),0) -> 0 | EW8: =EN8-EQ8-ET8-EV8 -> 0 | EX8: =EQ8+ET8+(1-$F8)*EW8 -> 6012.4334 | EY8: =EV8+$F8*EW8 -> 0 | EZ8: =EJ8+ET8+(1-$F8)*EW8 -> 0 | FA8: =EK8+EY8 -> 0 | FB8: =EO8+$D8*Inputs!$J$13-$D8*$E8 -> 23779.734 | FC8: =FB8*(1+$I8) -> 28535.681 | FD8: =FC8*Inputs!$J$14 -> 5707.1361 | FE8: =FC8-FD8 -> 22828.544 | FF8: =ER8+$D8*Inputs!$J$13 -> 995.39473 | FG8: =MIN(FD8,FF8) -> 995.39473 | FH8: =FF8-FG8 -> 0 | FI8: =EU8+$G8*(FF8+EU8) -> 0 | FJ8: =MIN(FD8-FG8,FI8) -> 0 | FK8: =FI8-FJ8 -> 0 | FL8: =IF($H8=1,MIN(FD8-FG8-FJ8,MAX(0,$F8/(1-$F8)*(EZ8+FJ8)-FA8)),0) -> 0 | FM8: =FD8-FG8-FJ8-FL8 -> 4711.7414 | FN8: =FG8+FJ8+(1-$F8)*FM8 -> 4764.7878 | FO8: =FL8+$F8*FM8 -> 942.34828 | FP8: =EZ8+FJ8+(1-$F8)*FM8 -> 3769.3931 | FQ8: =FA8+FO8 -> 942.34828 | FR8: =FE8+$D8*Inputs!$K$13-$D8*$E8 -> 22558.544 | FS8: =FR8*(1+$I8) -> 27070.253 | FT8: =FS8*Inputs!$K$14 -> 5414.0507 | FU8: =FS8-FT8 -> 21656.203 | FV8: =FH8+$D8*Inputs!$K$13 -> 0 | FW8: =MIN(FT8,FV8) -> 0 | FX8: =FV8-FW8 -> 0 | FY8: =FK8+$G8*(FV8+FK8) -> 0 | FZ8: =MIN(FT8-FW8,FY8) -> 0 | GA8: =FY8-FZ8 -> 0 | GB8: =IF($H8=1,MIN(FT8-FW8-FZ8,MAX(0,$F8/(1-$F8)*(FP8+FZ8)-FQ8)),0) -> 0 | GC8: =FT8-FW8-FZ8-GB8 -> 5414.0507 | GD8: =FW8+FZ8+(1-$F8)*GC8 -> 4331.2405 | GE8: =GB8+$F8*GC8 -> 1082.8101 | GF8: =FP8+FZ8+(1-$F8)*GC8 -> 8100.6336 | GG8: =FQ8+GE8 -> 2025.1584 | GH8: =FU8+$D8*Inputs!$L$13-$D8*$E8 -> 21386.203 | GI8: =GH8*(1+$I8) -> 25663.443 | GJ8: =GI8*Inputs!$L$14 -> 25663.443 | GK8: =GI8-GJ8 -> 0 | GL8: =FX8+$D8*Inputs!$L$13 -> 0 | GM8: =MIN(GJ8,GL8) -> 0 | GN8: =GL8-GM8 -> 0 | GO8: =GA8+$G8*(GL8+GA8) -> 0 | GP8: =MIN(GJ8-GM8,GO8) -> 0 | GQ8: =GO8-GP8 -> 0 | GR8: =IF($H8=1,MIN(GJ8-GM8-GP8,MAX(0,$F8/(1-$F8)*(GF8+GP8)-GG8)),0) -> 0 | GS8: =GJ8-GM8-GP8-GR8 -> 25663.443 | GT8: =GM8+GP8+(1-$F8)*GS8 -> 20530.755 | GU8: =GR8+$F8*GS8 -> 5132.6886 | GV8: =GF8+GP8+(1-$F8)*GS8 -> 28631.388 | GW8: =GG8+GU8 -> 7157.847
A9: M3 | B9: Offer + 8% hard hurdle | D9: =Inputs!$C$6 -> 20000 | E9: =Inputs!$C$19 -> 0.0135 | F9: =Inputs!$C$20 -> 0.2 | G9: =Inputs!$C$22 -> 0.08 | H9: 0 | I9: =Inputs!$C$8 -> 0.2 | J9: =Inputs!$C$9 -> 0.15 | K9: =IRR(W9:AG9,0.1) -> 0.16591822 | L9: =W9+NPV($J9,X9:AG9) -> 1303.5385 | M9: =SUM(BF9,BV9,CL9,DB9,DR9,EH9,EX9,FN9,GD9,GT9) -> 50426.835 | N9: =IF($D9*SUM(Inputs!$C$13:$L$13)=0,0,M9/($D9*SUM(Inputs!$C$13:$L$13))) -> 2.5213418 | O9: =$D9*$E9*COLUMNS(Inputs!$C$13:$L$13) -> 2700 | P9: =SUM(BG9,BW9,CM9,DC9,DS9,EI9,EY9,FO9,GE9,GU9) -> 5362.4 | Q9: =PV($J9,COLUMNS(Inputs!$C$13:$L$13),-$D9*$E9,0,1) -> 1558.3277 | R9: =NPV($J9,BG9,BW9,CM9,DC9,DS9,EI9,EY9,FO9,GE9,GU9) -> 1334.0204 | S9: =Q9+R9 -> 2892.3481 | T9: =IF(S9=0,0,Q9/S9) -> 0.53877597 | U9: =ROUND(ABS(GK9)+ABS(SUM(AV9,BL9,CB9,CR9,DH9,DX9,EN9,FD9,FT9,GJ9)-M9-P9)+ABS(S9-(AH9+NPV($J9,AI9:AR9))),6) -> 0 | W9: =-$D9*Inputs!$C$13 -> -4000 | X9: =BF9-$D9*Inputs!$D$13 -> -4000 | Y9: =BV9-$D9*Inputs!$E$13 -> -4000 | Z9: =CL9-$D9*Inputs!$F$13 -> -4000 | AA9: =DB9-$D9*Inputs!$G$13 -> -4000 | AB9: =DR9-$D9*Inputs!$H$13 -> 6661.7203 | AC9: =EH9-$D9*Inputs!$I$13 -> 6330.4515 | AD9: =EX9-$D9*Inputs!$J$13 -> 6012.4334 | AE9: =FN9-$D9*Inputs!$K$13 -> 5707.1361 | AF9: =GD9-$D9*Inputs!$L$13 -> 5184.3393 | AG9: =GT9 -> 20530.755 | AH9: =$D9*$E9 -> 270 | AI9: =BG9+$D9*$E9 -> 270 | AJ9: =BW9+$D9*$E9 -> 270 | AK9: =CM9+$D9*$E9 -> 270 | AL9: =DC9+$D9*$E9 -> 270 | AM9: =DS9+$D9*$E9 -> 270 | AN9: =EI9+$D9*$E9 -> 270 | AO9: =EY9+$D9*$E9 -> 270 | AP9: =FO9+$D9*$E9 -> 270 | AQ9: =GE9+$D9*$E9 -> 499.71134 | AR9: =GU9 -> 5132.6886 | AT9: =$D9*Inputs!$C$13-$D9*$E9 -> 3730 | AU9: =AT9*(1+$I9) -> 4476 | AV9: =AU9*Inputs!$C$14 -> 0 | AW9: =AU9-AV9 -> 4476 | AX9: =$D9*Inputs!$C$13 -> 4000 | AY9: =MIN(AV9,AX9) -> 0 | AZ9: =AX9-AY9 -> 4000 | BA9: =$G9*AX9 -> 320 | BB9: =MIN(AV9-AY9,BA9) -> 0 | BC9: =BA9-BB9 -> 320 | BD9: =IF($H9=1,MIN(AV9-AY9-BB9,MAX(0,$F9/(1-$F9)*BB9)),0) -> 0 | BE9: =AV9-AY9-BB9-BD9 -> 0 | BF9: =AY9+BB9+(1-$F9)*BE9 -> 0 | BG9: =BD9+$F9*BE9 -> 0 | BH9: =BB9+(1-$F9)*BE9 -> 0 | BI9: =BG9 -> 0 | BJ9: =AW9+$D9*Inputs!$D$13-$D9*$E9 -> 8206 | BK9: =BJ9*(1+$I9) -> 9847.2 | BL9: =BK9*Inputs!$D$14 -> 0 | BM9: =BK9-BL9 -> 9847.2 | BN9: =AZ9+$D9*Inputs!$D$13 -> 8000 | BO9: =MIN(BL9,BN9) -> 0 | BP9: =BN9-BO9 -> 8000 | BQ9: =BC9+$G9*(BN9+BC9) -> 985.6 | BR9: =MIN(BL9-BO9,BQ9) -> 0 | BS9: =BQ9-BR9 -> 985.6 | BT9: =IF($H9=1,MIN(BL9-BO9-BR9,MAX(0,$F9/(1-$F9)*(BH9+BR9)-BI9)),0) -> 0 | BU9: =BL9-BO9-BR9-BT9 -> 0 | BV9: =BO9+BR9+(1-$F9)*BU9 -> 0 | BW9: =BT9+$F9*BU9 -> 0 | BX9: =BH9+BR9+(1-$F9)*BU9 -> 0 | BY9: =BI9+BW9 -> 0 | BZ9: =BM9+$D9*Inputs!$E$13-$D9*$E9 -> 13577.2 | CA9: =BZ9*(1+$I9) -> 16292.64 | CB9: =CA9*Inputs!$E$14 -> 0 | CC9: =CA9-CB9 -> 16292.64 | CD9: =BP9+$D9*Inputs!$E$13 -> 12000 | CE9: =MIN(CB9,CD9) -> 0 | CF9: =CD9-CE9 -> 12000 | CG9: =BS9+$G9*(CD9+BS9) -> 2024.448 | CH9: =MIN(CB9-CE9,CG9) -> 0 | CI9: =CG9-CH9 -> 2024.448 | CJ9: =IF($H9=1,MIN(CB9-CE9-CH9,MAX(0,$F9/(1-$F9)*(BX9+CH9)-BY9)),0) -> 0 | CK9: =CB9-CE9-CH9-CJ9 -> 0 | CL9: =CE9+CH9+(1-$F9)*CK9 -> 0 | CM9: =CJ9+$F9*CK9 -> 0 | CN9: =BX9+CH9+(1-$F9)*CK9 -> 0 | CO9: =BY9+CM9 -> 0 | CP9: =CC9+$D9*Inputs!$F$13-$D9*$E9 -> 20022.64 | CQ9: =CP9*(1+$I9) -> 24027.168 | CR9: =CQ9*Inputs!$F$14 -> 0 | CS9: =CQ9-CR9 -> 24027.168 | CT9: =CF9+$D9*Inputs!$F$13 -> 16000 | CU9: =MIN(CR9,CT9) -> 0 | CV9: =CT9-CU9 -> 16000 | CW9: =CI9+$G9*(CT9+CI9) -> 3466.4038 | CX9: =MIN(CR9-CU9,CW9) -> 0 | CY9: =CW9-CX9 -> 3466.4038 | CZ9: =IF($H9=1,MIN(CR9-CU9-CX9,MAX(0,$F9/(1-$F9)*(CN9+CX9)-CO9)),0) -> 0 | DA9: =CR9-CU9-CX9-CZ9 -> 0 | DB9: =CU9+CX9+(1-$F9)*DA9 -> 0 | DC9: =CZ9+$F9*DA9 -> 0 | DD9: =CN9+CX9+(1-$F9)*DA9 -> 0 | DE9: =CO9+DC9 -> 0 | DF9: =CS9+$D9*Inputs!$G$13-$D9*$E9 -> 27757.168 | DG9: =DF9*(1+$I9) -> 33308.602 | DH9: =DG9*Inputs!$G$14 -> 6661.7203 | DI9: =DG9-DH9 -> 26646.881 | DJ9: =CV9+$D9*Inputs!$G$13 -> 20000 | DK9: =MIN(DH9,DJ9) -> 6661.7203 | DL9: =DJ9-DK9 -> 13338.28 | DM9: =CY9+$G9*(DJ9+CY9) -> 5343.7161 | DN9: =MIN(DH9-DK9,DM9) -> 0 | DO9: =DM9-DN9 -> 5343.7161 | DP9: =IF($H9=1,MIN(DH9-DK9-DN9,MAX(0,$F9/(1-$F9)*(DD9+DN9)-DE9)),0) -> 0 | DQ9: =DH9-DK9-DN9-DP9 -> 0 | DR9: =DK9+DN9+(1-$F9)*DQ9 -> 6661.7203 | DS9: =DP9+$F9*DQ9 -> 0 | DT9: =DD9+DN9+(1-$F9)*DQ9 -> 0 | DU9: =DE9+DS9 -> 0 | DV9: =DI9+$D9*Inputs!$H$13-$D9*$E9 -> 26376.881 | DW9: =DV9*(1+$I9) -> 31652.258 | DX9: =DW9*Inputs!$H$14 -> 6330.4515 | DY9: =DW9-DX9 -> 25321.806 | DZ9: =DL9+$D9*Inputs!$H$13 -> 13338.28 | EA9: =MIN(DX9,DZ9) -> 6330.4515 | EB9: =DZ9-EA9 -> 7007.8282 | EC9: =DO9+$G9*(DZ9+DO9) -> 6838.2758 | ED9: =MIN(DX9-EA9,EC9) -> 0 | EE9: =EC9-ED9 -> 6838.2758 | EF9: =IF($H9=1,MIN(DX9-EA9-ED9,MAX(0,$F9/(1-$F9)*(DT9+ED9)-DU9)),0) -> 0 | EG9: =DX9-EA9-ED9-EF9 -> 0 | EH9: =EA9+ED9+(1-$F9)*EG9 -> 6330.4515 | EI9: =EF9+$F9*EG9 -> 0 | EJ9: =DT9+ED9+(1-$F9)*EG9 -> 0 | EK9: =DU9+EI9 -> 0 | EL9: =DY9+$D9*Inputs!$I$13-$D9*$E9 -> 25051.806 | EM9: =EL9*(1+$I9) -> 30062.167 | EN9: =EM9*Inputs!$I$14 -> 6012.4334 | EO9: =EM9-EN9 -> 24049.734 | EP9: =EB9+$D9*Inputs!$I$13 -> 7007.8282 | EQ9: =MIN(EN9,EP9) -> 6012.4334 | ER9: =EP9-EQ9 -> 995.39473 | ES9: =EE9+$G9*(EP9+EE9) -> 7945.9641 | ET9: =MIN(EN9-EQ9,ES9) -> 0 | EU9: =ES9-ET9 -> 7945.9641 | EV9: =IF($H9=1,MIN(EN9-EQ9-ET9,MAX(0,$F9/(1-$F9)*(EJ9+ET9)-EK9)),0) -> 0 | EW9: =EN9-EQ9-ET9-EV9 -> 0 | EX9: =EQ9+ET9+(1-$F9)*EW9 -> 6012.4334 | EY9: =EV9+$F9*EW9 -> 0 | EZ9: =EJ9+ET9+(1-$F9)*EW9 -> 0 | FA9: =EK9+EY9 -> 0 | FB9: =EO9+$D9*Inputs!$J$13-$D9*$E9 -> 23779.734 | FC9: =FB9*(1+$I9) -> 28535.681 | FD9: =FC9*Inputs!$J$14 -> 5707.1361 | FE9: =FC9-FD9 -> 22828.544 | FF9: =ER9+$D9*Inputs!$J$13 -> 995.39473 | FG9: =MIN(FD9,FF9) -> 995.39473 | FH9: =FF9-FG9 -> 0 | FI9: =EU9+$G9*(FF9+EU9) -> 8661.2728 | FJ9: =MIN(FD9-FG9,FI9) -> 4711.7414 | FK9: =FI9-FJ9 -> 3949.5315 | FL9: =IF($H9=1,MIN(FD9-FG9-FJ9,MAX(0,$F9/(1-$F9)*(EZ9+FJ9)-FA9)),0) -> 0 | FM9: =FD9-FG9-FJ9-FL9 -> 0 | FN9: =FG9+FJ9+(1-$F9)*FM9 -> 5707.1361 | FO9: =FL9+$F9*FM9 -> 0 | FP9: =EZ9+FJ9+(1-$F9)*FM9 -> 4711.7414 | FQ9: =FA9+FO9 -> 0 | FR9: =FE9+$D9*Inputs!$K$13-$D9*$E9 -> 22558.544 | FS9: =FR9*(1+$I9) -> 27070.253 | FT9: =FS9*Inputs!$K$14 -> 5414.0507 | FU9: =FS9-FT9 -> 21656.203 | FV9: =FH9+$D9*Inputs!$K$13 -> 0 | FW9: =MIN(FT9,FV9) -> 0 | FX9: =FV9-FW9 -> 0 | FY9: =FK9+$G9*(FV9+FK9) -> 4265.494 | FZ9: =MIN(FT9-FW9,FY9) -> 4265.494 | GA9: =FY9-FZ9 -> 0 | GB9: =IF($H9=1,MIN(FT9-FW9-FZ9,MAX(0,$F9/(1-$F9)*(FP9+FZ9)-FQ9)),0) -> 0 | GC9: =FT9-FW9-FZ9-GB9 -> 1148.5567 | GD9: =FW9+FZ9+(1-$F9)*GC9 -> 5184.3393 | GE9: =GB9+$F9*GC9 -> 229.71134 | GF9: =FP9+FZ9+(1-$F9)*GC9 -> 9896.0807 | GG9: =FQ9+GE9 -> 229.71134 | GH9: =FU9+$D9*Inputs!$L$13-$D9*$E9 -> 21386.203 | GI9: =GH9*(1+$I9) -> 25663.443 | GJ9: =GI9*Inputs!$L$14 -> 25663.443 | GK9: =GI9-GJ9 -> 0 | GL9: =FX9+$D9*Inputs!$L$13 -> 0 | GM9: =MIN(GJ9,GL9) -> 0 | GN9: =GL9-GM9 -> 0 | GO9: =GA9+$G9*(GL9+GA9) -> 0 | GP9: =MIN(GJ9-GM9,GO9) -> 0 | GQ9: =GO9-GP9 -> 0 | GR9: =IF($H9=1,MIN(GJ9-GM9-GP9,MAX(0,$F9/(1-$F9)*(GF9+GP9)-GG9)),0) -> 0 | GS9: =GJ9-GM9-GP9-GR9 -> 25663.443 | GT9: =GM9+GP9+(1-$F9)*GS9 -> 20530.755 | GU9: =GR9+$F9*GS9 -> 5132.6886 | GV9: =GF9+GP9+(1-$F9)*GS9 -> 30426.835 | GW9: =GG9+GU9 -> 5362.4
A10: M4 | B10: Offer + 8% soft hurdle (100% catch-up) | D10: =Inputs!$C$6 -> 20000 | E10: =Inputs!$C$19 -> 0.0135 | F10: =Inputs!$C$20 -> 0.2 | G10: =Inputs!$C$22 -> 0.08 | H10: =Inputs!$C$23 -> 1 | I10: =Inputs!$C$8 -> 0.2 | J10: =Inputs!$C$9 -> 0.15 | K10: =IRR(W10:AG10,0.1) -> 0.16029224 | L10: =W10+NPV($J10,X10:AG10) -> 825.66274 | M10: =SUM(BF10,BV10,CL10,DB10,DR10,EH10,EX10,FN10,GD10,GT10) -> 48631.388 | N10: =IF($D10*SUM(Inputs!$C$13:$L$13)=0,0,M10/($D10*SUM(Inputs!$C$13:$L$13))) -> 2.4315694 | O10: =$D10*$E10*COLUMNS(Inputs!$C$13:$L$13) -> 2700 | P10: =SUM(BG10,BW10,CM10,DC10,DS10,EI10,EY10,FO10,GE10,GU10) -> 7157.847 | Q10: =PV($J10,COLUMNS(Inputs!$C$13:$L$13),-$D10*$E10,0,1) -> 1558.3277 | R10: =NPV($J10,BG10,BW10,CM10,DC10,DS10,EI10,EY10,FO10,GE10,GU10) -> 1811.8962 | S10: =Q10+R10 -> 3370.2238 | T10: =IF(S10=0,0,Q10/S10) -> 0.46238106 | U10: =ROUND(ABS(GK10)+ABS(SUM(AV10,BL10,CB10,CR10,DH10,DX10,EN10,FD10,FT10,GJ10)-M10-P10)+ABS(S10-(AH10+NPV($J10,AI10:AR10))),6) -> 0 | W10: =-$D10*Inputs!$C$13 -> -4000 | X10: =BF10-$D10*Inputs!$D$13 -> -4000 | Y10: =BV10-$D10*Inputs!$E$13 -> -4000 | Z10: =CL10-$D10*Inputs!$F$13 -> -4000 | AA10: =DB10-$D10*Inputs!$G$13 -> -4000 | AB10: =DR10-$D10*Inputs!$H$13 -> 6661.7203 | AC10: =EH10-$D10*Inputs!$I$13 -> 6330.4515 | AD10: =EX10-$D10*Inputs!$J$13 -> 6012.4334 | AE10: =FN10-$D10*Inputs!$K$13 -> 5707.1361 | AF10: =GD10-$D10*Inputs!$L$13 -> 4265.494 | AG10: =GT10 -> 19654.153 | AH10: =$D10*$E10 -> 270 | AI10: =BG10+$D10*$E10 -> 270 | AJ10: =BW10+$D10*$E10 -> 270 | AK10: =CM10+$D10*$E10 -> 270 | AL10: =DC10+$D10*$E10 -> 270 | AM10: =DS10+$D10*$E10 -> 270 | AN10: =EI10+$D10*$E10 -> 270 | AO10: =EY10+$D10*$E10 -> 270 | AP10: =FO10+$D10*$E10 -> 270 | AQ10: =GE10+$D10*$E10 -> 1418.5567 | AR10: =GU10 -> 6009.2904 | AT10: =$D10*Inputs!$C$13-$D10*$E10 -> 3730 | AU10: =AT10*(1+$I10) -> 4476 | AV10: =AU10*Inputs!$C$14 -> 0 | AW10: =AU10-AV10 -> 4476 | AX10: =$D10*Inputs!$C$13 -> 4000 | AY10: =MIN(AV10,AX10) -> 0 | AZ10: =AX10-AY10 -> 4000 | BA10: =$G10*AX10 -> 320 | BB10: =MIN(AV10-AY10,BA10) -> 0 | BC10: =BA10-BB10 -> 320 | BD10: =IF($H10=1,MIN(AV10-AY10-BB10,MAX(0,$F10/(1-$F10)*BB10)),0) -> 0 | BE10: =AV10-AY10-BB10-BD10 -> 0 | BF10: =AY10+BB10+(1-$F10)*BE10 -> 0 | BG10: =BD10+$F10*BE10 -> 0 | BH10: =BB10+(1-$F10)*BE10 -> 0 | BI10: =BG10 -> 0 | BJ10: =AW10+$D10*Inputs!$D$13-$D10*$E10 -> 8206 | BK10: =BJ10*(1+$I10) -> 9847.2 | BL10: =BK10*Inputs!$D$14 -> 0 | BM10: =BK10-BL10 -> 9847.2 | BN10: =AZ10+$D10*Inputs!$D$13 -> 8000 | BO10: =MIN(BL10,BN10) -> 0 | BP10: =BN10-BO10 -> 8000 | BQ10: =BC10+$G10*(BN10+BC10) -> 985.6 | BR10: =MIN(BL10-BO10,BQ10) -> 0 | BS10: =BQ10-BR10 -> 985.6 | BT10: =IF($H10=1,MIN(BL10-BO10-BR10,MAX(0,$F10/(1-$F10)*(BH10+BR10)-BI10)),0) -> 0 | BU10: =BL10-BO10-BR10-BT10 -> 0 | BV10: =BO10+BR10+(1-$F10)*BU10 -> 0 | BW10: =BT10+$F10*BU10 -> 0 | BX10: =BH10+BR10+(1-$F10)*BU10 -> 0 | BY10: =BI10+BW10 -> 0 | BZ10: =BM10+$D10*Inputs!$E$13-$D10*$E10 -> 13577.2 | CA10: =BZ10*(1+$I10) -> 16292.64 | CB10: =CA10*Inputs!$E$14 -> 0 | CC10: =CA10-CB10 -> 16292.64 | CD10: =BP10+$D10*Inputs!$E$13 -> 12000 | CE10: =MIN(CB10,CD10) -> 0 | CF10: =CD10-CE10 -> 12000 | CG10: =BS10+$G10*(CD10+BS10) -> 2024.448 | CH10: =MIN(CB10-CE10,CG10) -> 0 | CI10: =CG10-CH10 -> 2024.448 | CJ10: =IF($H10=1,MIN(CB10-CE10-CH10,MAX(0,$F10/(1-$F10)*(BX10+CH10)-BY10)),0) -> 0 | CK10: =CB10-CE10-CH10-CJ10 -> 0 | CL10: =CE10+CH10+(1-$F10)*CK10 -> 0 | CM10: =CJ10+$F10*CK10 -> 0 | CN10: =BX10+CH10+(1-$F10)*CK10 -> 0 | CO10: =BY10+CM10 -> 0 | CP10: =CC10+$D10*Inputs!$F$13-$D10*$E10 -> 20022.64 | CQ10: =CP10*(1+$I10) -> 24027.168 | CR10: =CQ10*Inputs!$F$14 -> 0 | CS10: =CQ10-CR10 -> 24027.168 | CT10: =CF10+$D10*Inputs!$F$13 -> 16000 | CU10: =MIN(CR10,CT10) -> 0 | CV10: =CT10-CU10 -> 16000 | CW10: =CI10+$G10*(CT10+CI10) -> 3466.4038 | CX10: =MIN(CR10-CU10,CW10) -> 0 | CY10: =CW10-CX10 -> 3466.4038 | CZ10: =IF($H10=1,MIN(CR10-CU10-CX10,MAX(0,$F10/(1-$F10)*(CN10+CX10)-CO10)),0) -> 0 | DA10: =CR10-CU10-CX10-CZ10 -> 0 | DB10: =CU10+CX10+(1-$F10)*DA10 -> 0 | DC10: =CZ10+$F10*DA10 -> 0 | DD10: =CN10+CX10+(1-$F10)*DA10 -> 0 | DE10: =CO10+DC10 -> 0 | DF10: =CS10+$D10*Inputs!$G$13-$D10*$E10 -> 27757.168 | DG10: =DF10*(1+$I10) -> 33308.602 | DH10: =DG10*Inputs!$G$14 -> 6661.7203 | DI10: =DG10-DH10 -> 26646.881 | DJ10: =CV10+$D10*Inputs!$G$13 -> 20000 | DK10: =MIN(DH10,DJ10) -> 6661.7203 | DL10: =DJ10-DK10 -> 13338.28 | DM10: =CY10+$G10*(DJ10+CY10) -> 5343.7161 | DN10: =MIN(DH10-DK10,DM10) -> 0 | DO10: =DM10-DN10 -> 5343.7161 | DP10: =IF($H10=1,MIN(DH10-DK10-DN10,MAX(0,$F10/(1-$F10)*(DD10+DN10)-DE10)),0) -> 0 | DQ10: =DH10-DK10-DN10-DP10 -> 0 | DR10: =DK10+DN10+(1-$F10)*DQ10 -> 6661.7203 | DS10: =DP10+$F10*DQ10 -> 0 | DT10: =DD10+DN10+(1-$F10)*DQ10 -> 0 | DU10: =DE10+DS10 -> 0 | DV10: =DI10+$D10*Inputs!$H$13-$D10*$E10 -> 26376.881 | DW10: =DV10*(1+$I10) -> 31652.258 | DX10: =DW10*Inputs!$H$14 -> 6330.4515 | DY10: =DW10-DX10 -> 25321.806 | DZ10: =DL10+$D10*Inputs!$H$13 -> 13338.28 | EA10: =MIN(DX10,DZ10) -> 6330.4515 | EB10: =DZ10-EA10 -> 7007.8282 | EC10: =DO10+$G10*(DZ10+DO10) -> 6838.2758 | ED10: =MIN(DX10-EA10,EC10) -> 0 | EE10: =EC10-ED10 -> 6838.2758 | EF10: =IF($H10=1,MIN(DX10-EA10-ED10,MAX(0,$F10/(1-$F10)*(DT10+ED10)-DU10)),0) -> 0 | EG10: =DX10-EA10-ED10-EF10 -> 0 | EH10: =EA10+ED10+(1-$F10)*EG10 -> 6330.4515 | EI10: =EF10+$F10*EG10 -> 0 | EJ10: =DT10+ED10+(1-$F10)*EG10 -> 0 | EK10: =DU10+EI10 -> 0 | EL10: =DY10+$D10*Inputs!$I$13-$D10*$E10 -> 25051.806 | EM10: =EL10*(1+$I10) -> 30062.167 | EN10: =EM10*Inputs!$I$14 -> 6012.4334 | EO10: =EM10-EN10 -> 24049.734 | EP10: =EB10+$D10*Inputs!$I$13 -> 7007.8282 | EQ10: =MIN(EN10,EP10) -> 6012.4334 | ER10: =EP10-EQ10 -> 995.39473 | ES10: =EE10+$G10*(EP10+EE10) -> 7945.9641 | ET10: =MIN(EN10-EQ10,ES10) -> 0 | EU10: =ES10-ET10 -> 7945.9641 | EV10: =IF($H10=1,MIN(EN10-EQ10-ET10,MAX(0,$F10/(1-$F10)*(EJ10+ET10)-EK10)),0) -> 0 | EW10: =EN10-EQ10-ET10-EV10 -> 0 | EX10: =EQ10+ET10+(1-$F10)*EW10 -> 6012.4334 | EY10: =EV10+$F10*EW10 -> 0 | EZ10: =EJ10+ET10+(1-$F10)*EW10 -> 0 | FA10: =EK10+EY10 -> 0 | FB10: =EO10+$D10*Inputs!$J$13-$D10*$E10 -> 23779.734 | FC10: =FB10*(1+$I10) -> 28535.681 | FD10: =FC10*Inputs!$J$14 -> 5707.1361 | FE10: =FC10-FD10 -> 22828.544 | FF10: =ER10+$D10*Inputs!$J$13 -> 995.39473 | FG10: =MIN(FD10,FF10) -> 995.39473 | FH10: =FF10-FG10 -> 0 | FI10: =EU10+$G10*(FF10+EU10) -> 8661.2728 | FJ10: =MIN(FD10-FG10,FI10) -> 4711.7414 | FK10: =FI10-FJ10 -> 3949.5315 | FL10: =IF($H10=1,MIN(FD10-FG10-FJ10,MAX(0,$F10/(1-$F10)*(EZ10+FJ10)-FA10)),0) -> 0 | FM10: =FD10-FG10-FJ10-FL10 -> 0 | FN10: =FG10+FJ10+(1-$F10)*FM10 -> 5707.1361 | FO10: =FL10+$F10*FM10 -> 0 | FP10: =EZ10+FJ10+(1-$F10)*FM10 -> 4711.7414 | FQ10: =FA10+FO10 -> 0 | FR10: =FE10+$D10*Inputs!$K$13-$D10*$E10 -> 22558.544 | FS10: =FR10*(1+$I10) -> 27070.253 | FT10: =FS10*Inputs!$K$14 -> 5414.0507 | FU10: =FS10-FT10 -> 21656.203 | FV10: =FH10+$D10*Inputs!$K$13 -> 0 | FW10: =MIN(FT10,FV10) -> 0 | FX10: =FV10-FW10 -> 0 | FY10: =FK10+$G10*(FV10+FK10) -> 4265.494 | FZ10: =MIN(FT10-FW10,FY10) -> 4265.494 | GA10: =FY10-FZ10 -> 0 | GB10: =IF($H10=1,MIN(FT10-FW10-FZ10,MAX(0,$F10/(1-$F10)*(FP10+FZ10)-FQ10)),0) -> 1148.5567 | GC10: =FT10-FW10-FZ10-GB10 -> 0 | GD10: =FW10+FZ10+(1-$F10)*GC10 -> 4265.494 | GE10: =GB10+$F10*GC10 -> 1148.5567 | GF10: =FP10+FZ10+(1-$F10)*GC10 -> 8977.2354 | GG10: =FQ10+GE10 -> 1148.5567 | GH10: =FU10+$D10*Inputs!$L$13-$D10*$E10 -> 21386.203 | GI10: =GH10*(1+$I10) -> 25663.443 | GJ10: =GI10*Inputs!$L$14 -> 25663.443 | GK10: =GI10-GJ10 -> 0 | GL10: =FX10+$D10*Inputs!$L$13 -> 0 | GM10: =MIN(GJ10,GL10) -> 0 | GN10: =GL10-GM10 -> 0 | GO10: =GA10+$G10*(GL10+GA10) -> 0 | GP10: =MIN(GJ10-GM10,GO10) -> 0 | GQ10: =GO10-GP10 -> 0 | GR10: =IF($H10=1,MIN(GJ10-GM10-GP10,MAX(0,$F10/(1-$F10)*(GF10+GP10)-GG10)),0) -> 1095.7521 | GS10: =GJ10-GM10-GP10-GR10 -> 24567.691 | GT10: =GM10+GP10+(1-$F10)*GS10 -> 19654.153 | GU10: =GR10+$F10*GS10 -> 6009.2904 | GV10: =GF10+GP10+(1-$F10)*GS10 -> 28631.388 | GW10: =GG10+GU10 -> 7157.847
